Workbook
Name p_bulan: Metode_Catatan!$C$6
Name p_listing_rendah: Metode_Catatan!$C$8
Name p_nilai_besar: Metode_Catatan!$C$7

Sheet Dashboard
B2: Dashboard Ekspor Indonesia 2025 | V2: PERIODE DATA
B3: Ekspor nasional per kode HS (Jan–Nov 2025) dan direktori eksportir terdaftar — seluruh angka dihitung dengan rumus dari sheet data | V3: Jan – Nov 2025
B6: TOTAL EKSPOR NASIONAL (US$ MILIAR) | F6: VOLUME EKSPOR (JUTA TON) | J6: KONSENTRASI TOP 10 KODE HS | N6: EKSPORTIR TERDAFTAR | R6: CAKUPAN KODE HS DI DIREKTORI | V6: LISTING BERESTIMASI TIDAK WAJAR
B7: =Ringkasan!$D$28 -> 234.62961 | F7: =Ringkasan!$D$29 -> 240.12678 | J7: =Ringkasan!$D$34 -> 0.26886351 | N7: =Ringkasan!$D$42 -> 773 | R7: =Ringkasan!$D$46 -> 0.063886857 | V7: =Ringkasan!$D$53 -> 0.27282303
B8: ="Jan–Nov 2025 · "&FIXED(Ringkasan!$D$31,0)&" kode HS aktif" -> Jan–Nov 2025 · 8,202 kode HS aktif | F8: ="Harga rata-rata US$ "&ROUND(Ringkasan!$D$30,2)&" per kg" -> Harga rata-rata US$ 0.96 per kg | J8: ="Top 100 HS = "&ROUND(Ringkasan!$D$36*100,1)&"%"&" dari nilai ekspor" -> Top 100 HS = 65.6% dari nilai ekspor | N8: =FIXED(Ringkasan!$D$43,0)&" listing · "&ROUND(Ringkasan!$D$44,1)&" per perusahaan" -> 3,400 listing · 4.4 per perusahaan | R8: ="Mewakili "&ROUND(Ringkasan!$D$47*100,1)&"%"&" nilai ekspor" -> Mewakili 11.7% nilai ekspor | V8: ="Klaim melebihi ekspor nasional HS-nya" -> Klaim melebihi ekspor nasional HS-nya
B10: TEMUAN UTAMA
B11: Ekspor sangat terkonsentrasi | J11: Direktori belum mewakili ekspor | R11: Estimasi pendapatan menyesatkan
B12: ="Top 10 HS = "&ROUND(Ringkasan!$D$34*100,1)&"%"&" nilai ekspor; Top 100 = "&ROUND(Ringkasan!$D$36*100,1)&"%"&". Bab terbesar: "&Ringkasan!$D$32&" ("&ROUND(Ringkasan!$D$33*100,1)&"%"&"). Barang < US$ 1/kg = "&ROUND(Ringkasan!$D$39*100,0)&"% volume tetapi hanya "&ROUND(Ringkasan!$D$38*100,0)&"% nilai." -> Top 10 HS = 26.9% nilai ekspor; Top 100 = 65.6%. Bab terbesar: 15 · Lemak & minyak nabati/hewani (13%). Barang < US$ 1/kg = 72% volume tetapi hanya 18% nilai. | J12: ="Hanya "&FIXED(Ringkasan!$D$45,0)&" dari "&FIXED(Ringkasan!$D$31,0)&" kode HS aktif ada di direktori (≈"&ROUND(Ringkasan!$D$47*100,1)&"%"&" nilai ekspor). "&FIXED(Ringkasan!$D$49,0)&" HS bernilai besar belum punya listing, senilai "&ROUND(Ringkasan!$D$50*100,1)&"%"&" ekspor nasional." -> Hanya 524 dari 8,202 kode HS aktif ada di direktori (≈11.7% nilai ekspor). 1,187 HS bernilai besar belum punya listing, senilai 85.7% ekspor nasional. | R12: =FIXED(Ringkasan!$D$52,0)&" listing ("&ROUND(Ringkasan!$D$53*100,1)&"%"&") mengklaim pendapatan di atas ekspor nasional HS-nya dan menyumbang "&ROUND(Ringkasan!$D$56*100,0)&"% total estimasi. Yang wajar hanya US$ "&ROUND(Ringkasan!$D$55,2)&" dari US$ "&ROUND(Ringkasan!$D$54,1)&" miliar/bulan." -> 777 listing (27.3%) mengklaim pendapatan di atas ekspor nasional HS-nya dan menyumbang 95% total estimasi. Yang wajar hanya US$ 0.69 dari US$ 13 miliar/bulan.
B17: ANALISIS EKSPOR NASIONAL
B52: DIREKTORI EKSPORTIR & KUALITAS DATA
B87: 10 KODE HS PRIORITAS: NILAI EKSPOR TINGGI, KETERWAKILAN RENDAH
B88: # | C88: KODE HS | F88: DESKRIPSI | N88: BAB | R88: NILAI FOB (US$ JUTA) | T88: LISTING | V88: STATUS
B89: =Celah_Pasokan!A9 -> 1 | C89: =Celah_Pasokan!B9 -> 72026000 | F89: =Celah_Pasokan!C9 -> Ferro-nickel | N89: =Celah_Pasokan!E9 -> Besi & baja | R89: =Celah_Pasokan!F9 -> 14941.058 | T89: =Celah_Pasokan!H9 -> 0 | V89: =Celah_Pasokan!I9 -> Belum terwakili
B90: =Celah_Pasokan!A10 -> 2 | C90: =Celah_Pasokan!B10 -> 15119037 | F90: =Celah_Pasokan!C10 -> Liquid fractions of palm oil, refined oil, but not chemically modified, with iodine value 55 or more, but less than 60 | N90: =Celah_Pasokan!E10 -> Lemak & minyak nabati/hewani | R90: =Celah_Pasokan!F10 -> 9998.5251 | T90: =Celah_Pasokan!H10 -> 0 | V90: =Celah_Pasokan!I10 -> Belum terwakili
B91: =Celah_Pasokan!A11 -> 3 | C91: =Celah_Pasokan!B11 -> 71131990 | F91: =Celah_Pasokan!C11 -> Articles of other precious metal jewellery (other than its parts), other than of silver, whether or not plated or clad with precious metal | N91: =Celah_Pasokan!E11 -> Mutiara, permata & logam mulia | R91: =Celah_Pasokan!F11 -> 6753.5157 | T91: =Celah_Pasokan!H11 -> 0 | V91: =Celah_Pasokan!I11 -> Belum terwakili
B92: =Celah_Pasokan!A12 -> 4 | C92: =Celah_Pasokan!B12 -> 15119020 | F92: =Celah_Pasokan!C12 -> Refined palm oil | N92: =Celah_Pasokan!E12 -> Lemak & minyak nabati/hewani | R92: =Celah_Pasokan!F12 -> 5248.687 | T92: =Celah_Pasokan!H12 -> 0 | V92: =Celah_Pasokan!I12 -> Belum terwakili
B93: =Celah_Pasokan!A13 -> 5 | C93: =Celah_Pasokan!B13 -> 27021000 | F93: =Celah_Pasokan!C13 -> Lignite, whether or not pulverised, but not agglomerated | N93: =Celah_Pasokan!E13 -> Batubara, migas & bahan bakar | R93: =Celah_Pasokan!F13 -> 5051.5174 | T93: =Celah_Pasokan!H13 -> 0 | V93: =Celah_Pasokan!I13 -> Belum terwakili
B94: =Celah_Pasokan!A14 -> 6 | C94: =Celah_Pasokan!B14 -> 27111100 | F94: =Celah_Pasokan!C14 -> Liquefied, natural gas | N94: =Celah_Pasokan!E14 -> Batubara, migas & bahan bakar | R94: =Celah_Pasokan!F14 -> 4966.8666 | T94: =Celah_Pasokan!H14 -> 0 | V94: =Celah_Pasokan!I14 -> Belum terwakili
B95: =Celah_Pasokan!A15 -> 7 | C95: =Celah_Pasokan!B15 -> 75012000 | F95: =Celah_Pasokan!C15 -> Nickel oxide sinters and other intermediate products; of nickel metallurgy | N95: =Celah_Pasokan!E15 -> Nikel | R95: =Celah_Pasokan!F15 -> 4843.0894 | T95: =Celah_Pasokan!H15 -> 0 | V95: =Celah_Pasokan!I15 -> Belum terwakili
B96: =Celah_Pasokan!A16 -> 8 | C96: =Celah_Pasokan!B16 -> 26030000 | F96: =Celah_Pasokan!C16 -> Copper ores and concentrates | N96: =Celah_Pasokan!E16 -> Bijih, terak & abu logam | R96: =Celah_Pasokan!F16 -> 4545.5013 | T96: =Celah_Pasokan!H16 -> 0 | V96: =Celah_Pasokan!I16 -> Belum terwakili
B97: =Celah_Pasokan!A17 -> 9 | C97: =Celah_Pasokan!B17 -> 87032259 | F97: =Celah_Pasokan!C17 -> Motor cars (including station wagons and sports cars, but not including vans), other than of 4-wheel drive, with only spark-ignition internal combustion piston engine, of a cylinder capacity > 1,000 cc but ≤ 1,500 cc, other than CKD | N97: =Celah_Pasokan!E17 -> Kendaraan bermotor | R97: =Celah_Pasokan!F17 -> 3584.1137 | T97: =Celah_Pasokan!H17 -> 0 | V97: =Celah_Pasokan!I17 -> Belum terwakili
B98: =Celah_Pasokan!A18 -> 10 | C98: =Celah_Pasokan!B18 -> 27011290 | F98: =Celah_Pasokan!C18 -> Bituminous coal, whether or not pulverised, but not agglomerated, other than coking coal | N98: =Celah_Pasokan!E18 -> Batubara, migas & bahan bakar | R98: =Celah_Pasokan!F18 -> 3150.4652 | T98: =Celah_Pasokan!H18 -> 0 | V98: =Celah_Pasokan!I18 -> Belum terwakili
B100: Sumber: HS_Code.csv (ekspor nasional Jan–Nov 2025) dan IndonesiaExportir.csv (direktori eksportir). Parameter dan metode ada di sheet Metode_Catatan; temuan lengkap di sheet Ringkasan.

Sheet Ringkasan
A1: Ringkasan Analisis
A2: Temuan utama, rekomendasi, dan metrik kunci — kalimat temuan dihitung otomatis dari data
B4: TEMUAN UTAMA
B5: 1 | C5: Ekspor sangat terkonsentrasi | D5: ="10 kode HS teratas menyumbang "&ROUND($D$34*100,1)&"%"&" nilai ekspor dan 100 teratas "&ROUND($D$36*100,1)&"%"&", padahal terdapat "&FIXED($D$31,0)&" kode HS aktif. Bab terbesar adalah "&$D$32&" dengan "&ROUND($D$33*100,1)&"%"&" dari total nilai ekspor US$ "&ROUND($D$28,1)&" miliar (Jan–Nov 2025)." -> 10 kode HS teratas menyumbang 26.9% nilai ekspor dan 100 teratas 65.6%, padahal terdapat 8,202 kode HS aktif. Bab terbesar adalah 15 · Lemak & minyak nabati/hewani dengan 13% dari total nilai ekspor US$ 234.6 miliar (Jan–Nov 2025).
B6: 2 | C6: Nilai dan volume bercerita berbeda | D6: ="Barang berharga di bawah US$ 1/kg menyumbang "&ROUND($D$39*100,1)&"%"&" volume tetapi hanya "&ROUND($D$38*100,1)&"%"&" nilai, sedangkan barang ≥ US$ 100/kg hanya "&ROUND($D$41*100,2)&"%"&" volume namun "&ROUND($D$40*100,1)&"%"&" nilai. Nilai ekspor lebih ditentukan oleh komposisi produk bernilai tambah daripada tonase." -> Barang berharga di bawah US$ 1/kg menyumbang 71.7% volume tetapi hanya 18.4% nilai, sedangkan barang ≥ US$ 100/kg hanya 0.01% volume namun 7.4% nilai. Nilai ekspor lebih ditentukan oleh komposisi produk bernilai tambah daripada tonase.
B7: 3 | C7: Direktori hanya mewakili sebagian kecil ekspor | D7: ="Direktori mencakup "&FIXED($D$45,0)&" dari "&FIXED($D$31,0)&" kode HS aktif ("&ROUND($D$46*100,1)&"%"&"), setara "&ROUND($D$47*100,1)&"%"&" nilai ekspor nasional. Dari "&FIXED($D$48,0)&" HS bernilai ≥ US$ "&ROUND(p_nilai_besar/10^6,0)&" juta, "&FIXED($D$49,0)&" belum punya satu pun listing eksportir." -> Direktori mencakup 524 dari 8,202 kode HS aktif (6.4%), setara 11.7% nilai ekspor nasional. Dari 1,308 HS bernilai ≥ US$ 10 juta, 1,187 belum punya satu pun listing eksportir.
B8: 4 | C8: Komposisi direktori condong ke komoditas tertentu | D8: ="Bab '"&$D$68&"' memuat "&ROUND($D$69*100,1)&"%"&" seluruh listing, padahal hanya "&ROUND($D$70*100,1)&"%"&" nilai ekspor nasional. Sebaliknya, di antara 10 bab terbesar, "&$D$71&" paling kurang terwakili: "&ROUND($D$72*100,1)&"%"&" nilai ekspor tetapi hanya "&FIXED($D$73,0)&" listing." -> Bab 'Kopi, teh & rempah' memuat 26.7% seluruh listing, padahal hanya 1.4% nilai ekspor nasional. Sebaliknya, di antara 10 bab terbesar, 75 · Nikel paling kurang terwakili: 3.6% nilai ekspor tetapi hanya 0 listing.
B9: 5 | C9: Celah pasokan terbesar ada pada bab bernilai tinggi | D9: ="Nilai HS yang belum terwakili mencapai "&ROUND($D$50*100,1)&"%"&" ekspor nasional (US$ "&ROUND($D$50*$D$28,1)&" miliar). Bab dengan nilai belum terwakili terbesar: "&Bab_HS!S19&" (US$ "&ROUND(Bab_HS!T19,1)&" miliar), disusul "&Bab_HS!S20&" dan "&Bab_HS!S21&". Daftar 30 HS prioritas ada di sheet Celah_Pasokan." -> Nilai HS yang belum terwakili mencapai 85.7% ekspor nasional (US$ 201.1 miliar). Bab dengan nilai belum terwakili terbesar: 72 · Besi & baja (US$ 24.4 miliar), disusul 15 · Lemak & minyak nabati/hewani dan 27 · Batubara, migas & bahan bakar. Daftar 30 HS prioritas ada di sheet Celah_Pasokan.
B10: 6 | C10: Estimasi pendapatan eksportir tidak bisa dipakai mentah | D10: ="Total estimasi pendapatan mentah US$ "&ROUND($D$54,1)&" miliar/bulan setara "&ROUND($D$54/$D$57*100,0)&"% seluruh ekspor Indonesia per bulan, tidak masuk akal untuk "&FIXED($D$42,0)&" perusahaan. Penyebabnya: "&FIXED($D$52,0)&" listing ("&ROUND($D$53*100,1)&"%"&" dari yang berestimasi) mengklaim pendapatan melebihi total ekspor nasional HS-nya dan menyumbang "&ROUND($D$56*100,1)&"%"&" total estimasi. Harga di direktori hanyalah rata-rata nasional per HS, sehingga salah pilih kode HS langsung membengkakkan angka. Setelah disaring tersisa US$ "&ROUND($D$55,2)&" miliar/bulan." -> Total estimasi pendapatan mentah US$ 13 miliar/bulan setara 61% seluruh ekspor Indonesia per bulan, tidak masuk akal untuk 773 perusahaan. Penyebabnya: 777 listing (27.3% dari yang berestimasi) mengklaim pendapatan melebihi total ekspor nasional HS-nya dan menyumbang 94.6% total estimasi. Harga di direktori hanyalah rata-rata nasional per HS, sehingga salah pilih kode HS langsung membengkakkan angka. Setelah disaring tersisa US$ 0.69 miliar/bulan.
B11: 7 | C11: Eksportir terpusat di Pulau Jawa | D11: =ROUND($D$58*100,1)&"%"&" perusahaan berada di enam provinsi Jawa (DKI Jakarta, Jawa Barat, Jawa Tengah, Jawa Timur, DI Yogyakarta, Banten). Provinsi terbanyak: "&$D$59&" ("&FIXED($D$60,0)&" perusahaan). Perusahaan dengan listing terbanyak: "&$D$61&" ("&FIXED($D$62,0)&" listing)." -> 68.7% perusahaan berada di enam provinsi Jawa (DKI Jakarta, Jawa Barat, Jawa Tengah, Jawa Timur, DI Yogyakarta, Banten). Provinsi terbanyak: Jawa Timur (149 perusahaan). Perusahaan dengan listing terbanyak: ATHAYA AGRO PRATINDO, PT (62 listing).
B12: 8 | C12: Praktik transaksi dan kelengkapan data | D12: ="FOB dipakai pada "&ROUND($D$63*100,1)&"%"&" listing; T/T "&ROUND($D$64*100,1)&"%"&" dan LC "&ROUND($D$65*100,1)&"%"&". Namun pelabuhan ekspor kosong pada "&ROUND($D$66*100,1)&"%"&" listing dan "&FIXED($D$67,0)&" listing berkode HS 00000000, sehingga analisis logistik dan pemetaan produk perlu dilengkapi dulu." -> FOB dipakai pada 69.8% listing; T/T 53.1% dan LC 38.2%. Namun pelabuhan ekspor kosong pada 68.3% listing dan 307 listing berkode HS 00000000, sehingga analisis logistik dan pemetaan produk perlu dilengkapi dulu.
B14: REKOMENDASI
B15: 1 | C15: Mulai skrining dari sheet Celah_Pasokan | D15: Verifikasi apakah eksportir besar pada 30 kode HS prioritas memang tidak memakai direktori. Sisanya dapat dijadikan target rekrutmen eksportir atau pencarian pemasok.
B16: 2 | C16: Jangan pakai estimasi pendapatan mentah | D16: Gunakan hanya listing berstatus 'Wajar' (filter kolom Status estimasi di Data_Eksportir). Minta harga penawaran per perusahaan dan perbaiki pemetaan kode HS pada listing yang melebihi ekspor nasional.
B17: 3 | C17: Perbaiki kualitas data direktori | D17: Lengkapi kode HS 00000000, nama produk kosong, dan pelabuhan ekspor yang belum terisi, serta minimum order/kapasitas agar estimasi volume tidak bergantung pada asumsi.
B18: 4 | C18: Bedakan strategi per bab | D18: Bab berindeks keterwakilan > 1 ramai pemasok relatif terhadap nilai ekspornya, sehingga fokus pada diferensiasi dan pasar baru. Bab bernilai besar berindeks < 1 menunjukkan ruang menambah pemasok terdaftar dan pendampingan ekspor (lihat sheet Bab_HS).
B19: 5 | C19: Pertimbangkan sebaran geografis | D19: Jika tujuannya pemerataan, perluas pembinaan dan onboarding eksportir di luar Jawa (lihat tabel provinsi di sheet Eksportir).
B20: 6 | C20: Perdalam data berikutnya | D20: Tambahkan data bulan/tahun sebelumnya untuk melihat pertumbuhan dan musiman, serta negara tujuan agar peluang pasar lebih tajam. Ubah parameter di Metode_Catatan untuk menguji sensitivitas ambang nilai.
B25: METRIK KUNCI (sumber seluruh angka pada dashboard & temuan)
B27: No | C27: Metrik | D27: Nilai | E27: Satuan
B28: 1 | C28: Total nilai ekspor nasional (Jan–Nov 2025) | D28: =SUM(Data_HS!$D$2:$D$8217)/10^9 -> 234.62961 | E28: USD miliar
B29: 2 | C29: Total volume ekspor (hanya HS yang punya data berat) | D29: =SUM(Data_HS!$C$2:$C$8217)/10^9 -> 240.12678 | E29: juta ton
B30: 3 | C30: Harga rata-rata tertimbang | D30: =SUMIFS(Data_HS!$D$2:$D$8217,Data_HS!$C$2:$C$8217,">0")/SUM(Data_HS!$C$2:$C$8217) -> 0.95607018 | E30: USD/kg
B31: 4 | C31: Jumlah kode HS aktif (nilai > 0) | D31: =COUNTIF(Data_HS!$D$2:$D$8217,">0") -> 8202 | E31: kode HS
B32: 5 | C32: Bab dengan nilai ekspor terbesar | D32: =Bab_HS!S6 -> 15 · Lemak & minyak nabati/hewani
B33: 6 | C33: Pangsa bab terbesar | D33: =Bab_HS!U6 -> 0.13031136 | E33: % nilai
B34: 7 | C34: Pangsa 10 kode HS teratas | D34: =Top_HS!Q6 -> 0.26886351 | E34: % nilai
B35: 8 | C35: Pangsa 50 kode HS teratas | D35: =Top_HS!Q7 -> 0.53665365 | E35: % nilai
B36: 9 | C36: Pangsa 100 kode HS teratas | D36: =Top_HS!Q8 -> 0.65612052 | E36: % nilai
B37: 10 | C37: Pangsa 500 kode HS teratas | D37: =Top_HS!Q9 -> 0.88411341 | E37: % nilai
B38: 11 | C38: Segmen < US$ 1/kg: pangsa nilai | D38: =Top_HS!S15 -> 0.18447282 | E38: % nilai
B39: 12 | C39: Segmen < US$ 1/kg: pangsa volume | D39: =Top_HS!T15 -> 0.71721676 | E39: % volume
B40: 13 | C40: Segmen ≥ US$ 100/kg: pangsa nilai | D40: =Top_HS!S19 -> 0.073711576 | E40: % nilai
B41: 14 | C41: Segmen ≥ US$ 100/kg: pangsa volume | D41: =Top_HS!T19 -> 0.0001112292 | E41: % volume
B42: 15 | C42: Jumlah perusahaan eksportir di direktori | D42: =COUNTA(Profil_Perusahaan!$A$2:$A$774) -> 773 | E42: perusahaan
B43: 16 | C43: Jumlah listing produk | D43: =COUNTA(Data_Eksportir!$B$2:$B$3401) -> 3400 | E43: listing
B44: 17 | C44: Rata-rata listing per perusahaan | D44: =D43/D42 -> 4.3984476 | E44: listing
B45: 18 | C45: Kode HS aktif yang punya ≥ 1 listing | D45: =COUNTIFS(Data_HS!$G$2:$G$8217,">0",Data_HS!$D$2:$D$8217,">0") -> 524 | E45: kode HS
B46: 19 | C46: Cakupan kode HS aktif oleh direktori | D46: =D45/D31 -> 0.063886857 | E46: % kode HS
B47: 20 | C47: Nilai ekspor dari HS yang punya listing | D47: =SUMIFS(Data_HS!$D$2:$D$8217,Data_HS!$G$2:$G$8217,">0")/SUM(Data_HS!$D$2:$D$8217) -> 0.11650167 | E47: % nilai
B48: 21 | C48: Kode HS bernilai besar (≥ ambang) | D48: =COUNTIF(Data_HS!$D$2:$D$8217,">="&p_nilai_besar) -> 1308 | E48: kode HS
B49: 22 | C49: HS bernilai besar yang belum punya listing | D49: =COUNTIF(Data_HS!$I$2:$I$8217,"Belum terwakili") -> 1187 | E49: kode HS
B50: 23 | C50: Nilai HS yang belum terwakili | D50: =SUMIFS(Data_HS!$D$2:$D$8217,Data_HS!$I$2:$I$8217,"Belum terwakili")/SUM(Data_HS!$D$2:$D$8217) -> 0.8572249 | E50: % nilai ekspor
B51: 24 | C51: Listing yang punya estimasi pendapatan | D51: =COUNT(Data_Eksportir!$N$2:$N$3401) -> 2848 | E51: listing
B52: 25 | C52: Listing: estimasi melebihi ekspor nasional HS-nya | D52: =COUNTIF(Data_Eksportir!$Q$2:$Q$3401,"Melebihi ekspor nasional HS") -> 777 | E52: listing
B53: 26 | C53: Persentase listing berestimasi tidak wajar | D53: =D52/D51 -> 0.27282303 | E53: % dari yg berestimasi
B54: 27 | C54: Total estimasi pendapatan mentah | D54: =SUM(Data_Eksportir!$N$2:$N$3401)/10^9 -> 12.968081 | E54: USD miliar/bulan
B55: 28 | C55: Total estimasi pendapatan 'Wajar' | D55: =SUMIFS(Data_Eksportir!$N$2:$N$3401,Data_Eksportir!$Q$2:$Q$3401,"Wajar")/10^9 -> 0.69446059 | E55: USD miliar/bulan
B56: 29 | C56: Pangsa listing tidak wajar dalam total estimasi | D56: =SUMIFS(Data_Eksportir!$N$2:$N$3401,Data_Eksportir!$Q$2:$Q$3401,"Melebihi ekspor nasional HS")/SUM(Data_Eksportir!$N$2:$N$3401) -> 0.94644847 | E56: % estimasi
B57: 30 | C57: Rata-rata ekspor nasional per bulan | D57: =D28/p_bulan -> 21.329964 | E57: USD miliar/bulan
B58: 31 | C58: Pangsa perusahaan di 6 provinsi Jawa | D58: =SUMPRODUCT(COUNTIF(Profil_Perusahaan!$B$2:$B$774,{"DKI Jakarta","Jawa Barat","Jawa Tengah","Jawa Timur","DI Yogyakarta","Banten"}))/D42 -> 0.68693402 | E58: % perusahaan
B59: 32 | C59: Provinsi dengan perusahaan terbanyak | D59: =Eksportir!I6 -> Jawa Timur
B60: 33 | C60: Jumlah perusahaan di provinsi tersebut | D60: =Eksportir!J6 -> 149 | E60: perusahaan
B61: 34 | C61: Perusahaan dengan listing terbanyak | D61: =Eksportir!A43 -> ATHAYA AGRO PRATINDO, PT
B62: 35 | C62: Jumlah listing perusahaan tersebut | D62: =Eksportir!D43 -> 62 | E62: listing
B63: 36 | C63: Pangsa listing ber-incoterms FOB | D63: =COUNTIF(Data_Eksportir!$G$2:$G$3401,"FOB")/D43 -> 0.69794118 | E63: % listing
B64: 37 | C64: Pangsa listing ber-payment T/T | D64: =COUNTIF(Data_Eksportir!$F$2:$F$3401,"T/T")/D43 -> 0.53147059 | E64: % listing
B65: 38 | C65: Pangsa listing ber-payment LC | D65: =COUNTIF(Data_Eksportir!$F$2:$F$3401,"LC")/D43 -> 0.38235294 | E65: % listing
B66: 39 | C66: Pangsa listing tanpa pelabuhan ekspor | D66: =COUNTIF(Data_Eksportir!$E$2:$E$3401,"Tidak diketahui")/D43 -> 0.68323529 | E66: % listing
B67: 40 | C67: Listing berkode HS 00000000 | D67: =COUNTIF(Data_Eksportir!$H$2:$H$3401,"00000000") -> 307 | E67: listing
B68: 41 | C68: Bab dengan listing terbanyak | D68: =INDEX(Bab_HS!$B$7:$B$104,MATCH(MAX(Bab_HS!$H$7:$H$104),Bab_HS!$H$7:$H$104,0)) -> Kopi, teh & rempah
B69: 42 | C69: Pangsa listing bab tersebut | D69: =MAX(Bab_HS!$I$7:$I$104) -> 0.26737795 | E69: % listing
B70: 43 | C70: Pangsa nilai ekspor bab tersebut | D70: =INDEX(Bab_HS!$F$7:$F$104,MATCH(MAX(Bab_HS!$H$7:$H$104),Bab_HS!$H$7:$H$104,0)) -> 0.0135299 | E70: % nilai
B71: 44 | C71: Bab terbesar yang paling kurang terwakili (top 10) | D71: =INDEX(Bab_HS!$S$6:$S$15,MATCH(MIN(Bab_HS!$W$6:$W$15),Bab_HS!$W$6:$W$15,0)) -> 75 · Nikel
B72: 45 | C72: Pangsa nilai bab tersebut | D72: =INDEX(Bab_HS!$U$6:$U$15,MATCH(MIN(Bab_HS!$W$6:$W$15),Bab_HS!$W$6:$W$15,0)) -> 0.036040295 | E72: % nilai
B73: 46 | C73: Jumlah listing bab tersebut | D73: =INDEX(Bab_HS!$X$6:$X$15,MATCH(MIN(Bab_HS!$W$6:$W$15),Bab_HS!$W$6:$W$15,0)) -> 0 | E73: listing

Sheet Bab_HS
A1: Analisis per Bab HS (2 digit)
A2: Ekspor nasional Jan–Nov 2025 vs keterwakilan eksportir di direktori — seluruh sel dihitung dengan rumus
A4: Ringkasan seluruh bab HS | Q4: Top 10 bab menurut nilai ekspor
A5: Bab | B5: Nama bab | C5: Jml HS aktif | D5: Berat (juta ton) | E5: Nilai FOB (USD miliar) | F5: Pangsa nilai | G5: Harga rata-rata (USD/kg) | H5: Listing eksportir | I5: Pangsa listing | J5: Indeks keterwakilan | K5: Jml HS belum terwakili | L5: Nilai HS belum terwakili (USD miliar) | M5: Est. kapasitas wajar (USD juta/bln) | N5: Urut nilai (helper) | O5: Urut celah (helper) | Q5: Peringkat | R5: Baris (helper) | S5: Bab | T5: Nilai FOB (USD miliar) | U5: Pangsa nilai | V5: Pangsa listing | W5: Indeks keterwakilan | X5: Listing
A6: 0 | B6: Tidak terklasifikasi (HS 00000000) | C6: =COUNTIFS(Data_HS!$F$2:$F$8217,A6,Data_HS!$D$2:$D$8217,">0") -> 0 | D6: =SUMIFS(Data_HS!$C$2:$C$8217,Data_HS!$F$2:$F$8217,A6)/10^9 -> 0 | E6: =SUMIFS(Data_HS!$D$2:$D$8217,Data_HS!$F$2:$F$8217,A6)/10^9 -> 0 | F6: =E6/$E$105 -> 0 | G6: =IFERROR(SUMIFS(Data_HS!$D$2:$D$8217,Data_HS!$F$2:$F$8217,A6,Data_HS!$C$2:$C$8217,">0")/SUMIFS(Data_HS!$C$2:$C$8217,Data_HS!$F$2:$F$8217,A6),"") | H6: =COUNTIF(Data_Eksportir!$O$2:$O$3401,A6) -> 307 | I6: =IF(A6=0,"",H6/COUNTIF(Data_Eksportir!$O$2:$O$3401,">0")) | J6: =IF(OR(A6=0,F6=0),"",I6/F6) | K6: =COUNTIFS(Data_HS!$F$2:$F$8217,A6,Data_HS!$I$2:$I$8217,"Belum terwakili") -> 0 | L6: =SUMIFS(Data_HS!$D$2:$D$8217,Data_HS!$F$2:$F$8217,A6,Data_HS!$I$2:$I$8217,"Belum terwakili")/10^9 -> 0 | M6: =SUMIFS(Data_Eksportir!$N$2:$N$3401,Data_Eksportir!$O$2:$O$3401,A6,Data_Eksportir!$Q$2:$Q$3401,"Wajar")/10^6 -> 0 | N6: =E6+ROW()/10^9 -> 6e-09 | O6: =L6+ROW()/10^9 -> 6e-09 | Q6: 1 | R6: =MATCH(LARGE($N$6:$N$104,Q6),$N$6:$N$104,0) -> 16 | S6: =TEXT(INDEX($A$6:$A$104,R6),"00")&" · "&INDEX($B$6:$B$104,R6) -> 15 · Lemak & minyak nabati/hewani | T6: =INDEX($E$6:$E$104,R6) -> 30.574903 | U6: =INDEX($F$6:$F$104,R6) -> 0.13031136 | V6: =INDEX($I$6:$I$104,R6) -> 0.042030391 | W6: =IFERROR(V6/U6,"") -> 0.3225382 | X6: =INDEX($H$6:$H$104,R6) -> 130
A7: 1 | B7: Hewan hidup | C7: =COUNTIFS(Data_HS!$F$2:$F$8217,A7,Data_HS!$D$2:$D$8217,">0") -> 17 | D7: =SUMIFS(Data_HS!$C$2:$C$8217,Data_HS!$F$2:$F$8217,A7)/10^9 -> 0.000394052 | E7: =SUMIFS(Data_HS!$D$2:$D$8217,Data_HS!$F$2:$F$8217,A7)/10^9 -> 0.007975873 | F7: =E7/$E$105 -> 3.3993464e-05 | G7: =IFERROR(SUMIFS(Data_HS!$D$2:$D$8217,Data_HS!$F$2:$F$8217,A7,Data_HS!$C$2:$C$8217,">0")/SUMIFS(Data_HS!$C$2:$C$8217,Data_HS!$F$2:$F$8217,A7),"") -> 20.240661 | H7: =COUNTIF(Data_Eksportir!$O$2:$O$3401,A7) -> 0 | I7: =IF(A7=0,"",H7/COUNTIF(Data_Eksportir!$O$2:$O$3401,">0")) -> 0 | J7: =IF(OR(A7=0,F7=0),"",I7/F7) -> 0 | K7: =COUNTIFS(Data_HS!$F$2:$F$8217,A7,Data_HS!$I$2:$I$8217,"Belum terwakili") -> 0 | L7: =SUMIFS(Data_HS!$D$2:$D$8217,Data_HS!$F$2:$F$8217,A7,Data_HS!$I$2:$I$8217,"Belum terwakili")/10^9 -> 0 | M7: =SUMIFS(Data_Eksportir!$N$2:$N$3401,Data_Eksportir!$O$2:$O$3401,A7,Data_Eksportir!$Q$2:$Q$3401,"Wajar")/10^6 -> 0 | N7: =E7+ROW()/10^9 -> 0.00797588 | O7: =L7+ROW()/10^9 -> 7e-09 | Q7: 2 | R7: =MATCH(LARGE($N$6:$N$104,Q7),$N$6:$N$104,0) -> 73 | S7: =TEXT(INDEX($A$6:$A$104,R7),"00")&" · "&INDEX($B$6:$B$104,R7) -> 72 · Besi & baja | T7: =INDEX($E$6:$E$104,R7) -> 24.775586 | U7: =INDEX($F$6:$F$104,R7) -> 0.10559446 | V7: =INDEX($I$6:$I$104,R7) -> 0.0054962819 | W7: =IFERROR(V7/U7,"") -> 0.052050857 | X7: =INDEX($H$6:$H$104,R7) -> 17
A8: 2 | B8: Daging | C8: =COUNTIFS(Data_HS!$F$2:$F$8217,A8,Data_HS!$D$2:$D$8217,">0") -> 22 | D8: =SUMIFS(Data_HS!$C$2:$C$8217,Data_HS!$F$2:$F$8217,A8)/10^9 -> 0.001825197 | E8: =SUMIFS(Data_HS!$D$2:$D$8217,Data_HS!$F$2:$F$8217,A8)/10^9 -> 0.011658113 | F8: =E8/$E$105 -> 4.9687306e-05 | G8: =IFERROR(SUMIFS(Data_HS!$D$2:$D$8217,Data_HS!$F$2:$F$8217,A8,Data_HS!$C$2:$C$8217,">0")/SUMIFS(Data_HS!$C$2:$C$8217,Data_HS!$F$2:$F$8217,A8),"") -> 6.3873176 | H8: =COUNTIF(Data_Eksportir!$O$2:$O$3401,A8) -> 28 | I8: =IF(A8=0,"",H8/COUNTIF(Data_Eksportir!$O$2:$O$3401,">0")) -> 0.0090526996 | J8: =IF(OR(A8=0,F8=0),"",I8/F8) -> 182.19341 | K8: =COUNTIFS(Data_HS!$F$2:$F$8217,A8,Data_HS!$I$2:$I$8217,"Belum terwakili") -> 0 | L8: =SUMIFS(Data_HS!$D$2:$D$8217,Data_HS!$F$2:$F$8217,A8,Data_HS!$I$2:$I$8217,"Belum terwakili")/10^9 -> 0 | M8: =SUMIFS(Data_Eksportir!$N$2:$N$3401,Data_Eksportir!$O$2:$O$3401,A8,Data_Eksportir!$Q$2:$Q$3401,"Wajar")/10^6 -> 5.9627792e-05 | N8: =E8+ROW()/10^9 -> 0.011658121 | O8: =L8+ROW()/10^9 -> 8e-09 | Q8: 3 | R8: =MATCH(LARGE($N$6:$N$104,Q8),$N$6:$N$104,0) -> 28 | S8: =TEXT(INDEX($A$6:$A$104,R8),"00")&" · "&INDEX($B$6:$B$104,R8) -> 27 · Batubara, migas & bahan bakar | T8: =INDEX($E$6:$E$104,R8) -> 23.823585 | U8: =INDEX($F$6:$F$104,R8) -> 0.101537 | V8: =INDEX($I$6:$I$104,R8) -> 0.010669253 | W8: =IFERROR(V8/U8,"") -> 0.10507749 | X8: =INDEX($H$6:$H$104,R8) -> 33
A9: 3 | B9: Ikan & hasil laut | C9: =COUNTIFS(Data_HS!$F$2:$F$8217,A9,Data_HS!$D$2:$D$8217,">0") -> 245 | D9: =SUMIFS(Data_HS!$C$2:$C$8217,Data_HS!$F$2:$F$8217,A9)/10^9 -> 0.803831 | E9: =SUMIFS(Data_HS!$D$2:$D$8217,Data_HS!$F$2:$F$8217,A9)/10^9 -> 3.5981188 | F9: =E9/$E$105 -> 0.015335315 | G9: =IFERROR(SUMIFS(Data_HS!$D$2:$D$8217,Data_HS!$F$2:$F$8217,A9,Data_HS!$C$2:$C$8217,">0")/SUMIFS(Data_HS!$C$2:$C$8217,Data_HS!$F$2:$F$8217,A9),"") -> 4.4762128 | H9: =COUNTIF(Data_Eksportir!$O$2:$O$3401,A9) -> 59 | I9: =IF(A9=0,"",H9/COUNTIF(Data_Eksportir!$O$2:$O$3401,">0")) -> 0.019075331 | J9: =IF(OR(A9=0,F9=0),"",I9/F9) -> 1.2438826 | K9: =COUNTIFS(Data_HS!$F$2:$F$8217,A9,Data_HS!$I$2:$I$8217,"Belum terwakili") -> 31 | L9: =SUMIFS(Data_HS!$D$2:$D$8217,Data_HS!$F$2:$F$8217,A9,Data_HS!$I$2:$I$8217,"Belum terwakili")/10^9 -> 2.4599276 | M9: =SUMIFS(Data_Eksportir!$N$2:$N$3401,Data_Eksportir!$O$2:$O$3401,A9,Data_Eksportir!$Q$2:$Q$3401,"Wajar")/10^6 -> 5.5478968 | N9: =E9+ROW()/10^9 -> 3.5981188 | O9: =L9+ROW()/10^9 -> 2.4599276 | Q9: 4 | R9: =MATCH(LARGE($N$6:$N$104,Q9),$N$6:$N$104,0) -> 85 | S9: =TEXT(INDEX($A$6:$A$104,R9),"00")&" · "&INDEX($B$6:$B$104,R9) -> 85 · Mesin listrik & elektronik | T9: =INDEX($E$6:$E$104,R9) -> 17.496555 | U9: =INDEX($F$6:$F$104,R9) -> 0.074570959 | V9: =INDEX($I$6:$I$104,R9) -> 0.0077594568 | W9: =IFERROR(V9/U9,"") -> 0.10405467 | X9: =INDEX($H$6:$H$104,R9) -> 24
A10: 4 | B10: Susu, telur & madu | C10: =COUNTIFS(Data_HS!$F$2:$F$8217,A10,Data_HS!$D$2:$D$8217,">0") -> 49 | D10: =SUMIFS(Data_HS!$C$2:$C$8217,Data_HS!$F$2:$F$8217,A10)/10^9 -> 0.055669622 | E10: =SUMIFS(Data_HS!$D$2:$D$8217,Data_HS!$F$2:$F$8217,A10)/10^9 -> 0.51110084 | F10: =E10/$E$105 -> 0.0021783306 | G10: =IFERROR(SUMIFS(Data_HS!$D$2:$D$8217,Data_HS!$F$2:$F$8217,A10,Data_HS!$C$2:$C$8217,">0")/SUMIFS(Data_HS!$C$2:$C$8217,Data_HS!$F$2:$F$8217,A10),"") -> 9.1809649 | H10: =COUNTIF(Data_Eksportir!$O$2:$O$3401,A10) -> 75 | I10: =IF(A10=0,"",H10/COUNTIF(Data_Eksportir!$O$2:$O$3401,">0")) -> 0.024248303 | J10: =IF(OR(A10=0,F10=0),"",I10/F10) -> 11.131599 | K10: =COUNTIFS(Data_HS!$F$2:$F$8217,A10,Data_HS!$I$2:$I$8217,"Belum terwakili") -> 0 | L10: =SUMIFS(Data_HS!$D$2:$D$8217,Data_HS!$F$2:$F$8217,A10,Data_HS!$I$2:$I$8217,"Belum terwakili")/10^9 -> 0 | M10: =SUMIFS(Data_Eksportir!$N$2:$N$3401,Data_Eksportir!$O$2:$O$3401,A10,Data_Eksportir!$Q$2:$Q$3401,"Wajar")/10^6 -> 1.2504402 | N10: =E10+ROW()/10^9 -> 0.51110086 | O10: =L10+ROW()/10^9 -> 1e-08 | Q10: 5 | R10: =MATCH(LARGE($N$6:$N$104,Q10),$N$6:$N$104,0) -> 87 | S10: =TEXT(INDEX($A$6:$A$104,R10),"00")&" · "&INDEX($B$6:$B$104,R10) -> 87 · Kendaraan bermotor | T10: =INDEX($E$6:$E$104,R10) -> 10.862972 | U10: =INDEX($F$6:$F$104,R10) -> 0.046298387 | V10: =INDEX($I$6:$I$104,R10) -> 0.0009699321 | W10: =IFERROR(V10/U10,"") -> 0.020949587 | X10: =INDEX($H$6:$H$104,R10) -> 3
A11: 5 | B11: Produk hewani lainnya | C11: =COUNTIFS(Data_HS!$F$2:$F$8217,A11,Data_HS!$D$2:$D$8217,">0") -> 16 | D11: =SUMIFS(Data_HS!$C$2:$C$8217,Data_HS!$F$2:$F$8217,A11)/10^9 -> 0.02208941 | E11: =SUMIFS(Data_HS!$D$2:$D$8217,Data_HS!$F$2:$F$8217,A11)/10^9 -> 0.039746529 | F11: =E11/$E$105 -> 0.00016940117 | G11: =IFERROR(SUMIFS(Data_HS!$D$2:$D$8217,Data_HS!$F$2:$F$8217,A11,Data_HS!$C$2:$C$8217,">0")/SUMIFS(Data_HS!$C$2:$C$8217,Data_HS!$F$2:$F$8217,A11),"") -> 1.7993477 | H11: =COUNTIF(Data_Eksportir!$O$2:$O$3401,A11) -> 15 | I11: =IF(A11=0,"",H11/COUNTIF(Data_Eksportir!$O$2:$O$3401,">0")) -> 0.0048496605 | J11: =IF(OR(A11=0,F11=0),"",I11/F11) -> 28.628259 | K11: =COUNTIFS(Data_HS!$F$2:$F$8217,A11,Data_HS!$I$2:$I$8217,"Belum terwakili") -> 1 | L11: =SUMIFS(Data_HS!$D$2:$D$8217,Data_HS!$F$2:$F$8217,A11,Data_HS!$I$2:$I$8217,"Belum terwakili")/10^9 -> 0.010421971 | M11: =SUMIFS(Data_Eksportir!$N$2:$N$3401,Data_Eksportir!$O$2:$O$3401,A11,Data_Eksportir!$Q$2:$Q$3401,"Wajar")/10^6 -> 0.14016826 | N11: =E11+ROW()/10^9 -> 0.03974654 | O11: =L11+ROW()/10^9 -> 0.010421982 | Q11: 6 | R11: =MATCH(LARGE($N$6:$N$104,Q11),$N$6:$N$104,0) -> 72 | S11: =TEXT(INDEX($A$6:$A$104,R11),"00")&" · "&INDEX($B$6:$B$104,R11) -> 71 · Mutiara, permata & logam mulia | T11: =INDEX($E$6:$E$104,R11) -> 10.777363 | U11: =INDEX($F$6:$F$104,R11) -> 0.045933519 | V11: =INDEX($I$6:$I$104,R11) -> 0.0006466214 | W11: =IFERROR(V11/U11,"") -> 0.014077332 | X11: =INDEX($H$6:$H$104,R11) -> 2
A12: 6 | B12: Tanaman hidup & bunga | C12: =COUNTIFS(Data_HS!$F$2:$F$8217,A12,Data_HS!$D$2:$D$8217,">0") -> 21 | D12: =SUMIFS(Data_HS!$C$2:$C$8217,Data_HS!$F$2:$F$8217,A12)/10^9 -> 0.006786545 | E12: =SUMIFS(Data_HS!$D$2:$D$8217,Data_HS!$F$2:$F$8217,A12)/10^9 -> 0.01988095 | F12: =E12/$E$105 -> 8.4733339e-05 | G12: =IFERROR(SUMIFS(Data_HS!$D$2:$D$8217,Data_HS!$F$2:$F$8217,A12,Data_HS!$C$2:$C$8217,">0")/SUMIFS(Data_HS!$C$2:$C$8217,Data_HS!$F$2:$F$8217,A12),"") -> 2.9294656 | H12: =COUNTIF(Data_Eksportir!$O$2:$O$3401,A12) -> 4 | I12: =IF(A12=0,"",H12/COUNTIF(Data_Eksportir!$O$2:$O$3401,">0")) -> 0.0012932428 | J12: =IF(OR(A12=0,F12=0),"",I12/F12) -> 15.262503 | K12: =COUNTIFS(Data_HS!$F$2:$F$8217,A12,Data_HS!$I$2:$I$8217,"Belum terwakili") -> 0 | L12: =SUMIFS(Data_HS!$D$2:$D$8217,Data_HS!$F$2:$F$8217,A12,Data_HS!$I$2:$I$8217,"Belum terwakili")/10^9 -> 0 | M12: =SUMIFS(Data_Eksportir!$N$2:$N$3401,Data_Eksportir!$O$2:$O$3401,A12,Data_Eksportir!$Q$2:$Q$3401,"Wajar")/10^6 -> 0.028312811 | N12: =E12+ROW()/10^9 -> 0.019880962 | O12: =L12+ROW()/10^9 -> 1.2e-08 | Q12: 7 | R12: =MATCH(LARGE($N$6:$N$104,Q12),$N$6:$N$104,0) -> 39 | S12: =TEXT(INDEX($A$6:$A$104,R12),"00")&" · "&INDEX($B$6:$B$104,R12) -> 38 · Produk kimia lainnya | T12: =INDEX($E$6:$E$104,R12) -> 8.6399942 | U12: =INDEX($F$6:$F$104,R12) -> 0.036823973 | V12: =INDEX($I$6:$I$104,R12) -> 0.07824119 | W12: =IFERROR(V12/U12,"") -> 2.1247352 | X12: =INDEX($H$6:$H$104,R12) -> 242
A13: 7 | B13: Sayuran & umbi | C13: =COUNTIFS(Data_HS!$F$2:$F$8217,A13,Data_HS!$D$2:$D$8217,">0") -> 83 | D13: =SUMIFS(Data_HS!$C$2:$C$8217,Data_HS!$F$2:$F$8217,A13)/10^9 -> 0.11240872 | E13: =SUMIFS(Data_HS!$D$2:$D$8217,Data_HS!$F$2:$F$8217,A13)/10^9 -> 0.098891759 | F13: =E13/$E$105 -> 0.00042148031 | G13: =IFERROR(SUMIFS(Data_HS!$D$2:$D$8217,Data_HS!$F$2:$F$8217,A13,Data_HS!$C$2:$C$8217,">0")/SUMIFS(Data_HS!$C$2:$C$8217,Data_HS!$F$2:$F$8217,A13),"") -> 0.87975169 | H13: =COUNTIF(Data_Eksportir!$O$2:$O$3401,A13) -> 127 | I13: =IF(A13=0,"",H13/COUNTIF(Data_Eksportir!$O$2:$O$3401,">0")) -> 0.041060459 | J13: =IF(OR(A13=0,F13=0),"",I13/F13) -> 97.419638 | K13: =COUNTIFS(Data_HS!$F$2:$F$8217,A13,Data_HS!$I$2:$I$8217,"Belum terwakili") -> 2 | L13: =SUMIFS(Data_HS!$D$2:$D$8217,Data_HS!$F$2:$F$8217,A13,Data_HS!$I$2:$I$8217,"Belum terwakili")/10^9 -> 0.045965723 | M13: =SUMIFS(Data_Eksportir!$N$2:$N$3401,Data_Eksportir!$O$2:$O$3401,A13,Data_Eksportir!$Q$2:$Q$3401,"Wajar")/10^6 -> 1.2088704 | N13: =E13+ROW()/10^9 -> 0.098891772 | O13: =L13+ROW()/10^9 -> 0.045965736 | Q13: 8 | R13: =MATCH(LARGE($N$6:$N$104,Q13),$N$6:$N$104,0) -> 76 | S13: =TEXT(INDEX($A$6:$A$104,R13),"00")&" · "&INDEX($B$6:$B$104,R13) -> 75 · Nikel | T13: =INDEX($E$6:$E$104,R13) -> 8.4561202 | U13: =INDEX($F$6:$F$104,R13) -> 0.036040295 | V13: =INDEX($I$6:$I$104,R13) -> 0 | W13: =IFERROR(V13/U13,"") -> 0 | X13: =INDEX($H$6:$H$104,R13) -> 0
A14: 8 | B14: Buah & kacang-kacangan | C14: =COUNTIFS(Data_HS!$F$2:$F$8217,A14,Data_HS!$D$2:$D$8217,">0") -> 76 | D14: =SUMIFS(Data_HS!$C$2:$C$8217,Data_HS!$F$2:$F$8217,A14)/10^9 -> 1.7455757 | E14: =SUMIFS(Data_HS!$D$2:$D$8217,Data_HS!$F$2:$F$8217,A14)/10^9 -> 1.3332451 | F14: =E14/$E$105 -> 0.0056823394 | G14: =IFERROR(SUMIFS(Data_HS!$D$2:$D$8217,Data_HS!$F$2:$F$8217,A14,Data_HS!$C$2:$C$8217,">0")/SUMIFS(Data_HS!$C$2:$C$8217,Data_HS!$F$2:$F$8217,A14),"") -> 0.76378531 | H14: =COUNTIF(Data_Eksportir!$O$2:$O$3401,A14) -> 252 | I14: =IF(A14=0,"",H14/COUNTIF(Data_Eksportir!$O$2:$O$3401,">0")) -> 0.081474297 | J14: =IF(OR(A14=0,F14=0),"",I14/F14) -> 14.338161 | K14: =COUNTIFS(Data_HS!$F$2:$F$8217,A14,Data_HS!$I$2:$I$8217,"Belum terwakili") -> 4 | L14: =SUMIFS(Data_HS!$D$2:$D$8217,Data_HS!$F$2:$F$8217,A14,Data_HS!$I$2:$I$8217,"Belum terwakili")/10^9 -> 0.29160744 | M14: =SUMIFS(Data_Eksportir!$N$2:$N$3401,Data_Eksportir!$O$2:$O$3401,A14,Data_Eksportir!$Q$2:$Q$3401,"Wajar")/10^6 -> 9.5562306 | N14: =E14+ROW()/10^9 -> 1.3332451 | O14: =L14+ROW()/10^9 -> 0.29160745 | Q14: 9 | R14: =MATCH(LARGE($N$6:$N$104,Q14),$N$6:$N$104,0) -> 84 | S14: =TEXT(INDEX($A$6:$A$104,R14),"00")&" · "&INDEX($B$6:$B$104,R14) -> 84 · Mesin & peralatan mekanis | T14: =INDEX($E$6:$E$104,R14) -> 7.4133267 | U14: =INDEX($F$6:$F$104,R14) -> 0.031595871 | V14: =INDEX($I$6:$I$104,R14) -> 0.010345942 | W14: =IFERROR(V14/U14,"") -> 0.32744603 | X14: =INDEX($H$6:$H$104,R14) -> 32
A15: 9 | B15: Kopi, teh & rempah | C15: =COUNTIFS(Data_HS!$F$2:$F$8217,A15,Data_HS!$D$2:$D$8217,">0") -> 62 | D15: =SUMIFS(Data_HS!$C$2:$C$8217,Data_HS!$F$2:$F$8217,A15)/10^9 -> 0.64447955 | E15: =SUMIFS(Data_HS!$D$2:$D$8217,Data_HS!$F$2:$F$8217,A15)/10^9 -> 3.1745151 | F15: =E15/$E$105 -> 0.0135299 | G15: =IFERROR(SUMIFS(Data_HS!$D$2:$D$8217,Data_HS!$F$2:$F$8217,A15,Data_HS!$C$2:$C$8217,">0")/SUMIFS(Data_HS!$C$2:$C$8217,Data_HS!$F$2:$F$8217,A15),"") -> 4.9257032 | H15: =COUNTIF(Data_Eksportir!$O$2:$O$3401,A15) -> 827 | I15: =IF(A15=0,"",H15/COUNTIF(Data_Eksportir!$O$2:$O$3401,">0")) -> 0.26737795 | J15: =IF(OR(A15=0,F15=0),"",I15/F15) -> 19.762005 | K15: =COUNTIFS(Data_HS!$F$2:$F$8217,A15,Data_HS!$I$2:$I$8217,"Belum terwakili") -> 4 | L15: =SUMIFS(Data_HS!$D$2:$D$8217,Data_HS!$F$2:$F$8217,A15,Data_HS!$I$2:$I$8217,"Belum terwakili")/10^9 -> 0.1586538 | M15: =SUMIFS(Data_Eksportir!$N$2:$N$3401,Data_Eksportir!$O$2:$O$3401,A15,Data_Eksportir!$Q$2:$Q$3401,"Wajar")/10^6 -> 75.838899 | N15: =E15+ROW()/10^9 -> 3.1745151 | O15: =L15+ROW()/10^9 -> 0.15865382 | Q15: 10 | R15: =MATCH(LARGE($N$6:$N$104,Q15),$N$6:$N$104,0) -> 65 | S15: =TEXT(INDEX($A$6:$A$104,R15),"00")&" · "&INDEX($B$6:$B$104,R15) -> 64 · Alas kaki | T15: =INDEX($E$6:$E$104,R15) -> 5.1029468 | U15: =INDEX($F$6:$F$104,R15) -> 0.021748947 | V15: =INDEX($I$6:$I$104,R15) -> 0.0045263498 | W15: =IFERROR(V15/U15,"") -> 0.20811812 | X15: =INDEX($H$6:$H$104,R15) -> 14
A16: 10 | B16: Serealia | C16: =COUNTIFS(Data_HS!$F$2:$F$8217,A16,Data_HS!$D$2:$D$8217,">0") -> 19 | D16: =SUMIFS(Data_HS!$C$2:$C$8217,Data_HS!$F$2:$F$8217,A16)/10^9 -> 0.007789274 | E16: =SUMIFS(Data_HS!$D$2:$D$8217,Data_HS!$F$2:$F$8217,A16)/10^9 -> 0.005560159 | F16: =E16/$E$105 -> 2.3697602e-05 | G16: =IFERROR(SUMIFS(Data_HS!$D$2:$D$8217,Data_HS!$F$2:$F$8217,A16,Data_HS!$C$2:$C$8217,">0")/SUMIFS(Data_HS!$C$2:$C$8217,Data_HS!$F$2:$F$8217,A16),"") -> 0.71382249 | H16: =COUNTIF(Data_Eksportir!$O$2:$O$3401,A16) -> 77 | I16: =IF(A16=0,"",H16/COUNTIF(Data_Eksportir!$O$2:$O$3401,">0")) -> 0.024894924 | J16: =IF(OR(A16=0,F16=0),"",I16/F16) -> 1050.525 | K16: =COUNTIFS(Data_HS!$F$2:$F$8217,A16,Data_HS!$I$2:$I$8217,"Belum terwakili") -> 0 | L16: =SUMIFS(Data_HS!$D$2:$D$8217,Data_HS!$F$2:$F$8217,A16,Data_HS!$I$2:$I$8217,"Belum terwakili")/10^9 -> 0 | M16: =SUMIFS(Data_Eksportir!$N$2:$N$3401,Data_Eksportir!$O$2:$O$3401,A16,Data_Eksportir!$Q$2:$Q$3401,"Wajar")/10^6 -> 0.12542886 | N16: =E16+ROW()/10^9 -> 0.005560175 | O16: =L16+ROW()/10^9 -> 1.6e-08
A17: 11 | B17: Produk penggilingan & pati | C17: =COUNTIFS(Data_HS!$F$2:$F$8217,A17,Data_HS!$D$2:$D$8217,">0") -> 33 | D17: =SUMIFS(Data_HS!$C$2:$C$8217,Data_HS!$F$2:$F$8217,A17)/10^9 -> 0.17628103 | E17: =SUMIFS(Data_HS!$D$2:$D$8217,Data_HS!$F$2:$F$8217,A17)/10^9 -> 0.089289736 | F17: =E17/$E$105 -> 0.00038055613 | G17: =IFERROR(SUMIFS(Data_HS!$D$2:$D$8217,Data_HS!$F$2:$F$8217,A17,Data_HS!$C$2:$C$8217,">0")/SUMIFS(Data_HS!$C$2:$C$8217,Data_HS!$F$2:$F$8217,A17),"") -> 0.50651926 | H17: =COUNTIF(Data_Eksportir!$O$2:$O$3401,A17) -> 40 | I17: =IF(A17=0,"",H17/COUNTIF(Data_Eksportir!$O$2:$O$3401,">0")) -> 0.012932428 | J17: =IF(OR(A17=0,F17=0),"",I17/F17) -> 33.982971 | K17: =COUNTIFS(Data_HS!$F$2:$F$8217,A17,Data_HS!$I$2:$I$8217,"Belum terwakili") -> 2 | L17: =SUMIFS(Data_HS!$D$2:$D$8217,Data_HS!$F$2:$F$8217,A17,Data_HS!$I$2:$I$8217,"Belum terwakili")/10^9 -> 0.044368613 | M17: =SUMIFS(Data_Eksportir!$N$2:$N$3401,Data_Eksportir!$O$2:$O$3401,A17,Data_Eksportir!$Q$2:$Q$3401,"Wajar")/10^6 -> 0.80791612 | N17: =E17+ROW()/10^9 -> 0.089289753 | O17: =L17+ROW()/10^9 -> 0.04436863 | Q17: Top 10 bab menurut nilai HS yang belum terwakili di direktori
A18: 12 | B18: Biji & buah berminyak | C18: =COUNTIFS(Data_HS!$F$2:$F$8217,A18,Data_HS!$D$2:$D$8217,">0") -> 57 | D18: =SUMIFS(Data_HS!$C$2:$C$8217,Data_HS!$F$2:$F$8217,A18)/10^9 -> 0.30017293 | E18: =SUMIFS(Data_HS!$D$2:$D$8217,Data_HS!$F$2:$F$8217,A18)/10^9 -> 0.49876592 | F18: =E18/$E$105 -> 0.0021257587 | G18: =IFERROR(SUMIFS(Data_HS!$D$2:$D$8217,Data_HS!$F$2:$F$8217,A18,Data_HS!$C$2:$C$8217,">0")/SUMIFS(Data_HS!$C$2:$C$8217,Data_HS!$F$2:$F$8217,A18),"") -> 1.6615953 | H18: =COUNTIF(Data_Eksportir!$O$2:$O$3401,A18) -> 88 | I18: =IF(A18=0,"",H18/COUNTIF(Data_Eksportir!$O$2:$O$3401,">0")) -> 0.028451342 | J18: =IF(OR(A18=0,F18=0),"",I18/F18) -> 13.384088 | K18: =COUNTIFS(Data_HS!$F$2:$F$8217,A18,Data_HS!$I$2:$I$8217,"Belum terwakili") -> 3 | L18: =SUMIFS(Data_HS!$D$2:$D$8217,Data_HS!$F$2:$F$8217,A18,Data_HS!$I$2:$I$8217,"Belum terwakili")/10^9 -> 0.25870226 | M18: =SUMIFS(Data_Eksportir!$N$2:$N$3401,Data_Eksportir!$O$2:$O$3401,A18,Data_Eksportir!$Q$2:$Q$3401,"Wajar")/10^6 -> 9.2326424 | N18: =E18+ROW()/10^9 -> 0.49876594 | O18: =L18+ROW()/10^9 -> 0.25870228 | Q18: Peringkat | R18: Baris (helper) | S18: Bab | T18: Nilai belum terwakili (USD miliar) | U18: Jml HS belum terwakili
A19: 13 | B19: Getah, gom & resin nabati | C19: =COUNTIFS(Data_HS!$F$2:$F$8217,A19,Data_HS!$D$2:$D$8217,">0") -> 16 | D19: =SUMIFS(Data_HS!$C$2:$C$8217,Data_HS!$F$2:$F$8217,A19)/10^9 -> 0.060181227 | E19: =SUMIFS(Data_HS!$D$2:$D$8217,Data_HS!$F$2:$F$8217,A19)/10^9 -> 0.1790012 | F19: =E19/$E$105 -> 0.00076290967 | G19: =IFERROR(SUMIFS(Data_HS!$D$2:$D$8217,Data_HS!$F$2:$F$8217,A19,Data_HS!$C$2:$C$8217,">0")/SUMIFS(Data_HS!$C$2:$C$8217,Data_HS!$F$2:$F$8217,A19),"") -> 2.9743673 | H19: =COUNTIF(Data_Eksportir!$O$2:$O$3401,A19) -> 7 | I19: =IF(A19=0,"",H19/COUNTIF(Data_Eksportir!$O$2:$O$3401,">0")) -> 0.0022631749 | J19: =IF(OR(A19=0,F19=0),"",I19/F19) -> 2.9665044 | K19: =COUNTIFS(Data_HS!$F$2:$F$8217,A19,Data_HS!$I$2:$I$8217,"Belum terwakili") -> 2 | L19: =SUMIFS(Data_HS!$D$2:$D$8217,Data_HS!$F$2:$F$8217,A19,Data_HS!$I$2:$I$8217,"Belum terwakili")/10^9 -> 0.14629173 | M19: =SUMIFS(Data_Eksportir!$N$2:$N$3401,Data_Eksportir!$O$2:$O$3401,A19,Data_Eksportir!$Q$2:$Q$3401,"Wajar")/10^6 -> 0.024429917 | N19: =E19+ROW()/10^9 -> 0.17900121 | O19: =L19+ROW()/10^9 -> 0.14629175 | Q19: 1 | R19: =MATCH(LARGE($O$6:$O$104,Q19),$O$6:$O$104,0) -> 73 | S19: =TEXT(INDEX($A$6:$A$104,R19),"00")&" · "&INDEX($B$6:$B$104,R19) -> 72 · Besi & baja | T19: =INDEX($L$6:$L$104,R19) -> 24.445481 | U19: =INDEX($K$6:$K$104,R19) -> 31
A20: 14 | B20: Bahan anyaman nabati | C20: =COUNTIFS(Data_HS!$F$2:$F$8217,A20,Data_HS!$D$2:$D$8217,">0") -> 8 | D20: =SUMIFS(Data_HS!$C$2:$C$8217,Data_HS!$F$2:$F$8217,A20)/10^9 -> 5.4643838 | E20: =SUMIFS(Data_HS!$D$2:$D$8217,Data_HS!$F$2:$F$8217,A20)/10^9 -> 0.57399589 | F20: =E20/$E$105 -> 0.0024463916 | G20: =IFERROR(SUMIFS(Data_HS!$D$2:$D$8217,Data_HS!$F$2:$F$8217,A20,Data_HS!$C$2:$C$8217,">0")/SUMIFS(Data_HS!$C$2:$C$8217,Data_HS!$F$2:$F$8217,A20),"") -> 0.10504311 | H20: =COUNTIF(Data_Eksportir!$O$2:$O$3401,A20) -> 54 | I20: =IF(A20=0,"",H20/COUNTIF(Data_Eksportir!$O$2:$O$3401,">0")) -> 0.017458778 | J20: =IF(OR(A20=0,F20=0),"",I20/F20) -> 7.1365427 | K20: =COUNTIFS(Data_HS!$F$2:$F$8217,A20,Data_HS!$I$2:$I$8217,"Belum terwakili") -> 0 | L20: =SUMIFS(Data_HS!$D$2:$D$8217,Data_HS!$F$2:$F$8217,A20,Data_HS!$I$2:$I$8217,"Belum terwakili")/10^9 -> 0 | M20: =SUMIFS(Data_Eksportir!$N$2:$N$3401,Data_Eksportir!$O$2:$O$3401,A20,Data_Eksportir!$Q$2:$Q$3401,"Wajar")/10^6 -> 27.890816 | N20: =E20+ROW()/10^9 -> 0.57399591 | O20: =L20+ROW()/10^9 -> 2e-08 | Q20: 2 | R20: =MATCH(LARGE($O$6:$O$104,Q20),$O$6:$O$104,0) -> 16 | S20: =TEXT(INDEX($A$6:$A$104,R20),"00")&" · "&INDEX($B$6:$B$104,R20) -> 15 · Lemak & minyak nabati/hewani | T20: =INDEX($L$6:$L$104,R20) -> 23.230673 | U20: =INDEX($K$6:$K$104,R20) -> 28
A21: 15 | B21: Lemak & minyak nabati/hewani | C21: =COUNTIFS(Data_HS!$F$2:$F$8217,A21,Data_HS!$D$2:$D$8217,">0") -> 111 | D21: =SUMIFS(Data_HS!$C$2:$C$8217,Data_HS!$F$2:$F$8217,A21)/10^9 -> 27.846508 | E21: =SUMIFS(Data_HS!$D$2:$D$8217,Data_HS!$F$2:$F$8217,A21)/10^9 -> 30.574903 | F21: =E21/$E$105 -> 0.13031136 | G21: =IFERROR(SUMIFS(Data_HS!$D$2:$D$8217,Data_HS!$F$2:$F$8217,A21,Data_HS!$C$2:$C$8217,">0")/SUMIFS(Data_HS!$C$2:$C$8217,Data_HS!$F$2:$F$8217,A21),"") -> 1.0979798 | H21: =COUNTIF(Data_Eksportir!$O$2:$O$3401,A21) -> 130 | I21: =IF(A21=0,"",H21/COUNTIF(Data_Eksportir!$O$2:$O$3401,">0")) -> 0.042030391 | J21: =IF(OR(A21=0,F21=0),"",I21/F21) -> 0.3225382 | K21: =COUNTIFS(Data_HS!$F$2:$F$8217,A21,Data_HS!$I$2:$I$8217,"Belum terwakili") -> 28 | L21: =SUMIFS(Data_HS!$D$2:$D$8217,Data_HS!$F$2:$F$8217,A21,Data_HS!$I$2:$I$8217,"Belum terwakili")/10^9 -> 23.230673 | M21: =SUMIFS(Data_Eksportir!$N$2:$N$3401,Data_Eksportir!$O$2:$O$3401,A21,Data_Eksportir!$Q$2:$Q$3401,"Wajar")/10^6 -> 195.82758 | N21: =E21+ROW()/10^9 -> 30.574903 | O21: =L21+ROW()/10^9 -> 23.230673 | Q21: 3 | R21: =MATCH(LARGE($O$6:$O$104,Q21),$O$6:$O$104,0) -> 28 | S21: =TEXT(INDEX($A$6:$A$104,R21),"00")&" · "&INDEX($B$6:$B$104,R21) -> 27 · Batubara, migas & bahan bakar | T21: =INDEX($L$6:$L$104,R21) -> 21.471178 | U21: =INDEX($K$6:$K$104,R21) -> 22
A22: 16 | B22: Olahan daging & ikan | C22: =COUNTIFS(Data_HS!$F$2:$F$8217,A22,Data_HS!$D$2:$D$8217,">0") -> 63 | D22: =SUMIFS(Data_HS!$C$2:$C$8217,Data_HS!$F$2:$F$8217,A22)/10^9 -> 0.19626269 | E22: =SUMIFS(Data_HS!$D$2:$D$8217,Data_HS!$F$2:$F$8217,A22)/10^9 -> 1.3531696 | F22: =E22/$E$105 -> 0.0057672585 | G22: =IFERROR(SUMIFS(Data_HS!$D$2:$D$8217,Data_HS!$F$2:$F$8217,A22,Data_HS!$C$2:$C$8217,">0")/SUMIFS(Data_HS!$C$2:$C$8217,Data_HS!$F$2:$F$8217,A22),"") -> 6.8946859 | H22: =COUNTIF(Data_Eksportir!$O$2:$O$3401,A22) -> 9 | I22: =IF(A22=0,"",H22/COUNTIF(Data_Eksportir!$O$2:$O$3401,">0")) -> 0.0029097963 | J22: =IF(OR(A22=0,F22=0),"",I22/F22) -> 0.50453717 | K22: =COUNTIFS(Data_HS!$F$2:$F$8217,A22,Data_HS!$I$2:$I$8217,"Belum terwakili") -> 14 | L22: =SUMIFS(Data_HS!$D$2:$D$8217,Data_HS!$F$2:$F$8217,A22,Data_HS!$I$2:$I$8217,"Belum terwakili")/10^9 -> 1.2878734 | M22: =SUMIFS(Data_Eksportir!$N$2:$N$3401,Data_Eksportir!$O$2:$O$3401,A22,Data_Eksportir!$Q$2:$Q$3401,"Wajar")/10^6 -> 0.72277498 | N22: =E22+ROW()/10^9 -> 1.3531696 | O22: =L22+ROW()/10^9 -> 1.2878734 | Q22: 4 | R22: =MATCH(LARGE($O$6:$O$104,Q22),$O$6:$O$104,0) -> 85 | S22: =TEXT(INDEX($A$6:$A$104,R22),"00")&" · "&INDEX($B$6:$B$104,R22) -> 85 · Mesin listrik & elektronik | T22: =INDEX($L$6:$L$104,R22) -> 15.585381 | U22: =INDEX($K$6:$K$104,R22) -> 141
A23: 17 | B23: Gula & kembang gula | C23: =COUNTIFS(Data_HS!$F$2:$F$8217,A23,Data_HS!$D$2:$D$8217,">0") -> 32 | D23: =SUMIFS(Data_HS!$C$2:$C$8217,Data_HS!$F$2:$F$8217,A23)/10^9 -> 0.90922792 | E23: =SUMIFS(Data_HS!$D$2:$D$8217,Data_HS!$F$2:$F$8217,A23)/10^9 -> 0.42006576 | F23: =E23/$E$105 -> 0.0017903357 | G23: =IFERROR(SUMIFS(Data_HS!$D$2:$D$8217,Data_HS!$F$2:$F$8217,A23,Data_HS!$C$2:$C$8217,">0")/SUMIFS(Data_HS!$C$2:$C$8217,Data_HS!$F$2:$F$8217,A23),"") -> 0.4620027 | H23: =COUNTIF(Data_Eksportir!$O$2:$O$3401,A23) -> 81 | I23: =IF(A23=0,"",H23/COUNTIF(Data_Eksportir!$O$2:$O$3401,">0")) -> 0.026188167 | J23: =IF(OR(A23=0,F23=0),"",I23/F23) -> 14.627518 | K23: =COUNTIFS(Data_HS!$F$2:$F$8217,A23,Data_HS!$I$2:$I$8217,"Belum terwakili") -> 5 | L23: =SUMIFS(Data_HS!$D$2:$D$8217,Data_HS!$F$2:$F$8217,A23,Data_HS!$I$2:$I$8217,"Belum terwakili")/10^9 -> 0.36451348 | M23: =SUMIFS(Data_Eksportir!$N$2:$N$3401,Data_Eksportir!$O$2:$O$3401,A23,Data_Eksportir!$Q$2:$Q$3401,"Wajar")/10^6 -> 4.0470731 | N23: =E23+ROW()/10^9 -> 0.42006578 | O23: =L23+ROW()/10^9 -> 0.3645135 | Q23: 5 | R23: =MATCH(LARGE($O$6:$O$104,Q23),$O$6:$O$104,0) -> 72 | S23: =TEXT(INDEX($A$6:$A$104,R23),"00")&" · "&INDEX($B$6:$B$104,R23) -> 71 · Mutiara, permata & logam mulia | T23: =INDEX($L$6:$L$104,R23) -> 10.678077 | U23: =INDEX($K$6:$K$104,R23) -> 11
A24: 18 | B24: Kakao & olahannya | C24: =COUNTIFS(Data_HS!$F$2:$F$8217,A24,Data_HS!$D$2:$D$8217,">0") -> 16 | D24: =SUMIFS(Data_HS!$C$2:$C$8217,Data_HS!$F$2:$F$8217,A24)/10^9 -> 0.31666107 | E24: =SUMIFS(Data_HS!$D$2:$D$8217,Data_HS!$F$2:$F$8217,A24)/10^9 -> 3.3654286 | F24: =E24/$E$105 -> 0.01434358 | G24: =IFERROR(SUMIFS(Data_HS!$D$2:$D$8217,Data_HS!$F$2:$F$8217,A24,Data_HS!$C$2:$C$8217,">0")/SUMIFS(Data_HS!$C$2:$C$8217,Data_HS!$F$2:$F$8217,A24),"") -> 10.627857 | H24: =COUNTIF(Data_Eksportir!$O$2:$O$3401,A24) -> 93 | I24: =IF(A24=0,"",H24/COUNTIF(Data_Eksportir!$O$2:$O$3401,">0")) -> 0.030067895 | J24: =IF(OR(A24=0,F24=0),"",I24/F24) -> 2.0962615 | K24: =COUNTIFS(Data_HS!$F$2:$F$8217,A24,Data_HS!$I$2:$I$8217,"Belum terwakili") -> 3 | L24: =SUMIFS(Data_HS!$D$2:$D$8217,Data_HS!$F$2:$F$8217,A24,Data_HS!$I$2:$I$8217,"Belum terwakili")/10^9 -> 0.30437157 | M24: =SUMIFS(Data_Eksportir!$N$2:$N$3401,Data_Eksportir!$O$2:$O$3401,A24,Data_Eksportir!$Q$2:$Q$3401,"Wajar")/10^6 -> 170.56714 | N24: =E24+ROW()/10^9 -> 3.3654286 | O24: =L24+ROW()/10^9 -> 0.3043716 | Q24: 6 | R24: =MATCH(LARGE($O$6:$O$104,Q24),$O$6:$O$104,0) -> 87 | S24: =TEXT(INDEX($A$6:$A$104,R24),"00")&" · "&INDEX($B$6:$B$104,R24) -> 87 · Kendaraan bermotor | T24: =INDEX($L$6:$L$104,R24) -> 10.599114 | U24: =INDEX($K$6:$K$104,R24) -> 72
A25: 19 | B25: Olahan tepung & roti | C25: =COUNTIFS(Data_HS!$F$2:$F$8217,A25,Data_HS!$D$2:$D$8217,">0") -> 57 | D25: =SUMIFS(Data_HS!$C$2:$C$8217,Data_HS!$F$2:$F$8217,A25)/10^9 -> 0.6605908 | E25: =SUMIFS(Data_HS!$D$2:$D$8217,Data_HS!$F$2:$F$8217,A25)/10^9 -> 1.5250503 | F25: =E25/$E$105 -> 0.0064998203 | G25: =IFERROR(SUMIFS(Data_HS!$D$2:$D$8217,Data_HS!$F$2:$F$8217,A25,Data_HS!$C$2:$C$8217,">0")/SUMIFS(Data_HS!$C$2:$C$8217,Data_HS!$F$2:$F$8217,A25),"") -> 2.3086155 | H25: =COUNTIF(Data_Eksportir!$O$2:$O$3401,A25) -> 19 | I25: =IF(A25=0,"",H25/COUNTIF(Data_Eksportir!$O$2:$O$3401,">0")) -> 0.0061429033 | J25: =IF(OR(A25=0,F25=0),"",I25/F25) -> 0.94508818 | K25: =COUNTIFS(Data_HS!$F$2:$F$8217,A25,Data_HS!$I$2:$I$8217,"Belum terwakili") -> 12 | L25: =SUMIFS(Data_HS!$D$2:$D$8217,Data_HS!$F$2:$F$8217,A25,Data_HS!$I$2:$I$8217,"Belum terwakili")/10^9 -> 0.76684902 | M25: =SUMIFS(Data_Eksportir!$N$2:$N$3401,Data_Eksportir!$O$2:$O$3401,A25,Data_Eksportir!$Q$2:$Q$3401,"Wajar")/10^6 -> 0.94979613 | N25: =E25+ROW()/10^9 -> 1.5250503 | O25: =L25+ROW()/10^9 -> 0.76684904 | Q25: 7 | R25: =MATCH(LARGE($O$6:$O$104,Q25),$O$6:$O$104,0) -> 76 | S25: =TEXT(INDEX($A$6:$A$104,R25),"00")&" · "&INDEX($B$6:$B$104,R25) -> 75 · Nikel | T25: =INDEX($L$6:$L$104,R25) -> 8.4452439 | U25: =INDEX($K$6:$K$104,R25) -> 3
A26: 20 | B26: Olahan sayur & buah | C26: =COUNTIFS(Data_HS!$F$2:$F$8217,A26,Data_HS!$D$2:$D$8217,">0") -> 69 | D26: =SUMIFS(Data_HS!$C$2:$C$8217,Data_HS!$F$2:$F$8217,A26)/10^9 -> 0.26972792 | E26: =SUMIFS(Data_HS!$D$2:$D$8217,Data_HS!$F$2:$F$8217,A26)/10^9 -> 0.46093583 | F26: =E26/$E$105 -> 0.0019645254 | G26: =IFERROR(SUMIFS(Data_HS!$D$2:$D$8217,Data_HS!$F$2:$F$8217,A26,Data_HS!$C$2:$C$8217,">0")/SUMIFS(Data_HS!$C$2:$C$8217,Data_HS!$F$2:$F$8217,A26),"") -> 1.7088918 | H26: =COUNTIF(Data_Eksportir!$O$2:$O$3401,A26) -> 60 | I26: =IF(A26=0,"",H26/COUNTIF(Data_Eksportir!$O$2:$O$3401,">0")) -> 0.019398642 | J26: =IF(OR(A26=0,F26=0),"",I26/F26) -> 9.8744673 | K26: =COUNTIFS(Data_HS!$F$2:$F$8217,A26,Data_HS!$I$2:$I$8217,"Belum terwakili") -> 3 | L26: =SUMIFS(Data_HS!$D$2:$D$8217,Data_HS!$F$2:$F$8217,A26,Data_HS!$I$2:$I$8217,"Belum terwakili")/10^9 -> 0.31454055 | M26: =SUMIFS(Data_Eksportir!$N$2:$N$3401,Data_Eksportir!$O$2:$O$3401,A26,Data_Eksportir!$Q$2:$Q$3401,"Wajar")/10^6 -> 1.0353413 | N26: =E26+ROW()/10^9 -> 0.46093585 | O26: =L26+ROW()/10^9 -> 0.31454057 | Q26: 8 | R26: =MATCH(LARGE($O$6:$O$104,Q26),$O$6:$O$104,0) -> 84 | S26: =TEXT(INDEX($A$6:$A$104,R26),"00")&" · "&INDEX($B$6:$B$104,R26) -> 84 · Mesin & peralatan mekanis | T26: =INDEX($L$6:$L$104,R26) -> 6.6888486 | U26: =INDEX($K$6:$K$104,R26) -> 96
A27: 21 | B27: Olahan makanan lainnya | C27: =COUNTIFS(Data_HS!$F$2:$F$8217,A27,Data_HS!$D$2:$D$8217,">0") -> 56 | D27: =SUMIFS(Data_HS!$C$2:$C$8217,Data_HS!$F$2:$F$8217,A27)/10^9 -> 0.67347292 | E27: =SUMIFS(Data_HS!$D$2:$D$8217,Data_HS!$F$2:$F$8217,A27)/10^9 -> 1.7877899 | F27: =E27/$E$105 -> 0.0076196264 | G27: =IFERROR(SUMIFS(Data_HS!$D$2:$D$8217,Data_HS!$F$2:$F$8217,A27,Data_HS!$C$2:$C$8217,">0")/SUMIFS(Data_HS!$C$2:$C$8217,Data_HS!$F$2:$F$8217,A27),"") -> 2.6545832 | H27: =COUNTIF(Data_Eksportir!$O$2:$O$3401,A27) -> 51 | I27: =IF(A27=0,"",H27/COUNTIF(Data_Eksportir!$O$2:$O$3401,">0")) -> 0.016488846 | J27: =IF(OR(A27=0,F27=0),"",I27/F27) -> 2.1639966 | K27: =COUNTIFS(Data_HS!$F$2:$F$8217,A27,Data_HS!$I$2:$I$8217,"Belum terwakili") -> 14 | L27: =SUMIFS(Data_HS!$D$2:$D$8217,Data_HS!$F$2:$F$8217,A27,Data_HS!$I$2:$I$8217,"Belum terwakili")/10^9 -> 0.80312026 | M27: =SUMIFS(Data_Eksportir!$N$2:$N$3401,Data_Eksportir!$O$2:$O$3401,A27,Data_Eksportir!$Q$2:$Q$3401,"Wajar")/10^6 -> 1.0149949 | N27: =E27+ROW()/10^9 -> 1.78779 | O27: =L27+ROW()/10^9 -> 0.80312029 | Q27: 9 | R27: =MATCH(LARGE($O$6:$O$104,Q27),$O$6:$O$104,0) -> 39 | S27: =TEXT(INDEX($A$6:$A$104,R27),"00")&" · "&INDEX($B$6:$B$104,R27) -> 38 · Produk kimia lainnya | T27: =INDEX($L$6:$L$104,R27) -> 6.5637392 | U27: =INDEX($K$6:$K$104,R27) -> 26
A28: 22 | B28: Minuman & cuka | C28: =COUNTIFS(Data_HS!$F$2:$F$8217,A28,Data_HS!$D$2:$D$8217,">0") -> 47 | D28: =SUMIFS(Data_HS!$C$2:$C$8217,Data_HS!$F$2:$F$8217,A28)/10^9 -> 0.44864151 | E28: =SUMIFS(Data_HS!$D$2:$D$8217,Data_HS!$F$2:$F$8217,A28)/10^9 -> 0.28287226 | F28: =E28/$E$105 -> 0.001205612 | G28: =IFERROR(SUMIFS(Data_HS!$D$2:$D$8217,Data_HS!$F$2:$F$8217,A28,Data_HS!$C$2:$C$8217,">0")/SUMIFS(Data_HS!$C$2:$C$8217,Data_HS!$F$2:$F$8217,A28),"") -> 0.63050812 | H28: =COUNTIF(Data_Eksportir!$O$2:$O$3401,A28) -> 8 | I28: =IF(A28=0,"",H28/COUNTIF(Data_Eksportir!$O$2:$O$3401,">0")) -> 0.0025864856 | J28: =IF(OR(A28=0,F28=0),"",I28/F28) -> 2.1453716 | K28: =COUNTIFS(Data_HS!$F$2:$F$8217,A28,Data_HS!$I$2:$I$8217,"Belum terwakili") -> 6 | L28: =SUMIFS(Data_HS!$D$2:$D$8217,Data_HS!$F$2:$F$8217,A28,Data_HS!$I$2:$I$8217,"Belum terwakili")/10^9 -> 0.24882477 | M28: =SUMIFS(Data_Eksportir!$N$2:$N$3401,Data_Eksportir!$O$2:$O$3401,A28,Data_Eksportir!$Q$2:$Q$3401,"Wajar")/10^6 -> 0 | N28: =E28+ROW()/10^9 -> 0.28287229 | O28: =L28+ROW()/10^9 -> 0.2488248 | Q28: 10 | R28: =MATCH(LARGE($O$6:$O$104,Q28),$O$6:$O$104,0) -> 65 | S28: =TEXT(INDEX($A$6:$A$104,R28),"00")&" · "&INDEX($B$6:$B$104,R28) -> 64 · Alas kaki | T28: =INDEX($L$6:$L$104,R28) -> 5.0616357 | U28: =INDEX($K$6:$K$104,R28) -> 16
A29: 23 | B29: Sisa industri & pakan ternak | C29: =COUNTIFS(Data_HS!$F$2:$F$8217,A29,Data_HS!$D$2:$D$8217,">0") -> 32 | D29: =SUMIFS(Data_HS!$C$2:$C$8217,Data_HS!$F$2:$F$8217,A29)/10^9 -> 5.7881414 | E29: =SUMIFS(Data_HS!$D$2:$D$8217,Data_HS!$F$2:$F$8217,A29)/10^9 -> 0.91550182 | F29: =E29/$E$105 -> 0.0039019024 | G29: =IFERROR(SUMIFS(Data_HS!$D$2:$D$8217,Data_HS!$F$2:$F$8217,A29,Data_HS!$C$2:$C$8217,">0")/SUMIFS(Data_HS!$C$2:$C$8217,Data_HS!$F$2:$F$8217,A29),"") -> 0.15816853 | H29: =COUNTIF(Data_Eksportir!$O$2:$O$3401,A29) -> 54 | I29: =IF(A29=0,"",H29/COUNTIF(Data_Eksportir!$O$2:$O$3401,">0")) -> 0.017458778 | J29: =IF(OR(A29=0,F29=0),"",I29/F29) -> 4.4744271 | K29: =COUNTIFS(Data_HS!$F$2:$F$8217,A29,Data_HS!$I$2:$I$8217,"Belum terwakili") -> 8 | L29: =SUMIFS(Data_HS!$D$2:$D$8217,Data_HS!$F$2:$F$8217,A29,Data_HS!$I$2:$I$8217,"Belum terwakili")/10^9 -> 0.57117411 | M29: =SUMIFS(Data_Eksportir!$N$2:$N$3401,Data_Eksportir!$O$2:$O$3401,A29,Data_Eksportir!$Q$2:$Q$3401,"Wajar")/10^6 -> 3.3034961 | N29: =E29+ROW()/10^9 -> 0.91550185 | O29: =L29+ROW()/10^9 -> 0.57117414
A30: 24 | B30: Tembakau & rokok | C30: =COUNTIFS(Data_HS!$F$2:$F$8217,A30,Data_HS!$D$2:$D$8217,">0") -> 36 | D30: =SUMIFS(Data_HS!$C$2:$C$8217,Data_HS!$F$2:$F$8217,A30)/10^9 -> 0.16223312 | E30: =SUMIFS(Data_HS!$D$2:$D$8217,Data_HS!$F$2:$F$8217,A30)/10^9 -> 2.1071463 | F30: =E30/$E$105 -> 0.0089807348 | G30: =IFERROR(SUMIFS(Data_HS!$D$2:$D$8217,Data_HS!$F$2:$F$8217,A30,Data_HS!$C$2:$C$8217,">0")/SUMIFS(Data_HS!$C$2:$C$8217,Data_HS!$F$2:$F$8217,A30),"") -> 12.988385 | H30: =COUNTIF(Data_Eksportir!$O$2:$O$3401,A30) -> 45 | I30: =IF(A30=0,"",H30/COUNTIF(Data_Eksportir!$O$2:$O$3401,">0")) -> 0.014548982 | J30: =IF(OR(A30=0,F30=0),"",I30/F30) -> 1.6200213 | K30: =COUNTIFS(Data_HS!$F$2:$F$8217,A30,Data_HS!$I$2:$I$8217,"Belum terwakili") -> 11 | L30: =SUMIFS(Data_HS!$D$2:$D$8217,Data_HS!$F$2:$F$8217,A30,Data_HS!$I$2:$I$8217,"Belum terwakili")/10^9 -> 1.5833145 | M30: =SUMIFS(Data_Eksportir!$N$2:$N$3401,Data_Eksportir!$O$2:$O$3401,A30,Data_Eksportir!$Q$2:$Q$3401,"Wajar")/10^6 -> 36.706014 | N30: =E30+ROW()/10^9 -> 2.1071463 | O30: =L30+ROW()/10^9 -> 1.5833145
A31: 25 | B31: Garam, belerang, semen & batu | C31: =COUNTIFS(Data_HS!$F$2:$F$8217,A31,Data_HS!$D$2:$D$8217,">0") -> 50 | D31: =SUMIFS(Data_HS!$C$2:$C$8217,Data_HS!$F$2:$F$8217,A31)/10^9 -> 24.609453 | E31: =SUMIFS(Data_HS!$D$2:$D$8217,Data_HS!$F$2:$F$8217,A31)/10^9 -> 0.55274645 | F31: =E31/$E$105 -> 0.0023558257 | G31: =IFERROR(SUMIFS(Data_HS!$D$2:$D$8217,Data_HS!$F$2:$F$8217,A31,Data_HS!$C$2:$C$8217,">0")/SUMIFS(Data_HS!$C$2:$C$8217,Data_HS!$F$2:$F$8217,A31),"") -> 0.022460737 | H31: =COUNTIF(Data_Eksportir!$O$2:$O$3401,A31) -> 22 | I31: =IF(A31=0,"",H31/COUNTIF(Data_Eksportir!$O$2:$O$3401,">0")) -> 0.0071128354 | J31: =IF(OR(A31=0,F31=0),"",I31/F31) -> 3.0192537 | K31: =COUNTIFS(Data_HS!$F$2:$F$8217,A31,Data_HS!$I$2:$I$8217,"Belum terwakili") -> 5 | L31: =SUMIFS(Data_HS!$D$2:$D$8217,Data_HS!$F$2:$F$8217,A31,Data_HS!$I$2:$I$8217,"Belum terwakili")/10^9 -> 0.44967179 | M31: =SUMIFS(Data_Eksportir!$N$2:$N$3401,Data_Eksportir!$O$2:$O$3401,A31,Data_Eksportir!$Q$2:$Q$3401,"Wajar")/10^6 -> 0.041372254 | N31: =E31+ROW()/10^9 -> 0.55274648 | O31: =L31+ROW()/10^9 -> 0.44967183
A32: 26 | B32: Bijih, terak & abu logam | C32: =COUNTIFS(Data_HS!$F$2:$F$8217,A32,Data_HS!$D$2:$D$8217,">0") -> 15 | D32: =SUMIFS(Data_HS!$C$2:$C$8217,Data_HS!$F$2:$F$8217,A32)/10^9 -> 2.8581045 | E32: =SUMIFS(Data_HS!$D$2:$D$8217,Data_HS!$F$2:$F$8217,A32)/10^9 -> 4.6904165 | F32: =E32/$E$105 -> 0.019990727 | G32: =IFERROR(SUMIFS(Data_HS!$D$2:$D$8217,Data_HS!$F$2:$F$8217,A32,Data_HS!$C$2:$C$8217,">0")/SUMIFS(Data_HS!$C$2:$C$8217,Data_HS!$F$2:$F$8217,A32),"") -> 1.6410934 | H32: =COUNTIF(Data_Eksportir!$O$2:$O$3401,A32) -> 8 | I32: =IF(A32=0,"",H32/COUNTIF(Data_Eksportir!$O$2:$O$3401,">0")) -> 0.0025864856 | J32: =IF(OR(A32=0,F32=0),"",I32/F32) -> 0.12938427 | K32: =COUNTIFS(Data_HS!$F$2:$F$8217,A32,Data_HS!$I$2:$I$8217,"Belum terwakili") -> 4 | L32: =SUMIFS(Data_HS!$D$2:$D$8217,Data_HS!$F$2:$F$8217,A32,Data_HS!$I$2:$I$8217,"Belum terwakili")/10^9 -> 4.667153 | M32: =SUMIFS(Data_Eksportir!$N$2:$N$3401,Data_Eksportir!$O$2:$O$3401,A32,Data_Eksportir!$Q$2:$Q$3401,"Wajar")/10^6 -> 0.025444443 | N32: =E32+ROW()/10^9 -> 4.6904165 | O32: =L32+ROW()/10^9 -> 4.6671531
A33: 27 | B33: Batubara, migas & bahan bakar | C33: =COUNTIFS(Data_HS!$F$2:$F$8217,A33,Data_HS!$D$2:$D$8217,">0") -> 53 | D33: =SUMIFS(Data_HS!$C$2:$C$8217,Data_HS!$F$2:$F$8217,A33)/10^9 -> 91.808234 | E33: =SUMIFS(Data_HS!$D$2:$D$8217,Data_HS!$F$2:$F$8217,A33)/10^9 -> 23.823585 | F33: =E33/$E$105 -> 0.101537 | G33: =IFERROR(SUMIFS(Data_HS!$D$2:$D$8217,Data_HS!$F$2:$F$8217,A33,Data_HS!$C$2:$C$8217,">0")/SUMIFS(Data_HS!$C$2:$C$8217,Data_HS!$F$2:$F$8217,A33),"") -> 0.20447042 | H33: =COUNTIF(Data_Eksportir!$O$2:$O$3401,A33) -> 33 | I33: =IF(A33=0,"",H33/COUNTIF(Data_Eksportir!$O$2:$O$3401,">0")) -> 0.010669253 | J33: =IF(OR(A33=0,F33=0),"",I33/F33) -> 0.10507749 | K33: =COUNTIFS(Data_HS!$F$2:$F$8217,A33,Data_HS!$I$2:$I$8217,"Belum terwakili") -> 22 | L33: =SUMIFS(Data_HS!$D$2:$D$8217,Data_HS!$F$2:$F$8217,A33,Data_HS!$I$2:$I$8217,"Belum terwakili")/10^9 -> 21.471178 | M33: =SUMIFS(Data_Eksportir!$N$2:$N$3401,Data_Eksportir!$O$2:$O$3401,A33,Data_Eksportir!$Q$2:$Q$3401,"Wajar")/10^6 -> 36.307329 | N33: =E33+ROW()/10^9 -> 23.823585 | O33: =L33+ROW()/10^9 -> 21.471178
A34: 28 | B34: Kimia anorganik | C34: =COUNTIFS(Data_HS!$F$2:$F$8217,A34,Data_HS!$D$2:$D$8217,">0") -> 127 | D34: =SUMIFS(Data_HS!$C$2:$C$8217,Data_HS!$F$2:$F$8217,A34)/10^9 -> 6.8996891 | E34: =SUMIFS(Data_HS!$D$2:$D$8217,Data_HS!$F$2:$F$8217,A34)/10^9 -> 4.1171817 | F34: =E34/$E$105 -> 0.01754758 | G34: =IFERROR(SUMIFS(Data_HS!$D$2:$D$8217,Data_HS!$F$2:$F$8217,A34,Data_HS!$C$2:$C$8217,">0")/SUMIFS(Data_HS!$C$2:$C$8217,Data_HS!$F$2:$F$8217,A34),"") -> 0.59671988 | H34: =COUNTIF(Data_Eksportir!$O$2:$O$3401,A34) -> 6 | I34: =IF(A34=0,"",H34/COUNTIF(Data_Eksportir!$O$2:$O$3401,">0")) -> 0.0019398642 | J34: =IF(OR(A34=0,F34=0),"",I34/F34) -> 0.11054882 | K34: =COUNTIFS(Data_HS!$F$2:$F$8217,A34,Data_HS!$I$2:$I$8217,"Belum terwakili") -> 16 | L34: =SUMIFS(Data_HS!$D$2:$D$8217,Data_HS!$F$2:$F$8217,A34,Data_HS!$I$2:$I$8217,"Belum terwakili")/10^9 -> 3.7680205 | M34: =SUMIFS(Data_Eksportir!$N$2:$N$3401,Data_Eksportir!$O$2:$O$3401,A34,Data_Eksportir!$Q$2:$Q$3401,"Wajar")/10^6 -> 0.001398722 | N34: =E34+ROW()/10^9 -> 4.1171817 | O34: =L34+ROW()/10^9 -> 3.7680206
A35: 29 | B35: Kimia organik | C35: =COUNTIFS(Data_HS!$F$2:$F$8217,A35,Data_HS!$D$2:$D$8217,">0") -> 278 | D35: =SUMIFS(Data_HS!$C$2:$C$8217,Data_HS!$F$2:$F$8217,A35)/10^9 -> 3.7068386 | E35: =SUMIFS(Data_HS!$D$2:$D$8217,Data_HS!$F$2:$F$8217,A35)/10^9 -> 3.965024 | F35: =E35/$E$105 -> 0.016899078 | G35: =IFERROR(SUMIFS(Data_HS!$D$2:$D$8217,Data_HS!$F$2:$F$8217,A35,Data_HS!$C$2:$C$8217,">0")/SUMIFS(Data_HS!$C$2:$C$8217,Data_HS!$F$2:$F$8217,A35),"") -> 1.0696509 | H35: =COUNTIF(Data_Eksportir!$O$2:$O$3401,A35) -> 3 | I35: =IF(A35=0,"",H35/COUNTIF(Data_Eksportir!$O$2:$O$3401,">0")) -> 0.0009699321 | J35: =IF(OR(A35=0,F35=0),"",I35/F35) -> 0.057395563 | K35: =COUNTIFS(Data_HS!$F$2:$F$8217,A35,Data_HS!$I$2:$I$8217,"Belum terwakili") -> 38 | L35: =SUMIFS(Data_HS!$D$2:$D$8217,Data_HS!$F$2:$F$8217,A35,Data_HS!$I$2:$I$8217,"Belum terwakili")/10^9 -> 3.8425245 | M35: =SUMIFS(Data_Eksportir!$N$2:$N$3401,Data_Eksportir!$O$2:$O$3401,A35,Data_Eksportir!$Q$2:$Q$3401,"Wajar")/10^6 -> 0 | N35: =E35+ROW()/10^9 -> 3.9650241 | O35: =L35+ROW()/10^9 -> 3.8425246
A36: 30 | B36: Farmasi | C36: =COUNTIFS(Data_HS!$F$2:$F$8217,A36,Data_HS!$D$2:$D$8217,">0") -> 86 | D36: =SUMIFS(Data_HS!$C$2:$C$8217,Data_HS!$F$2:$F$8217,A36)/10^9 -> 0.023487927 | E36: =SUMIFS(Data_HS!$D$2:$D$8217,Data_HS!$F$2:$F$8217,A36)/10^9 -> 0.68423699 | F36: =E36/$E$105 -> 0.0029162432 | G36: =IFERROR(SUMIFS(Data_HS!$D$2:$D$8217,Data_HS!$F$2:$F$8217,A36,Data_HS!$C$2:$C$8217,">0")/SUMIFS(Data_HS!$C$2:$C$8217,Data_HS!$F$2:$F$8217,A36),"") -> 29.131417 | H36: =COUNTIF(Data_Eksportir!$O$2:$O$3401,A36) -> 6 | I36: =IF(A36=0,"",H36/COUNTIF(Data_Eksportir!$O$2:$O$3401,">0")) -> 0.0019398642 | J36: =IF(OR(A36=0,F36=0),"",I36/F36) -> 0.66519288 | K36: =COUNTIFS(Data_HS!$F$2:$F$8217,A36,Data_HS!$I$2:$I$8217,"Belum terwakili") -> 13 | L36: =SUMIFS(Data_HS!$D$2:$D$8217,Data_HS!$F$2:$F$8217,A36,Data_HS!$I$2:$I$8217,"Belum terwakili")/10^9 -> 0.59631306 | M36: =SUMIFS(Data_Eksportir!$N$2:$N$3401,Data_Eksportir!$O$2:$O$3401,A36,Data_Eksportir!$Q$2:$Q$3401,"Wajar")/10^6 -> 0 | N36: =E36+ROW()/10^9 -> 0.68423703 | O36: =L36+ROW()/10^9 -> 0.59631309
A37: 31 | B37: Pupuk | C37: =COUNTIFS(Data_HS!$F$2:$F$8217,A37,Data_HS!$D$2:$D$8217,">0") -> 23 | D37: =SUMIFS(Data_HS!$C$2:$C$8217,Data_HS!$F$2:$F$8217,A37)/10^9 -> 1.9069557 | E37: =SUMIFS(Data_HS!$D$2:$D$8217,Data_HS!$F$2:$F$8217,A37)/10^9 -> 0.76641507 | F37: =E37/$E$105 -> 0.0032664892 | G37: =IFERROR(SUMIFS(Data_HS!$D$2:$D$8217,Data_HS!$F$2:$F$8217,A37,Data_HS!$C$2:$C$8217,">0")/SUMIFS(Data_HS!$C$2:$C$8217,Data_HS!$F$2:$F$8217,A37),"") -> 0.40190503 | H37: =COUNTIF(Data_Eksportir!$O$2:$O$3401,A37) -> 11 | I37: =IF(A37=0,"",H37/COUNTIF(Data_Eksportir!$O$2:$O$3401,">0")) -> 0.0035564177 | J37: =IF(OR(A37=0,F37=0),"",I37/F37) -> 1.0887585 | K37: =COUNTIFS(Data_HS!$F$2:$F$8217,A37,Data_HS!$I$2:$I$8217,"Belum terwakili") -> 4 | L37: =SUMIFS(Data_HS!$D$2:$D$8217,Data_HS!$F$2:$F$8217,A37,Data_HS!$I$2:$I$8217,"Belum terwakili")/10^9 -> 0.73318268 | M37: =SUMIFS(Data_Eksportir!$N$2:$N$3401,Data_Eksportir!$O$2:$O$3401,A37,Data_Eksportir!$Q$2:$Q$3401,"Wajar")/10^6 -> 0.35003501 | N37: =E37+ROW()/10^9 -> 0.76641511 | O37: =L37+ROW()/10^9 -> 0.73318272
A38: 32 | B38: Pewarna, cat & pernis | C38: =COUNTIFS(Data_HS!$F$2:$F$8217,A38,Data_HS!$D$2:$D$8217,">0") -> 73 | D38: =SUMIFS(Data_HS!$C$2:$C$8217,Data_HS!$F$2:$F$8217,A38)/10^9 -> 0.13728833 | E38: =SUMIFS(Data_HS!$D$2:$D$8217,Data_HS!$F$2:$F$8217,A38)/10^9 -> 0.41810061 | F38: =E38/$E$105 -> 0.0017819601 | G38: =IFERROR(SUMIFS(Data_HS!$D$2:$D$8217,Data_HS!$F$2:$F$8217,A38,Data_HS!$C$2:$C$8217,">0")/SUMIFS(Data_HS!$C$2:$C$8217,Data_HS!$F$2:$F$8217,A38),"") -> 3.0454185 | H38: =COUNTIF(Data_Eksportir!$O$2:$O$3401,A38) -> 16 | I38: =IF(A38=0,"",H38/COUNTIF(Data_Eksportir!$O$2:$O$3401,">0")) -> 0.0051729712 | J38: =IF(OR(A38=0,F38=0),"",I38/F38) -> 2.9029669 | K38: =COUNTIFS(Data_HS!$F$2:$F$8217,A38,Data_HS!$I$2:$I$8217,"Belum terwakili") -> 10 | L38: =SUMIFS(Data_HS!$D$2:$D$8217,Data_HS!$F$2:$F$8217,A38,Data_HS!$I$2:$I$8217,"Belum terwakili")/10^9 -> 0.27531779 | M38: =SUMIFS(Data_Eksportir!$N$2:$N$3401,Data_Eksportir!$O$2:$O$3401,A38,Data_Eksportir!$Q$2:$Q$3401,"Wajar")/10^6 -> 0.45161774 | N38: =E38+ROW()/10^9 -> 0.41810064 | O38: =L38+ROW()/10^9 -> 0.27531783
A39: 33 | B39: Minyak atsiri & kosmetik | C39: =COUNTIFS(Data_HS!$F$2:$F$8217,A39,Data_HS!$D$2:$D$8217,">0") -> 50 | D39: =SUMIFS(Data_HS!$C$2:$C$8217,Data_HS!$F$2:$F$8217,A39)/10^9 -> 0.13001755 | E39: =SUMIFS(Data_HS!$D$2:$D$8217,Data_HS!$F$2:$F$8217,A39)/10^9 -> 1.0498032 | F39: =E39/$E$105 -> 0.0044742996 | G39: =IFERROR(SUMIFS(Data_HS!$D$2:$D$8217,Data_HS!$F$2:$F$8217,A39,Data_HS!$C$2:$C$8217,">0")/SUMIFS(Data_HS!$C$2:$C$8217,Data_HS!$F$2:$F$8217,A39),"") -> 8.0743192 | H39: =COUNTIF(Data_Eksportir!$O$2:$O$3401,A39) -> 49 | I39: =IF(A39=0,"",H39/COUNTIF(Data_Eksportir!$O$2:$O$3401,">0")) -> 0.015842224 | J39: =IF(OR(A39=0,F39=0),"",I39/F39) -> 3.540716 | K39: =COUNTIFS(Data_HS!$F$2:$F$8217,A39,Data_HS!$I$2:$I$8217,"Belum terwakili") -> 14 | L39: =SUMIFS(Data_HS!$D$2:$D$8217,Data_HS!$F$2:$F$8217,A39,Data_HS!$I$2:$I$8217,"Belum terwakili")/10^9 -> 0.70894141 | M39: =SUMIFS(Data_Eksportir!$N$2:$N$3401,Data_Eksportir!$O$2:$O$3401,A39,Data_Eksportir!$Q$2:$Q$3401,"Wajar")/10^6 -> 3.6100428 | N39: =E39+ROW()/10^9 -> 1.0498032 | O39: =L39+ROW()/10^9 -> 0.70894145
A40: 34 | B40: Sabun & bahan pembersih | C40: =COUNTIFS(Data_HS!$F$2:$F$8217,A40,Data_HS!$D$2:$D$8217,">0") -> 64 | D40: =SUMIFS(Data_HS!$C$2:$C$8217,Data_HS!$F$2:$F$8217,A40)/10^9 -> 1.1703614 | E40: =SUMIFS(Data_HS!$D$2:$D$8217,Data_HS!$F$2:$F$8217,A40)/10^9 -> 1.3951377 | F40: =E40/$E$105 -> 0.0059461281 | G40: =IFERROR(SUMIFS(Data_HS!$D$2:$D$8217,Data_HS!$F$2:$F$8217,A40,Data_HS!$C$2:$C$8217,">0")/SUMIFS(Data_HS!$C$2:$C$8217,Data_HS!$F$2:$F$8217,A40),"") -> 1.1920571 | H40: =COUNTIF(Data_Eksportir!$O$2:$O$3401,A40) -> 11 | I40: =IF(A40=0,"",H40/COUNTIF(Data_Eksportir!$O$2:$O$3401,">0")) -> 0.0035564177 | J40: =IF(OR(A40=0,F40=0),"",I40/F40) -> 0.59810647 | K40: =COUNTIFS(Data_HS!$F$2:$F$8217,A40,Data_HS!$I$2:$I$8217,"Belum terwakili") -> 14 | L40: =SUMIFS(Data_HS!$D$2:$D$8217,Data_HS!$F$2:$F$8217,A40,Data_HS!$I$2:$I$8217,"Belum terwakili")/10^9 -> 1.2783745 | M40: =SUMIFS(Data_Eksportir!$N$2:$N$3401,Data_Eksportir!$O$2:$O$3401,A40,Data_Eksportir!$Q$2:$Q$3401,"Wajar")/10^6 -> 0.48992884 | N40: =E40+ROW()/10^9 -> 1.3951377 | O40: =L40+ROW()/10^9 -> 1.2783745
... A104: 99 | B104: Klasifikasi khusus (Bab 99) | C104: =COUNTIFS(Data_HS!$F$2:$F$8217,A104,Data_HS!$D$2:$D$8217,">0") -> 5 | D104: =SUMIFS(Data_HS!$C$2:$C$8217,Data_HS!$F$2:$F$8217,A104)/10^9 -> 0.001418043 | E104: =SUMIFS(Data_HS!$D$2:$D$8217,Data_HS!$F$2:$F$8217,A104)/10^9 -> 0.001325312 | F104: =E104/$E$105 -> 5.6485284e-06 | G104: =IFERROR(SUMIFS(Data_HS!$D$2:$D$8217,Data_HS!$F$2:$F$8217,A104,Data_HS!$C$2:$C$8217,">0")/SUMIFS(Data_HS!$C$2:$C$8217,Data_HS!$F$2:$F$8217,A104),"") -> 0.93460636 | H104: =COUNTIF(Data_Eksportir!$O$2:$O$3401,A104) -> 0 | I104: =IF(A104=0,"",H104/COUNTIF(Data_Eksportir!$O$2:$O$3401,">0")) -> 0 | J104: =IF(OR(A104=0,F104=0),"",I104/F104) -> 0 | K104: =COUNTIFS(Data_HS!$F$2:$F$8217,A104,Data_HS!$I$2:$I$8217,"Belum terwakili") -> 0 | L104: =SUMIFS(Data_HS!$D$2:$D$8217,Data_HS!$F$2:$F$8217,A104,Data_HS!$I$2:$I$8217,"Belum terwakili")/10^9 -> 0 | M104: =SUMIFS(Data_Eksportir!$N$2:$N$3401,Data_Eksportir!$O$2:$O$3401,A104,Data_Eksportir!$Q$2:$Q$3401,"Wajar")/10^6 -> 0 | N104: =E104+ROW()/10^9 -> 0.001325416 | O104: =L104+ROW()/10^9 -> 1.04e-07
A105: Total | B105: Seluruh bab | C105: =SUM(C6:C104) -> 8202 | D105: =SUM(D6:D104) -> 240.12678 | E105: =SUM(E6:E104) -> 234.62961 | F105: =SUM(F6:F104) -> 1 | G105: =SUMIFS(Data_HS!$D$2:$D$8217,Data_HS!$C$2:$C$8217,">0")/SUM(Data_HS!$C$2:$C$8217) -> 0.95607018 | H105: =SUM(H6:H104) -> 3400 | I105: =SUM(I6:I104) -> 1 | K105: =SUM(K6:K104) -> 1187 | L105: =SUM(L6:L104) -> 201.13034 | M105: =SUM(M6:M104) -> 694.46059

Sheet Top_HS
A1: Top Kode HS, Konsentrasi & Segmen Harga
A2: 50 kode HS dengan nilai ekspor terbesar (Jan–Nov 2025) dan struktur nilai vs volume
A4: 50 kode HS menurut nilai ekspor | O4: Konsentrasi nilai ekspor
A5: Peringkat | B5: Kode HS | C5: Deskripsi | D5: Bab | E5: Berat (ton) | F5: Nilai FOB (USD juta) | G5: Harga (USD/kg) | H5: Pangsa nilai | I5: Pangsa kumulatif | J5: Listing eksportir | K5: Status pasokan | L5: Baris (helper) | M5: Label grafik | O5: Kelompok | P5: Nilai (USD miliar) | Q5: Pangsa dari total
A6: 1 | B6: =INDEX(Data_HS!$A$2:$A$8217,$L6) -> 72026000 | C6: =INDEX(Data_HS!$B$2:$B$8217,$L6) -> Ferro-nickel | D6: =INDEX(Data_HS!$F$2:$F$8217,$L6) -> 72 | E6: =IF(INDEX(Data_HS!$C$2:$C$8217,$L6)="","",INDEX(Data_HS!$C$2:$C$8217,$L6)/1000) -> 10461948 | F6: =INDEX(Data_HS!$D$2:$D$8217,$L6)/10^6 -> 14941.058 | G6: =INDEX(Data_HS!$E$2:$E$8217,$L6) -> 1.4281334 | H6: =INDEX(Data_HS!$D$2:$D$8217,$L6)/SUM(Data_HS!$D$2:$D$8217) -> 0.063679337 | I6: =SUM($H$6:H6) -> 0.063679337 | J6: =INDEX(Data_HS!$G$2:$G$8217,$L6) -> 0 | K6: =INDEX(Data_HS!$I$2:$I$8217,$L6) -> Belum terwakili | L6: =MATCH(LARGE(Data_HS!$J$2:$J$8217,A6),Data_HS!$J$2:$J$8217,0) -> 4553 | M6: =B6&" · "&LEFT(C6,34)&IF(LEN(C6)>34,"…","") -> 72026000 · Ferro-nickel | O6: 10 | P6: =SUMIF(Data_HS!$D$2:$D$8217,">="&LARGE(Data_HS!$D$2:$D$8217,O6))/10^9 -> 63.083339 | Q6: =P6/$P$10 -> 0.26886351
A7: 2 | B7: =INDEX(Data_HS!$A$2:$A$8217,$L7) -> 15119037 | C7: =INDEX(Data_HS!$B$2:$B$8217,$L7) -> Liquid fractions of palm oil, refined oil, but not chemically modified, with iodine value 55 or more, but less than 60 | D7: =INDEX(Data_HS!$F$2:$F$8217,$L7) -> 15 | E7: =IF(INDEX(Data_HS!$C$2:$C$8217,$L7)="","",INDEX(Data_HS!$C$2:$C$8217,$L7)/1000) -> 9815509.1 | F7: =INDEX(Data_HS!$D$2:$D$8217,$L7)/10^6 -> 9998.5251 | G7: =INDEX(Data_HS!$E$2:$E$8217,$L7) -> 1.0186456 | H7: =INDEX(Data_HS!$D$2:$D$8217,$L7)/SUM(Data_HS!$D$2:$D$8217) -> 0.042614081 | I7: =SUM($H$6:H7) -> 0.10629342 | J7: =INDEX(Data_HS!$G$2:$G$8217,$L7) -> 0 | K7: =INDEX(Data_HS!$I$2:$I$8217,$L7) -> Belum terwakili | L7: =MATCH(LARGE(Data_HS!$J$2:$J$8217,A7),Data_HS!$J$2:$J$8217,0) -> 748 | M7: =B7&" · "&LEFT(C7,34)&IF(LEN(C7)>34,"…","") -> 15119037 · Liquid fractions of palm oil, refi… | O7: 50 | P7: =SUMIF(Data_HS!$D$2:$D$8217,">="&LARGE(Data_HS!$D$2:$D$8217,O7))/10^9 -> 125.91483 | Q7: =P7/$P$10 -> 0.53665365
A8: 3 | B8: =INDEX(Data_HS!$A$2:$A$8217,$L8) -> 71131990 | C8: =INDEX(Data_HS!$B$2:$B$8217,$L8) -> Articles of other precious metal jewellery (other than its parts), other than of silver, whether or not plated or clad with precious metal | D8: =INDEX(Data_HS!$F$2:$F$8217,$L8) -> 71 | E8: =IF(INDEX(Data_HS!$C$2:$C$8217,$L8)="","",INDEX(Data_HS!$C$2:$C$8217,$L8)/1000) -> 72.515 | F8: =INDEX(Data_HS!$D$2:$D$8217,$L8)/10^6 -> 6753.5157 | G8: =INDEX(Data_HS!$E$2:$E$8217,$L8) -> 93132.673 | H8: =INDEX(Data_HS!$D$2:$D$8217,$L8)/SUM(Data_HS!$D$2:$D$8217) -> 0.028783732 | I8: =SUM($H$6:H8) -> 0.13507715 | J8: =INDEX(Data_HS!$G$2:$G$8217,$L8) -> 0 | K8: =INDEX(Data_HS!$I$2:$I$8217,$L8) -> Belum terwakili | L8: =MATCH(LARGE(Data_HS!$J$2:$J$8217,A8),Data_HS!$J$2:$J$8217,0) -> 4527 | M8: =B8&" · "&LEFT(C8,34)&IF(LEN(C8)>34,"…","") -> 71131990 · Articles of other precious metal j… | O8: 100 | P8: =SUMIF(Data_HS!$D$2:$D$8217,">="&LARGE(Data_HS!$D$2:$D$8217,O8))/10^9 -> 153.9453 | Q8: =P8/$P$10 -> 0.65612052
A9: 4 | B9: =INDEX(Data_HS!$A$2:$A$8217,$L9) -> 15119020 | C9: =INDEX(Data_HS!$B$2:$B$8217,$L9) -> Refined palm oil | D9: =INDEX(Data_HS!$F$2:$F$8217,$L9) -> 15 | E9: =IF(INDEX(Data_HS!$C$2:$C$8217,$L9)="","",INDEX(Data_HS!$C$2:$C$8217,$L9)/1000) -> 5094685.2 | F9: =INDEX(Data_HS!$D$2:$D$8217,$L9)/10^6 -> 5248.687 | G9: =INDEX(Data_HS!$E$2:$E$8217,$L9) -> 1.0302279 | H9: =INDEX(Data_HS!$D$2:$D$8217,$L9)/SUM(Data_HS!$D$2:$D$8217) -> 0.022370097 | I9: =SUM($H$6:H9) -> 0.15744725 | J9: =INDEX(Data_HS!$G$2:$G$8217,$L9) -> 0 | K9: =INDEX(Data_HS!$I$2:$I$8217,$L9) -> Belum terwakili | L9: =MATCH(LARGE(Data_HS!$J$2:$J$8217,A9),Data_HS!$J$2:$J$8217,0) -> 744 | M9: =B9&" · "&LEFT(C9,34)&IF(LEN(C9)>34,"…","") -> 15119020 · Refined palm oil | O9: 500 | P9: =SUMIF(Data_HS!$D$2:$D$8217,">="&LARGE(Data_HS!$D$2:$D$8217,O9))/10^9 -> 207.43918 | Q9: =P9/$P$10 -> 0.88411341
A10: 5 | B10: =INDEX(Data_HS!$A$2:$A$8217,$L10) -> 27021000 | C10: =INDEX(Data_HS!$B$2:$B$8217,$L10) -> Lignite, whether or not pulverised, but not agglomerated | D10: =INDEX(Data_HS!$F$2:$F$8217,$L10) -> 27 | E10: =IF(INDEX(Data_HS!$C$2:$C$8217,$L10)="","",INDEX(Data_HS!$C$2:$C$8217,$L10)/1000) | F10: =INDEX(Data_HS!$D$2:$D$8217,$L10)/10^6 -> 5051.5174 | G10: =INDEX(Data_HS!$E$2:$E$8217,$L10) | H10: =INDEX(Data_HS!$D$2:$D$8217,$L10)/SUM(Data_HS!$D$2:$D$8217) -> 0.021529753 | I10: =SUM($H$6:H10) -> 0.178977 | J10: =INDEX(Data_HS!$G$2:$G$8217,$L10) -> 0 | K10: =INDEX(Data_HS!$I$2:$I$8217,$L10) -> Belum terwakili | L10: =MATCH(LARGE(Data_HS!$J$2:$J$8217,A10),Data_HS!$J$2:$J$8217,0) -> 1313 | M10: =B10&" · "&LEFT(C10,34)&IF(LEN(C10)>34,"…","") -> 27021000 · Lignite, whether or not pulverised… | O10: Total seluruh HS | P10: =SUM(Data_HS!$D$2:$D$8217)/10^9 -> 234.62961 | Q10: =P10/$P$10 -> 1
A11: 6 | B11: =INDEX(Data_HS!$A$2:$A$8217,$L11) -> 27111100 | C11: =INDEX(Data_HS!$B$2:$B$8217,$L11) -> Liquefied, natural gas | D11: =INDEX(Data_HS!$F$2:$F$8217,$L11) -> 27 | E11: =IF(INDEX(Data_HS!$C$2:$C$8217,$L11)="","",INDEX(Data_HS!$C$2:$C$8217,$L11)/1000) -> 9728691.7 | F11: =INDEX(Data_HS!$D$2:$D$8217,$L11)/10^6 -> 4966.8666 | G11: =INDEX(Data_HS!$E$2:$E$8217,$L11) -> 0.51053798 | H11: =INDEX(Data_HS!$D$2:$D$8217,$L11)/SUM(Data_HS!$D$2:$D$8217) -> 0.021168968 | I11: =SUM($H$6:H11) -> 0.20014597 | J11: =INDEX(Data_HS!$G$2:$G$8217,$L11) -> 0 | K11: =INDEX(Data_HS!$I$2:$I$8217,$L11) -> Belum terwakili | L11: =MATCH(LARGE(Data_HS!$J$2:$J$8217,A11),Data_HS!$J$2:$J$8217,0) -> 1345 | M11: =B11&" · "&LEFT(C11,34)&IF(LEN(C11)>34,"…","") -> 27111100 · Liquefied, natural gas
A12: 7 | B12: =INDEX(Data_HS!$A$2:$A$8217,$L12) -> 75012000 | C12: =INDEX(Data_HS!$B$2:$B$8217,$L12) -> Nickel oxide sinters and other intermediate products; of nickel metallurgy | D12: =INDEX(Data_HS!$F$2:$F$8217,$L12) -> 75 | E12: =IF(INDEX(Data_HS!$C$2:$C$8217,$L12)="","",INDEX(Data_HS!$C$2:$C$8217,$L12)/1000) -> 1818159.2 | F12: =INDEX(Data_HS!$D$2:$D$8217,$L12)/10^6 -> 4843.0894 | G12: =INDEX(Data_HS!$E$2:$E$8217,$L12) -> 2.6637322 | H12: =INDEX(Data_HS!$D$2:$D$8217,$L12)/SUM(Data_HS!$D$2:$D$8217) -> 0.020641425 | I12: =SUM($H$6:H12) -> 0.22078739 | J12: =INDEX(Data_HS!$G$2:$G$8217,$L12) -> 0 | K12: =INDEX(Data_HS!$I$2:$I$8217,$L12) -> Belum terwakili | L12: =MATCH(LARGE(Data_HS!$J$2:$J$8217,A12),Data_HS!$J$2:$J$8217,0) -> 5097 | M12: =B12&" · "&LEFT(C12,34)&IF(LEN(C12)>34,"…","") -> 75012000 · Nickel oxide sinters and other int…
A13: 8 | B13: =INDEX(Data_HS!$A$2:$A$8217,$L13) -> 26030000 | C13: =INDEX(Data_HS!$B$2:$B$8217,$L13) -> Copper ores and concentrates | D13: =INDEX(Data_HS!$F$2:$F$8217,$L13) -> 26 | E13: =IF(INDEX(Data_HS!$C$2:$C$8217,$L13)="","",INDEX(Data_HS!$C$2:$C$8217,$L13)/1000) -> 1364736.3 | F13: =INDEX(Data_HS!$D$2:$D$8217,$L13)/10^6 -> 4545.5013 | G13: =INDEX(Data_HS!$E$2:$E$8217,$L13) -> 3.3306809 | H13: =INDEX(Data_HS!$D$2:$D$8217,$L13)/SUM(Data_HS!$D$2:$D$8217) -> 0.019373094 | I13: =SUM($H$6:H13) -> 0.24016049 | J13: =INDEX(Data_HS!$G$2:$G$8217,$L13) -> 0 | K13: =INDEX(Data_HS!$I$2:$I$8217,$L13) -> Belum terwakili | L13: =MATCH(LARGE(Data_HS!$J$2:$J$8217,A13),Data_HS!$J$2:$J$8217,0) -> 1294 | M13: =B13&" · "&LEFT(C13,34)&IF(LEN(C13)>34,"…","") -> 26030000 · Copper ores and concentrates | O13: Segmen harga (USD per kg): nilai vs volume
A14: 9 | B14: =INDEX(Data_HS!$A$2:$A$8217,$L14) -> 87032259 | C14: =INDEX(Data_HS!$B$2:$B$8217,$L14) -> Motor cars (including station wagons and sports cars, but not including vans), other than of 4-wheel drive, with only spark-ignition internal combustion piston engine, of a cylinder capacity > 1,000 cc but ≤ 1,500 cc, other than CKD | D14: =INDEX(Data_HS!$F$2:$F$8217,$L14) -> 87 | E14: =IF(INDEX(Data_HS!$C$2:$C$8217,$L14)="","",INDEX(Data_HS!$C$2:$C$8217,$L14)/1000) -> 366680.69 | F14: =INDEX(Data_HS!$D$2:$D$8217,$L14)/10^6 -> 3584.1137 | G14: =INDEX(Data_HS!$E$2:$E$8217,$L14) -> 9.7744816 | H14: =INDEX(Data_HS!$D$2:$D$8217,$L14)/SUM(Data_HS!$D$2:$D$8217) -> 0.015275624 | I14: =SUM($H$6:H14) -> 0.25543611 | J14: =INDEX(Data_HS!$G$2:$G$8217,$L14) -> 0 | K14: =INDEX(Data_HS!$I$2:$I$8217,$L14) -> Belum terwakili | L14: =MATCH(LARGE(Data_HS!$J$2:$J$8217,A14),Data_HS!$J$2:$J$8217,0) -> 7233 | M14: =B14&" · "&LEFT(C14,34)&IF(LEN(C14)>34,"…","") -> 87032259 · Motor cars (including station wago… | O14: Segmen | P14: Jml HS | Q14: Nilai FOB (USD miliar) | R14: Berat (juta ton) | S14: Pangsa nilai | T14: Pangsa volume | U14: Listing eksportir
A15: 10 | B15: =INDEX(Data_HS!$A$2:$A$8217,$L15) -> 27011290 | C15: =INDEX(Data_HS!$B$2:$B$8217,$L15) -> Bituminous coal, whether or not pulverised, but not agglomerated, other than coking coal | D15: =INDEX(Data_HS!$F$2:$F$8217,$L15) -> 27 | E15: =IF(INDEX(Data_HS!$C$2:$C$8217,$L15)="","",INDEX(Data_HS!$C$2:$C$8217,$L15)/1000) -> 38510615 | F15: =INDEX(Data_HS!$D$2:$D$8217,$L15)/10^6 -> 3150.4652 | G15: =INDEX(Data_HS!$E$2:$E$8217,$L15) -> 0.08180771 | H15: =INDEX(Data_HS!$D$2:$D$8217,$L15)/SUM(Data_HS!$D$2:$D$8217) -> 0.013427398 | I15: =SUM($H$6:H15) -> 0.26886351 | J15: =INDEX(Data_HS!$G$2:$G$8217,$L15) -> 0 | K15: =INDEX(Data_HS!$I$2:$I$8217,$L15) -> Belum terwakili | L15: =MATCH(LARGE(Data_HS!$J$2:$J$8217,A15),Data_HS!$J$2:$J$8217,0) -> 1311 | M15: =B15&" · "&LEFT(C15,34)&IF(LEN(C15)>34,"…","") -> 27011290 · Bituminous coal, whether or not pu… | O15: Di bawah 1 | P15: =COUNTIF(Data_HS!$H$2:$H$8217,O15) -> 1070 | Q15: =SUMIFS(Data_HS!$D$2:$D$8217,Data_HS!$H$2:$H$8217,O15)/10^9 -> 43.282786 | R15: =SUMIFS(Data_HS!$C$2:$C$8217,Data_HS!$H$2:$H$8217,O15)/10^9 -> 172.22296 | S15: =Q15/Q$21 -> 0.18447282 | T15: =IF(R$21=0,0,R15/R$21) -> 0.71721676 | U15: =SUMIFS(Data_HS!$G$2:$G$8217,Data_HS!$H$2:$H$8217,O15) -> 713
A16: 11 | B16: =INDEX(Data_HS!$A$2:$A$8217,$L16) -> 15111000 | C16: =INDEX(Data_HS!$B$2:$B$8217,$L16) -> Crude palm oil | D16: =INDEX(Data_HS!$F$2:$F$8217,$L16) -> 15 | E16: =IF(INDEX(Data_HS!$C$2:$C$8217,$L16)="","",INDEX(Data_HS!$C$2:$C$8217,$L16)/1000) -> 2482133.2 | F16: =INDEX(Data_HS!$D$2:$D$8217,$L16)/10^6 -> 2598.8706 | G16: =INDEX(Data_HS!$E$2:$E$8217,$L16) -> 1.0470311 | H16: =INDEX(Data_HS!$D$2:$D$8217,$L16)/SUM(Data_HS!$D$2:$D$8217) -> 0.011076482 | I16: =SUM($H$6:H16) -> 0.27993999 | J16: =INDEX(Data_HS!$G$2:$G$8217,$L16) -> 4 | K16: =INDEX(Data_HS!$I$2:$I$8217,$L16) -> Terwakili | L16: =MATCH(LARGE(Data_HS!$J$2:$J$8217,A16),Data_HS!$J$2:$J$8217,0) -> 743 | M16: =B16&" · "&LEFT(C16,34)&IF(LEN(C16)>34,"…","") -> 15111000 · Crude palm oil | O16: 1 – 5 | P16: =COUNTIF(Data_HS!$H$2:$H$8217,O16) -> 2609 | Q16: =SUMIFS(Data_HS!$D$2:$D$8217,Data_HS!$H$2:$H$8217,O16)/10^9 -> 98.244438 | R16: =SUMIFS(Data_HS!$C$2:$C$8217,Data_HS!$H$2:$H$8217,O16)/10^9 -> 62.442335 | S16: =Q16/Q$21 -> 0.4187214 | T16: =IF(R$21=0,0,R16/R$21) -> 0.26003902 | U16: =SUMIFS(Data_HS!$G$2:$G$8217,Data_HS!$H$2:$H$8217,O16) -> 1225
A17: 12 | B17: =INDEX(Data_HS!$A$2:$A$8217,$L17) -> 40012220 | C17: =INDEX(Data_HS!$B$2:$B$8217,$L17) -> Technically specified natural rubber (TSNR) 20 | D17: =INDEX(Data_HS!$F$2:$F$8217,$L17) -> 40 | E17: =IF(INDEX(Data_HS!$C$2:$C$8217,$L17)="","",INDEX(Data_HS!$C$2:$C$8217,$L17)/1000) -> 1315379.5 | F17: =INDEX(Data_HS!$D$2:$D$8217,$L17)/10^6 -> 2485.8537 | G17: =INDEX(Data_HS!$E$2:$E$8217,$L17) -> 1.8898377 | H17: =INDEX(Data_HS!$D$2:$D$8217,$L17)/SUM(Data_HS!$D$2:$D$8217) -> 0.0105948 | I17: =SUM($H$6:H17) -> 0.29053479 | J17: =INDEX(Data_HS!$G$2:$G$8217,$L17) -> 0 | K17: =INDEX(Data_HS!$I$2:$I$8217,$L17) -> Belum terwakili | L17: =MATCH(LARGE(Data_HS!$J$2:$J$8217,A17),Data_HS!$J$2:$J$8217,0) -> 2568 | M17: =B17&" · "&LEFT(C17,34)&IF(LEN(C17)>34,"…","") -> 40012220 · Technically specified natural rubb… | O17: 5 – 20 | P17: =COUNTIF(Data_HS!$H$2:$H$8217,O17) -> 2487 | Q17: =SUMIFS(Data_HS!$D$2:$D$8217,Data_HS!$H$2:$H$8217,O17)/10^9 -> 48.420793 | R17: =SUMIFS(Data_HS!$C$2:$C$8217,Data_HS!$H$2:$H$8217,O17)/10^9 -> 4.7301188 | S17: =Q17/Q$21 -> 0.2063712 | T17: =IF(R$21=0,0,R17/R$21) -> 0.019698422 | U17: =SUMIFS(Data_HS!$G$2:$G$8217,Data_HS!$H$2:$H$8217,O17) -> 895
A18: 13 | B18: =INDEX(Data_HS!$A$2:$A$8217,$L18) -> 75011000 | C18: =INDEX(Data_HS!$B$2:$B$8217,$L18) -> Nickel mattes | D18: =INDEX(Data_HS!$F$2:$F$8217,$L18) -> 75 | E18: =IF(INDEX(Data_HS!$C$2:$C$8217,$L18)="","",INDEX(Data_HS!$C$2:$C$8217,$L18)/1000) -> 257961.3 | F18: =INDEX(Data_HS!$D$2:$D$8217,$L18)/10^6 -> 2476.2362 | G18: =INDEX(Data_HS!$E$2:$E$8217,$L18) -> 9.5992548 | H18: =INDEX(Data_HS!$D$2:$D$8217,$L18)/SUM(Data_HS!$D$2:$D$8217) -> 0.01055381 | I18: =SUM($H$6:H18) -> 0.3010886 | J18: =INDEX(Data_HS!$G$2:$G$8217,$L18) -> 0 | K18: =INDEX(Data_HS!$I$2:$I$8217,$L18) -> Belum terwakili | L18: =MATCH(LARGE(Data_HS!$J$2:$J$8217,A18),Data_HS!$J$2:$J$8217,0) -> 5096 | M18: =B18&" · "&LEFT(C18,34)&IF(LEN(C18)>34,"…","") -> 75011000 · Nickel mattes | O18: 20 – 100 | P18: =COUNTIF(Data_HS!$H$2:$H$8217,O18) -> 1440 | Q18: =SUMIFS(Data_HS!$D$2:$D$8217,Data_HS!$H$2:$H$8217,O18)/10^9 -> 22.335123 | R18: =SUMIFS(Data_HS!$C$2:$C$8217,Data_HS!$H$2:$H$8217,O18)/10^9 -> 0.70466667 | S18: =Q18/Q$21 -> 0.095193113 | T18: =IF(R$21=0,0,R18/R$21) -> 0.0029345609 | U18: =SUMIFS(Data_HS!$G$2:$G$8217,Data_HS!$H$2:$H$8217,O18) -> 228
A19: 14 | B19: =INDEX(Data_HS!$A$2:$A$8217,$L19) -> 47032900 | C19: =INDEX(Data_HS!$B$2:$B$8217,$L19) -> Chemical wood pulp, soda or sulphate, other than dissolving grades, semi-bleached or bleached, of non-coniferous | D19: =INDEX(Data_HS!$F$2:$F$8217,$L19) -> 47 | E19: =IF(INDEX(Data_HS!$C$2:$C$8217,$L19)="","",INDEX(Data_HS!$C$2:$C$8217,$L19)/1000) -> 4364121.6 | F19: =INDEX(Data_HS!$D$2:$D$8217,$L19)/10^6 -> 2204.9161 | G19: =INDEX(Data_HS!$E$2:$E$8217,$L19) -> 0.5052371 | H19: =INDEX(Data_HS!$D$2:$D$8217,$L19)/SUM(Data_HS!$D$2:$D$8217) -> 0.0093974336 | I19: =SUM($H$6:H19) -> 0.31048603 | J19: =INDEX(Data_HS!$G$2:$G$8217,$L19) -> 0 | K19: =INDEX(Data_HS!$I$2:$I$8217,$L19) -> Belum terwakili | L19: =MATCH(LARGE(Data_HS!$J$2:$J$8217,A19),Data_HS!$J$2:$J$8217,0) -> 2977 | M19: =B19&" · "&LEFT(C19,34)&IF(LEN(C19)>34,"…","") -> 47032900 · Chemical wood pulp, soda or sulpha… | O19: 100 ke atas | P19: =COUNTIF(Data_HS!$H$2:$H$8217,O19) -> 488 | Q19: =SUMIFS(Data_HS!$D$2:$D$8217,Data_HS!$H$2:$H$8217,O19)/10^9 -> 17.294918 | R19: =SUMIFS(Data_HS!$C$2:$C$8217,Data_HS!$H$2:$H$8217,O19)/10^9 -> 0.026709109 | S19: =Q19/Q$21 -> 0.073711576 | T19: =IF(R$21=0,0,R19/R$21) -> 0.0001112292 | U19: =SUMIFS(Data_HS!$G$2:$G$8217,Data_HS!$H$2:$H$8217,O19) -> 19
A20: 15 | B20: =INDEX(Data_HS!$A$2:$A$8217,$L20) -> 27011210 | C20: =INDEX(Data_HS!$B$2:$B$8217,$L20) -> Bituminous coal, whether or not pulverised, but not agglomerated, coking coal | D20: =INDEX(Data_HS!$F$2:$F$8217,$L20) -> 27 | E20: =IF(INDEX(Data_HS!$C$2:$C$8217,$L20)="","",INDEX(Data_HS!$C$2:$C$8217,$L20)/1000) -> 21341942 | F20: =INDEX(Data_HS!$D$2:$D$8217,$L20)/10^6 -> 2155.4424 | G20: =INDEX(Data_HS!$E$2:$E$8217,$L20) -> 0.10099561 | H20: =INDEX(Data_HS!$D$2:$D$8217,$L20)/SUM(Data_HS!$D$2:$D$8217) -> 0.0091865749 | I20: =SUM($H$6:H20) -> 0.31967261 | J20: =INDEX(Data_HS!$G$2:$G$8217,$L20) -> 4 | K20: =INDEX(Data_HS!$I$2:$I$8217,$L20) -> Terwakili | L20: =MATCH(LARGE(Data_HS!$J$2:$J$8217,A20),Data_HS!$J$2:$J$8217,0) -> 1310 | M20: =B20&" · "&LEFT(C20,34)&IF(LEN(C20)>34,"…","") -> 27011210 · Bituminous coal, whether or not pu… | O20: Tanpa data berat | P20: =COUNTIF(Data_HS!$H$2:$H$8217,O20) -> 122 | Q20: =SUMIFS(Data_HS!$D$2:$D$8217,Data_HS!$H$2:$H$8217,O20)/10^9 -> 5.0515488 | R20: =SUMIFS(Data_HS!$C$2:$C$8217,Data_HS!$H$2:$H$8217,O20)/10^9 -> 0 | S20: =Q20/Q$21 -> 0.021529886 | T20: =IF(R$21=0,0,R20/R$21) -> 0 | U20: =SUMIFS(Data_HS!$G$2:$G$8217,Data_HS!$H$2:$H$8217,O20) -> 12
A21: 16 | B21: =INDEX(Data_HS!$A$2:$A$8217,$L21) -> 28182000 | C21: =INDEX(Data_HS!$B$2:$B$8217,$L21) -> Aluminium oxide, other than artificial corundum | D21: =INDEX(Data_HS!$F$2:$F$8217,$L21) -> 28 | E21: =IF(INDEX(Data_HS!$C$2:$C$8217,$L21)="","",INDEX(Data_HS!$C$2:$C$8217,$L21)/1000) -> 4666463.5 | F21: =INDEX(Data_HS!$D$2:$D$8217,$L21)/10^6 -> 2134.657 | G21: =INDEX(Data_HS!$E$2:$E$8217,$L21) -> 0.4574464 | H21: =INDEX(Data_HS!$D$2:$D$8217,$L21)/SUM(Data_HS!$D$2:$D$8217) -> 0.0090979864 | I21: =SUM($H$6:H21) -> 0.32877059 | J21: =INDEX(Data_HS!$G$2:$G$8217,$L21) -> 0 | K21: =INDEX(Data_HS!$I$2:$I$8217,$L21) -> Belum terwakili | L21: =MATCH(LARGE(Data_HS!$J$2:$J$8217,A21),Data_HS!$J$2:$J$8217,0) -> 1400 | M21: =B21&" · "&LEFT(C21,34)&IF(LEN(C21)>34,"…","") -> 28182000 · Aluminium oxide, other than artifi… | O21: Total | P21: =SUM(P15:P20) -> 8216 | Q21: =SUM(Q15:Q20) -> 234.62961 | R21: =SUM(R15:R20) -> 240.12678 | S21: =SUM(S15:S20) -> 1 | T21: =SUM(T15:T20) -> 1 | U21: =SUM(U15:U20) -> 3092
A22: 17 | B22: =INDEX(Data_HS!$A$2:$A$8217,$L22) -> 18040000 | C22: =INDEX(Data_HS!$B$2:$B$8217,$L22) -> Cocoa butter, fat and oil | D22: =INDEX(Data_HS!$F$2:$F$8217,$L22) -> 18 | E22: =IF(INDEX(Data_HS!$C$2:$C$8217,$L22)="","",INDEX(Data_HS!$C$2:$C$8217,$L22)/1000) -> 115565.35 | F22: =INDEX(Data_HS!$D$2:$D$8217,$L22)/10^6 -> 2084.7033 | G22: =INDEX(Data_HS!$E$2:$E$8217,$L22) -> 18.039173 | H22: =INDEX(Data_HS!$D$2:$D$8217,$L22)/SUM(Data_HS!$D$2:$D$8217) -> 0.0088850819 | I22: =SUM($H$6:H22) -> 0.33765568 | J22: =INDEX(Data_HS!$G$2:$G$8217,$L22) -> 18 | K22: =INDEX(Data_HS!$I$2:$I$8217,$L22) -> Terwakili | L22: =MATCH(LARGE(Data_HS!$J$2:$J$8217,A22),Data_HS!$J$2:$J$8217,0) -> 936 | M22: =B22&" · "&LEFT(C22,34)&IF(LEN(C22)>34,"…","") -> 18040000 · Cocoa butter, fat and oil
A23: 18 | B23: =INDEX(Data_HS!$A$2:$A$8217,$L23) -> 74031100 | C23: =INDEX(Data_HS!$B$2:$B$8217,$L23) -> Cathodes and sections of cathodes; of refined copper | D23: =INDEX(Data_HS!$F$2:$F$8217,$L23) -> 74 | E23: =IF(INDEX(Data_HS!$C$2:$C$8217,$L23)="","",INDEX(Data_HS!$C$2:$C$8217,$L23)/1000) -> 210618.88 | F23: =INDEX(Data_HS!$D$2:$D$8217,$L23)/10^6 -> 2043.2109 | G23: =INDEX(Data_HS!$E$2:$E$8217,$L23) -> 9.7009869 | H23: =INDEX(Data_HS!$D$2:$D$8217,$L23)/SUM(Data_HS!$D$2:$D$8217) -> 0.0087082401 | I23: =SUM($H$6:H23) -> 0.34636392 | J23: =INDEX(Data_HS!$G$2:$G$8217,$L23) -> 0 | K23: =INDEX(Data_HS!$I$2:$I$8217,$L23) -> Belum terwakili | L23: =MATCH(LARGE(Data_HS!$J$2:$J$8217,A23),Data_HS!$J$2:$J$8217,0) -> 5029 | M23: =B23&" · "&LEFT(C23,34)&IF(LEN(C23)>34,"…","") -> 74031100 · Cathodes and sections of cathodes;…
A24: 19 | B24: =INDEX(Data_HS!$A$2:$A$8217,$L24) -> 15179043 | C24: =INDEX(Data_HS!$B$2:$B$8217,$L24) -> Shortening | D24: =INDEX(Data_HS!$F$2:$F$8217,$L24) -> 15 | E24: =IF(INDEX(Data_HS!$C$2:$C$8217,$L24)="","",INDEX(Data_HS!$C$2:$C$8217,$L24)/1000) -> 1930051.1 | F24: =INDEX(Data_HS!$D$2:$D$8217,$L24)/10^6 -> 2021.3346 | G24: =INDEX(Data_HS!$E$2:$E$8217,$L24) -> 1.0472959 | H24: =INDEX(Data_HS!$D$2:$D$8217,$L24)/SUM(Data_HS!$D$2:$D$8217) -> 0.0086150025 | I24: =SUM($H$6:H24) -> 0.35497892 | J24: =INDEX(Data_HS!$G$2:$G$8217,$L24) -> 1 | K24: =INDEX(Data_HS!$I$2:$I$8217,$L24) -> Keterwakilan rendah | L24: =MATCH(LARGE(Data_HS!$J$2:$J$8217,A24),Data_HS!$J$2:$J$8217,0) -> 817 | M24: =B24&" · "&LEFT(C24,34)&IF(LEN(C24)>34,"…","") -> 15179043 · Shortening
A25: 20 | B25: =INDEX(Data_HS!$A$2:$A$8217,$L25) -> 72189100 | C25: =INDEX(Data_HS!$B$2:$B$8217,$L25) -> Semi- finished products of stainless steel; of rectangular (other than square) cross-section | D25: =INDEX(Data_HS!$F$2:$F$8217,$L25) -> 72 | E25: =IF(INDEX(Data_HS!$C$2:$C$8217,$L25)="","",INDEX(Data_HS!$C$2:$C$8217,$L25)/1000) -> 1206467.1 | F25: =INDEX(Data_HS!$D$2:$D$8217,$L25)/10^6 -> 1938.3918 | G25: =INDEX(Data_HS!$E$2:$E$8217,$L25) -> 1.6066678 | H25: =INDEX(Data_HS!$D$2:$D$8217,$L25)/SUM(Data_HS!$D$2:$D$8217) -> 0.0082614972 | I25: =SUM($H$6:H25) -> 0.36324042 | J25: =INDEX(Data_HS!$G$2:$G$8217,$L25) -> 0 | K25: =INDEX(Data_HS!$I$2:$I$8217,$L25) -> Belum terwakili | L25: =MATCH(LARGE(Data_HS!$J$2:$J$8217,A25),Data_HS!$J$2:$J$8217,0) -> 4714 | M25: =B25&" · "&LEFT(C25,34)&IF(LEN(C25)>34,"…","") -> 72189100 · Semi- finished products of stainle…
A26: 21 | B26: =INDEX(Data_HS!$A$2:$A$8217,$L26) -> 38237090 | C26: =INDEX(Data_HS!$B$2:$B$8217,$L26) -> Industrial fatty alcohols other than in the form of wax | D26: =INDEX(Data_HS!$F$2:$F$8217,$L26) -> 38 | E26: =IF(INDEX(Data_HS!$C$2:$C$8217,$L26)="","",INDEX(Data_HS!$C$2:$C$8217,$L26)/1000) -> 811350.35 | F26: =INDEX(Data_HS!$D$2:$D$8217,$L26)/10^6 -> 1913.9304 | G26: =INDEX(Data_HS!$E$2:$E$8217,$L26) -> 2.3589444 | H26: =INDEX(Data_HS!$D$2:$D$8217,$L26)/SUM(Data_HS!$D$2:$D$8217) -> 0.0081572415 | I26: =SUM($H$6:H26) -> 0.37139766 | J26: =INDEX(Data_HS!$G$2:$G$8217,$L26) -> 0 | K26: =INDEX(Data_HS!$I$2:$I$8217,$L26) -> Belum terwakili | L26: =MATCH(LARGE(Data_HS!$J$2:$J$8217,A26),Data_HS!$J$2:$J$8217,0) -> 2219 | M26: =B26&" · "&LEFT(C26,34)&IF(LEN(C26)>34,"…","") -> 38237090 · Industrial fatty alcohols other th…
A27: 22 | B27: =INDEX(Data_HS!$A$2:$A$8217,$L27) -> 27101979 | C27: =INDEX(Data_HS!$B$2:$B$8217,$L27) -> Fuel oils | D27: =INDEX(Data_HS!$F$2:$F$8217,$L27) -> 27 | E27: =IF(INDEX(Data_HS!$C$2:$C$8217,$L27)="","",INDEX(Data_HS!$C$2:$C$8217,$L27)/1000) -> 3916764.5 | F27: =INDEX(Data_HS!$D$2:$D$8217,$L27)/10^6 -> 1908.2428 | G27: =INDEX(Data_HS!$E$2:$E$8217,$L27) -> 0.48719876 | H27: =INDEX(Data_HS!$D$2:$D$8217,$L27)/SUM(Data_HS!$D$2:$D$8217) -> 0.0081330008 | I27: =SUM($H$6:H27) -> 0.37953066 | J27: =INDEX(Data_HS!$G$2:$G$8217,$L27) -> 0 | K27: =INDEX(Data_HS!$I$2:$I$8217,$L27) -> Belum terwakili | L27: =MATCH(LARGE(Data_HS!$J$2:$J$8217,A27),Data_HS!$J$2:$J$8217,0) -> 1338 | M27: =B27&" · "&LEFT(C27,34)&IF(LEN(C27)>34,"…","") -> 27101979 · Fuel oils
A28: 23 | B28: =INDEX(Data_HS!$A$2:$A$8217,$L28) -> 09011130 | C28: =INDEX(Data_HS!$B$2:$B$8217,$L28) -> Robusta, not roasted, not decaffeinated | D28: =INDEX(Data_HS!$F$2:$F$8217,$L28) -> 9 | E28: =IF(INDEX(Data_HS!$C$2:$C$8217,$L28)="","",INDEX(Data_HS!$C$2:$C$8217,$L28)/1000) -> 402531.22 | F28: =INDEX(Data_HS!$D$2:$D$8217,$L28)/10^6 -> 1820.3075 | G28: =INDEX(Data_HS!$E$2:$E$8217,$L28) -> 4.5221524 | H28: =INDEX(Data_HS!$D$2:$D$8217,$L28)/SUM(Data_HS!$D$2:$D$8217) -> 0.0077582175 | I28: =SUM($H$6:H28) -> 0.38728888 | J28: =INDEX(Data_HS!$G$2:$G$8217,$L28) -> 15 | K28: =INDEX(Data_HS!$I$2:$I$8217,$L28) -> Terwakili | L28: =MATCH(LARGE(Data_HS!$J$2:$J$8217,A28),Data_HS!$J$2:$J$8217,0) -> 531 | M28: =B28&" · "&LEFT(C28,34)&IF(LEN(C28)>34,"…","") -> 09011130 · Robusta, not roasted, not decaffei…
A29: 24 | B29: =INDEX(Data_HS!$A$2:$A$8217,$L29) -> 72191300 | C29: =INDEX(Data_HS!$B$2:$B$8217,$L29) -> Flat-rolled products of stainless steel, of a width of 600 mm or more; not further worked than hot-rolled, in coils; of a thickness of 3 mm or more but less than 4.75 mm | D29: =INDEX(Data_HS!$F$2:$F$8217,$L29) -> 72 | E29: =IF(INDEX(Data_HS!$C$2:$C$8217,$L29)="","",INDEX(Data_HS!$C$2:$C$8217,$L29)/1000) -> 1029773 | F29: =INDEX(Data_HS!$D$2:$D$8217,$L29)/10^6 -> 1750.3504 | G29: =INDEX(Data_HS!$E$2:$E$8217,$L29) -> 1.699744 | H29: =INDEX(Data_HS!$D$2:$D$8217,$L29)/SUM(Data_HS!$D$2:$D$8217) -> 0.0074600577 | I29: =SUM($H$6:H29) -> 0.39474893 | J29: =INDEX(Data_HS!$G$2:$G$8217,$L29) -> 0 | K29: =INDEX(Data_HS!$I$2:$I$8217,$L29) -> Belum terwakili | L29: =MATCH(LARGE(Data_HS!$J$2:$J$8217,A29),Data_HS!$J$2:$J$8217,0) -> 4718 | M29: =B29&" · "&LEFT(C29,34)&IF(LEN(C29)>34,"…","") -> 72191300 · Flat-rolled products of stainless …
A30: 25 | B30: =INDEX(Data_HS!$A$2:$A$8217,$L30) -> 15119036 | C30: =INDEX(Data_HS!$B$2:$B$8217,$L30) -> Liquid fractions of palm oil, refined oil, but not chemically modified, in packing of a net weight not exceeding 25 kg | D30: =INDEX(Data_HS!$F$2:$F$8217,$L30) -> 15 | E30: =IF(INDEX(Data_HS!$C$2:$C$8217,$L30)="","",INDEX(Data_HS!$C$2:$C$8217,$L30)/1000) -> 1499720.8 | F30: =INDEX(Data_HS!$D$2:$D$8217,$L30)/10^6 -> 1724.5855 | G30: =INDEX(Data_HS!$E$2:$E$8217,$L30) -> 1.1499377 | H30: =INDEX(Data_HS!$D$2:$D$8217,$L30)/SUM(Data_HS!$D$2:$D$8217) -> 0.0073502466 | I30: =SUM($H$6:H30) -> 0.40209918 | J30: =INDEX(Data_HS!$G$2:$G$8217,$L30) -> 0 | K30: =INDEX(Data_HS!$I$2:$I$8217,$L30) -> Belum terwakili | L30: =MATCH(LARGE(Data_HS!$J$2:$J$8217,A30),Data_HS!$J$2:$J$8217,0) -> 747 | M30: =B30&" · "&LEFT(C30,34)&IF(LEN(C30)>34,"…","") -> 15119036 · Liquid fractions of palm oil, refi…
A31: 26 | B31: =INDEX(Data_HS!$A$2:$A$8217,$L31) -> 27112190 | C31: =INDEX(Data_HS!$B$2:$B$8217,$L31) -> Natural gas, in gaseous state, other than of a kind used as a motor fuel | D31: =INDEX(Data_HS!$F$2:$F$8217,$L31) -> 27 | E31: =IF(INDEX(Data_HS!$C$2:$C$8217,$L31)="","",INDEX(Data_HS!$C$2:$C$8217,$L31)/1000) -> 3173468.5 | F31: =INDEX(Data_HS!$D$2:$D$8217,$L31)/10^6 -> 1651.4732 | G31: =INDEX(Data_HS!$E$2:$E$8217,$L31) -> 0.52040006 | H31: =INDEX(Data_HS!$D$2:$D$8217,$L31)/SUM(Data_HS!$D$2:$D$8217) -> 0.0070386395 | I31: =SUM($H$6:H31) -> 0.40913782 | J31: =INDEX(Data_HS!$G$2:$G$8217,$L31) -> 0 | K31: =INDEX(Data_HS!$I$2:$I$8217,$L31) -> Belum terwakili | L31: =MATCH(LARGE(Data_HS!$J$2:$J$8217,A31),Data_HS!$J$2:$J$8217,0) -> 1348 | M31: =B31&" · "&LEFT(C31,34)&IF(LEN(C31)>34,"…","") -> 27112190 · Natural gas, in gaseous state, oth…
A32: 27 | B32: =INDEX(Data_HS!$A$2:$A$8217,$L32) -> 15132995 | C32: =INDEX(Data_HS!$B$2:$B$8217,$L32) -> Palm kernel oil, refined, bleached and deodorised (rbd) | D32: =INDEX(Data_HS!$F$2:$F$8217,$L32) -> 15 | E32: =IF(INDEX(Data_HS!$C$2:$C$8217,$L32)="","",INDEX(Data_HS!$C$2:$C$8217,$L32)/1000) -> 916215.79 | F32: =INDEX(Data_HS!$D$2:$D$8217,$L32)/10^6 -> 1639.5062 | G32: =INDEX(Data_HS!$E$2:$E$8217,$L32) -> 1.7894324 | H32: =INDEX(Data_HS!$D$2:$D$8217,$L32)/SUM(Data_HS!$D$2:$D$8217) -> 0.0069876358 | I32: =SUM($H$6:H32) -> 0.41612546 | J32: =INDEX(Data_HS!$G$2:$G$8217,$L32) -> 3 | K32: =INDEX(Data_HS!$I$2:$I$8217,$L32) -> Keterwakilan rendah | L32: =MATCH(LARGE(Data_HS!$J$2:$J$8217,A32),Data_HS!$J$2:$J$8217,0) -> 763 | M32: =B32&" · "&LEFT(C32,34)&IF(LEN(C32)>34,"…","") -> 15132995 · Palm kernel oil, refined, bleached…
A33: 28 | B33: =INDEX(Data_HS!$A$2:$A$8217,$L33) -> 38231990 | C33: =INDEX(Data_HS!$B$2:$B$8217,$L33) -> Industrial monocarboxylic fatty acids, other than acid oils from refining, other than palm fatty acid distillate and palm kernel fatty acid distillate | D33: =INDEX(Data_HS!$F$2:$F$8217,$L33) -> 38 | E33: =IF(INDEX(Data_HS!$C$2:$C$8217,$L33)="","",INDEX(Data_HS!$C$2:$C$8217,$L33)/1000) -> 1214878.5 | F33: =INDEX(Data_HS!$D$2:$D$8217,$L33)/10^6 -> 1612.3659 | G33: =INDEX(Data_HS!$E$2:$E$8217,$L33) -> 1.3271829 | H33: =INDEX(Data_HS!$D$2:$D$8217,$L33)/SUM(Data_HS!$D$2:$D$8217) -> 0.0068719627 | I33: =SUM($H$6:H33) -> 0.42299742 | J33: =INDEX(Data_HS!$G$2:$G$8217,$L33) -> 0 | K33: =INDEX(Data_HS!$I$2:$I$8217,$L33) -> Belum terwakili | L33: =MATCH(LARGE(Data_HS!$J$2:$J$8217,A33),Data_HS!$J$2:$J$8217,0) -> 2217 | M33: =B33&" · "&LEFT(C33,34)&IF(LEN(C33)>34,"…","") -> 38231990 · Industrial monocarboxylic fatty ac…
... A55: 50 | B55: =INDEX(Data_HS!$A$2:$A$8217,$L55) -> 48025690 | C55: =INDEX(Data_HS!$B$2:$B$8217,$L55) -> Uncoated paper and paperboard, weighing 40 g/m2 or more but not more than 150 g/m2, in sheets with one side not exceeding 435 mm and the other side not exceeding 297 mm in the unfolded state, not containing fibres obtained by a mechanical or chemi-mechanical process or of which not more than 10 % by weight of the total fibre content consists of such fibres, n.e.c. in subheading 480256 | D55: =INDEX(Data_HS!$F$2:$F$8217,$L55) -> 48 | E55: =IF(INDEX(Data_HS!$C$2:$C$8217,$L55)="","",INDEX(Data_HS!$C$2:$C$8217,$L55)/1000) -> 1320919.3 | F55: =INDEX(Data_HS!$D$2:$D$8217,$L55)/10^6 -> 930.3756 | G55: =INDEX(Data_HS!$E$2:$E$8217,$L55) -> 0.70433949 | H55: =INDEX(Data_HS!$D$2:$D$8217,$L55)/SUM(Data_HS!$D$2:$D$8217) -> 0.003965295 | I55: =SUM($H$6:H55) -> 0.53665365 | J55: =INDEX(Data_HS!$G$2:$G$8217,$L55) -> 0 | K55: =INDEX(Data_HS!$I$2:$I$8217,$L55) -> Belum terwakili | L55: =MATCH(LARGE(Data_HS!$J$2:$J$8217,A55),Data_HS!$J$2:$J$8217,0) -> 3007 | M55: =B55&" · "&LEFT(C55,34)&IF(LEN(C55)>34,"…","") -> 48025690 · Uncoated paper and paperboard, wei…

Sheet Eksportir
A1: Analisis Direktori Eksportir
A2: Sebaran geografis, profil usaha, praktik transaksi, dan validasi estimasi pendapatan
A4: Sebaran perusahaan per provinsi | I4: Top 10 provinsi (jumlah perusahaan) | Q4: Validasi estimasi pendapatan listing
A5: Provinsi | B5: Perusahaan | C5: Listing produk | D5: Pangsa perusahaan | E5: Listing per perusahaan | F5: Est. pendapatan wajar (USD juta/bln) | G5: Urut (helper) | I5: Provinsi | J5: Perusahaan | K5: Listing | L5: Pangsa | M5: Baris (helper) | Q5: Status estimasi | R5: Listing | S5: Pangsa listing | T5: Est. pendapatan (USD miliar/bln) | U5: Pangsa estimasi pendapatan
A6: Jawa Timur | B6: =COUNTIF(Profil_Perusahaan!$B$2:$B$774,A6) -> 149 | C6: =COUNTIF(Data_Eksportir!$C$2:$C$3401,A6) -> 656 | D6: =B6/$B$38 -> 0.1927555 | E6: =IF(B6=0,"",C6/B6) -> 4.4026846 | F6: =SUMIFS(Data_Eksportir!$N$2:$N$3401,Data_Eksportir!$C$2:$C$3401,A6,Data_Eksportir!$Q$2:$Q$3401,"Wajar")/10^6 -> 34.412954 | G6: =B6+C6/10^4+ROW()/10^9 -> 149.0656 | I6: =INDEX($A$6:$A$37,$M6) -> Jawa Timur | J6: =INDEX($B$6:$B$37,$M6) -> 149 | K6: =INDEX($C$6:$C$37,$M6) -> 656 | L6: =INDEX($D$6:$D$37,$M6) -> 0.1927555 | M6: =MATCH(LARGE($G$6:$G$37,ROWS(I$6:I6)),$G$6:$G$37,0) -> 1 | Q6: Wajar | R6: =COUNTIF(Data_Eksportir!$Q$2:$Q$3401,Q6) -> 1613 | S6: =R6/R$12 -> 0.47441176 | T6: =SUMIFS(Data_Eksportir!$N$2:$N$3401,Data_Eksportir!$Q$2:$Q$3401,Q6)/10^9 -> 0.69446059 | U6: =IF(T$12=0,0,T6/T$12) -> 0.053551532
A7: DKI Jakarta | B7: =COUNTIF(Profil_Perusahaan!$B$2:$B$774,A7) -> 131 | C7: =COUNTIF(Data_Eksportir!$C$2:$C$3401,A7) -> 629 | D7: =B7/$B$38 -> 0.1694696 | E7: =IF(B7=0,"",C7/B7) -> 4.8015267 | F7: =SUMIFS(Data_Eksportir!$N$2:$N$3401,Data_Eksportir!$C$2:$C$3401,A7,Data_Eksportir!$Q$2:$Q$3401,"Wajar")/10^6 -> 162.76925 | G7: =B7+C7/10^4+ROW()/10^9 -> 131.0629 | I7: =INDEX($A$6:$A$37,$M7) -> DKI Jakarta | J7: =INDEX($B$6:$B$37,$M7) -> 131 | K7: =INDEX($C$6:$C$37,$M7) -> 629 | L7: =INDEX($D$6:$D$37,$M7) -> 0.1694696 | M7: =MATCH(LARGE($G$6:$G$37,ROWS(I$6:I7)),$G$6:$G$37,0) -> 2 | Q7: Melebihi ekspor nasional HS | R7: =COUNTIF(Data_Eksportir!$Q$2:$Q$3401,Q7) -> 777 | S7: =R7/R$12 -> 0.22852941 | T7: =SUMIFS(Data_Eksportir!$N$2:$N$3401,Data_Eksportir!$Q$2:$Q$3401,Q7)/10^9 -> 12.27362 | U7: =IF(T$12=0,0,T7/T$12) -> 0.94644847
A8: Jawa Barat | B8: =COUNTIF(Profil_Perusahaan!$B$2:$B$774,A8) -> 122 | C8: =COUNTIF(Data_Eksportir!$C$2:$C$3401,A8) -> 479 | D8: =B8/$B$38 -> 0.15782665 | E8: =IF(B8=0,"",C8/B8) -> 3.9262295 | F8: =SUMIFS(Data_Eksportir!$N$2:$N$3401,Data_Eksportir!$C$2:$C$3401,A8,Data_Eksportir!$Q$2:$Q$3401,"Wajar")/10^6 -> 75.431063 | G8: =B8+C8/10^4+ROW()/10^9 -> 122.0479 | I8: =INDEX($A$6:$A$37,$M8) -> Jawa Barat | J8: =INDEX($B$6:$B$37,$M8) -> 122 | K8: =INDEX($C$6:$C$37,$M8) -> 479 | L8: =INDEX($D$6:$D$37,$M8) -> 0.15782665 | M8: =MATCH(LARGE($G$6:$G$37,ROWS(I$6:I8)),$G$6:$G$37,0) -> 3 | Q8: Estimasi nol | R8: =COUNTIF(Data_Eksportir!$Q$2:$Q$3401,Q8) -> 458 | S8: =R8/R$12 -> 0.13470588 | T8: =SUMIFS(Data_Eksportir!$N$2:$N$3401,Data_Eksportir!$Q$2:$Q$3401,Q8)/10^9 -> 0 | U8: =IF(T$12=0,0,T8/T$12) -> 0
A9: Jawa Tengah | B9: =COUNTIF(Profil_Perusahaan!$B$2:$B$774,A9) -> 70 | C9: =COUNTIF(Data_Eksportir!$C$2:$C$3401,A9) -> 414 | D9: =B9/$B$38 -> 0.090556274 | E9: =IF(B9=0,"",C9/B9) -> 5.9142857 | F9: =SUMIFS(Data_Eksportir!$N$2:$N$3401,Data_Eksportir!$C$2:$C$3401,A9,Data_Eksportir!$Q$2:$Q$3401,"Wajar")/10^6 -> 60.751825 | G9: =B9+C9/10^4+ROW()/10^9 -> 70.0414 | I9: =INDEX($A$6:$A$37,$M9) -> Jawa Tengah | J9: =INDEX($B$6:$B$37,$M9) -> 70 | K9: =INDEX($C$6:$C$37,$M9) -> 414 | L9: =INDEX($D$6:$D$37,$M9) -> 0.090556274 | M9: =MATCH(LARGE($G$6:$G$37,ROWS(I$6:I9)),$G$6:$G$37,0) -> 4 | Q9: Tanpa estimasi | R9: =COUNTIF(Data_Eksportir!$Q$2:$Q$3401,Q9) -> 245 | S9: =R9/R$12 -> 0.072058824 | T9: =SUMIFS(Data_Eksportir!$N$2:$N$3401,Data_Eksportir!$Q$2:$Q$3401,Q9)/10^9 -> 0 | U9: =IF(T$12=0,0,T9/T$12) -> 0
A10: Banten | B10: =COUNTIF(Profil_Perusahaan!$B$2:$B$774,A10) -> 44 | C10: =COUNTIF(Data_Eksportir!$C$2:$C$3401,A10) -> 234 | D10: =B10/$B$38 -> 0.056921087 | E10: =IF(B10=0,"",C10/B10) -> 5.3181818 | F10: =SUMIFS(Data_Eksportir!$N$2:$N$3401,Data_Eksportir!$C$2:$C$3401,A10,Data_Eksportir!$Q$2:$Q$3401,"Wajar")/10^6 -> 43.48475 | G10: =B10+C10/10^4+ROW()/10^9 -> 44.0234 | I10: =INDEX($A$6:$A$37,$M10) -> Banten | J10: =INDEX($B$6:$B$37,$M10) -> 44 | K10: =INDEX($C$6:$C$37,$M10) -> 234 | L10: =INDEX($D$6:$D$37,$M10) -> 0.056921087 | M10: =MATCH(LARGE($G$6:$G$37,ROWS(I$6:I10)),$G$6:$G$37,0) -> 5 | Q10: HS tidak valid | R10: =COUNTIF(Data_Eksportir!$Q$2:$Q$3401,Q10) -> 307 | S10: =R10/R$12 -> 0.090294118 | T10: =SUMIFS(Data_Eksportir!$N$2:$N$3401,Data_Eksportir!$Q$2:$Q$3401,Q10)/10^9 -> 0 | U10: =IF(T$12=0,0,T10/T$12) -> 0
A11: Sulawesi Selatan | B11: =COUNTIF(Profil_Perusahaan!$B$2:$B$774,A11) -> 43 | C11: =COUNTIF(Data_Eksportir!$C$2:$C$3401,A11) -> 138 | D11: =B11/$B$38 -> 0.055627426 | E11: =IF(B11=0,"",C11/B11) -> 3.2093023 | F11: =SUMIFS(Data_Eksportir!$N$2:$N$3401,Data_Eksportir!$C$2:$C$3401,A11,Data_Eksportir!$Q$2:$Q$3401,"Wajar")/10^6 -> 30.746394 | G11: =B11+C11/10^4+ROW()/10^9 -> 43.0138 | I11: =INDEX($A$6:$A$37,$M11) -> Sulawesi Selatan | J11: =INDEX($B$6:$B$37,$M11) -> 43 | K11: =INDEX($C$6:$C$37,$M11) -> 138 | L11: =INDEX($D$6:$D$37,$M11) -> 0.055627426 | M11: =MATCH(LARGE($G$6:$G$37,ROWS(I$6:I11)),$G$6:$G$37,0) -> 6 | Q11: HS tidak ada di data nasional | R11: =COUNTIF(Data_Eksportir!$Q$2:$Q$3401,Q11) -> 0 | S11: =R11/R$12 -> 0 | T11: =SUMIFS(Data_Eksportir!$N$2:$N$3401,Data_Eksportir!$Q$2:$Q$3401,Q11)/10^9 -> 0 | U11: =IF(T$12=0,0,T11/T$12) -> 0
A12: Sumatera Utara | B12: =COUNTIF(Profil_Perusahaan!$B$2:$B$774,A12) -> 38 | C12: =COUNTIF(Data_Eksportir!$C$2:$C$3401,A12) -> 106 | D12: =B12/$B$38 -> 0.04915912 | E12: =IF(B12=0,"",C12/B12) -> 2.7894737 | F12: =SUMIFS(Data_Eksportir!$N$2:$N$3401,Data_Eksportir!$C$2:$C$3401,A12,Data_Eksportir!$Q$2:$Q$3401,"Wajar")/10^6 -> 120.78109 | G12: =B12+C12/10^4+ROW()/10^9 -> 38.0106 | I12: =INDEX($A$6:$A$37,$M12) -> Sumatera Utara | J12: =INDEX($B$6:$B$37,$M12) -> 38 | K12: =INDEX($C$6:$C$37,$M12) -> 106 | L12: =INDEX($D$6:$D$37,$M12) -> 0.04915912 | M12: =MATCH(LARGE($G$6:$G$37,ROWS(I$6:I12)),$G$6:$G$37,0) -> 7 | Q12: Total | R12: =SUM(R6:R11) -> 3400 | S12: =SUM(S6:S11) -> 1 | T12: =SUM(T6:T11) -> 12.968081 | U12: =SUM(U6:U11) -> 1
A13: Sumatera Barat | B13: =COUNTIF(Profil_Perusahaan!$B$2:$B$774,A13) -> 18 | C13: =COUNTIF(Data_Eksportir!$C$2:$C$3401,A13) -> 69 | D13: =B13/$B$38 -> 0.023285899 | E13: =IF(B13=0,"",C13/B13) -> 3.8333333 | F13: =SUMIFS(Data_Eksportir!$N$2:$N$3401,Data_Eksportir!$C$2:$C$3401,A13,Data_Eksportir!$Q$2:$Q$3401,"Wajar")/10^6 -> 5.6207353 | G13: =B13+C13/10^4+ROW()/10^9 -> 18.0069 | I13: =INDEX($A$6:$A$37,$M13) -> Sumatera Barat | J13: =INDEX($B$6:$B$37,$M13) -> 18 | K13: =INDEX($C$6:$C$37,$M13) -> 69 | L13: =INDEX($D$6:$D$37,$M13) -> 0.023285899 | M13: =MATCH(LARGE($G$6:$G$37,ROWS(I$6:I13)),$G$6:$G$37,0) -> 8
A14: Aceh | B14: =COUNTIF(Profil_Perusahaan!$B$2:$B$774,A14) -> 17 | C14: =COUNTIF(Data_Eksportir!$C$2:$C$3401,A14) -> 68 | D14: =B14/$B$38 -> 0.021992238 | E14: =IF(B14=0,"",C14/B14) -> 4 | F14: =SUMIFS(Data_Eksportir!$N$2:$N$3401,Data_Eksportir!$C$2:$C$3401,A14,Data_Eksportir!$Q$2:$Q$3401,"Wajar")/10^6 -> 1.4791749 | G14: =B14+C14/10^4+ROW()/10^9 -> 17.0068 | I14: =INDEX($A$6:$A$37,$M14) -> Aceh | J14: =INDEX($B$6:$B$37,$M14) -> 17 | K14: =INDEX($C$6:$C$37,$M14) -> 68 | L14: =INDEX($D$6:$D$37,$M14) -> 0.021992238 | M14: =MATCH(LARGE($G$6:$G$37,ROWS(I$6:I14)),$G$6:$G$37,0) -> 9
A15: DI Yogyakarta | B15: =COUNTIF(Profil_Perusahaan!$B$2:$B$774,A15) -> 15 | C15: =COUNTIF(Data_Eksportir!$C$2:$C$3401,A15) -> 89 | D15: =B15/$B$38 -> 0.019404916 | E15: =IF(B15=0,"",C15/B15) -> 5.9333333 | F15: =SUMIFS(Data_Eksportir!$N$2:$N$3401,Data_Eksportir!$C$2:$C$3401,A15,Data_Eksportir!$Q$2:$Q$3401,"Wajar")/10^6 -> 2.878289 | G15: =B15+C15/10^4+ROW()/10^9 -> 15.0089 | I15: =INDEX($A$6:$A$37,$M15) -> DI Yogyakarta | J15: =INDEX($B$6:$B$37,$M15) -> 15 | K15: =INDEX($C$6:$C$37,$M15) -> 89 | L15: =INDEX($D$6:$D$37,$M15) -> 0.019404916 | M15: =MATCH(LARGE($G$6:$G$37,ROWS(I$6:I15)),$G$6:$G$37,0) -> 10 | Q15: 10 pelabuhan ekspor teratas (dari listing yang mengisi pelabuhan)
A16: Kalimantan Timur | B16: =COUNTIF(Profil_Perusahaan!$B$2:$B$774,A16) -> 15 | C16: =COUNTIF(Data_Eksportir!$C$2:$C$3401,A16) -> 42 | D16: =B16/$B$38 -> 0.019404916 | E16: =IF(B16=0,"",C16/B16) -> 2.8 | F16: =SUMIFS(Data_Eksportir!$N$2:$N$3401,Data_Eksportir!$C$2:$C$3401,A16,Data_Eksportir!$Q$2:$Q$3401,"Wajar")/10^6 -> 14.2068 | G16: =B16+C16/10^4+ROW()/10^9 -> 15.0042 | Q16: Pelabuhan | R16: Listing | S16: Pangsa dari seluruh listing
A17: Bali | B17: =COUNTIF(Profil_Perusahaan!$B$2:$B$774,A17) -> 12 | C17: =COUNTIF(Data_Eksportir!$C$2:$C$3401,A17) -> 38 | D17: =B17/$B$38 -> 0.015523933 | E17: =IF(B17=0,"",C17/B17) -> 3.1666667 | F17: =SUMIFS(Data_Eksportir!$N$2:$N$3401,Data_Eksportir!$C$2:$C$3401,A17,Data_Eksportir!$Q$2:$Q$3401,"Wajar")/10^6 -> 1.6913181 | G17: =B17+C17/10^4+ROW()/10^9 -> 12.0038 | Q17: TANJUNG PRIOK | R17: =COUNTIF(Data_Eksportir!$E$2:$E$3401,Q17) -> 381 | S17: =R17/COUNTA(Data_Eksportir!$B$2:$B$3401) -> 0.11205882
A18: Kalimantan Barat | B18: =COUNTIF(Profil_Perusahaan!$B$2:$B$774,A18) -> 11 | C18: =COUNTIF(Data_Eksportir!$C$2:$C$3401,A18) -> 31 | D18: =B18/$B$38 -> 0.014230272 | E18: =IF(B18=0,"",C18/B18) -> 2.8181818 | F18: =SUMIFS(Data_Eksportir!$N$2:$N$3401,Data_Eksportir!$C$2:$C$3401,A18,Data_Eksportir!$Q$2:$Q$3401,"Wajar")/10^6 -> 0.67779802 | G18: =B18+C18/10^4+ROW()/10^9 -> 11.0031 | I18: Jenis usaha | Q18: TANJUNG PERAK | R18: =COUNTIF(Data_Eksportir!$E$2:$E$3401,Q18) -> 280 | S18: =R18/COUNTA(Data_Eksportir!$B$2:$B$3401) -> 0.082352941
A19: Lampung | B19: =COUNTIF(Profil_Perusahaan!$B$2:$B$774,A19) -> 10 | C19: =COUNTIF(Data_Eksportir!$C$2:$C$3401,A19) -> 25 | D19: =B19/$B$38 -> 0.012936611 | E19: =IF(B19=0,"",C19/B19) -> 2.5 | F19: =SUMIFS(Data_Eksportir!$N$2:$N$3401,Data_Eksportir!$C$2:$C$3401,A19,Data_Eksportir!$Q$2:$Q$3401,"Wajar")/10^6 -> 0.70521938 | G19: =B19+C19/10^4+ROW()/10^9 -> 10.0025 | I19: Jenis usaha | J19: Perusahaan | K19: Listing | L19: Pangsa perusahaan | Q19: BELAWAN | R19: =COUNTIF(Data_Eksportir!$E$2:$E$3401,Q19) -> 89 | S19: =R19/COUNTA(Data_Eksportir!$B$2:$B$3401) -> 0.026176471
A20: Sumatera Selatan | B20: =COUNTIF(Profil_Perusahaan!$B$2:$B$774,A20) -> 10 | C20: =COUNTIF(Data_Eksportir!$C$2:$C$3401,A20) -> 112 | D20: =B20/$B$38 -> 0.012936611 | E20: =IF(B20=0,"",C20/B20) -> 11.2 | F20: =SUMIFS(Data_Eksportir!$N$2:$N$3401,Data_Eksportir!$C$2:$C$3401,A20,Data_Eksportir!$Q$2:$Q$3401,"Wajar")/10^6 -> 115.73185 | G20: =B20+C20/10^4+ROW()/10^9 -> 10.0112 | I20: Exporter | J20: =COUNTIF(Profil_Perusahaan!$C$2:$C$774,I20) -> 333 | K20: =COUNTIF(Data_Eksportir!$D$2:$D$3401,I20) -> 1533 | L20: =J20/J$25 -> 0.43078913 | Q20: SURABAYA (PTT) | R20: =COUNTIF(Data_Eksportir!$E$2:$E$3401,Q20) -> 49 | S20: =R20/COUNTA(Data_Eksportir!$B$2:$B$3401) -> 0.014411765
A21: Nusa Tenggara Barat | B21: =COUNTIF(Profil_Perusahaan!$B$2:$B$774,A21) -> 9 | C21: =COUNTIF(Data_Eksportir!$C$2:$C$3401,A21) -> 24 | D21: =B21/$B$38 -> 0.01164295 | E21: =IF(B21=0,"",C21/B21) -> 2.6666667 | F21: =SUMIFS(Data_Eksportir!$N$2:$N$3401,Data_Eksportir!$C$2:$C$3401,A21,Data_Eksportir!$Q$2:$Q$3401,"Wajar")/10^6 -> 1.4807806 | G21: =B21+C21/10^4+ROW()/10^9 -> 9.0024 | I21: Exporter and Producer | J21: =COUNTIF(Profil_Perusahaan!$C$2:$C$774,I21) -> 279 | K21: =COUNTIF(Data_Eksportir!$D$2:$D$3401,I21) -> 1270 | L21: =J21/J$25 -> 0.36093144 | Q21: SEMARANG (PTT) | R21: =COUNTIF(Data_Eksportir!$E$2:$E$3401,Q21) -> 48 | S21: =R21/COUNTA(Data_Eksportir!$B$2:$B$3401) -> 0.014117647
A22: Riau | B22: =COUNTIF(Profil_Perusahaan!$B$2:$B$774,A22) -> 8 | C22: =COUNTIF(Data_Eksportir!$C$2:$C$3401,A22) -> 21 | D22: =B22/$B$38 -> 0.010349288 | E22: =IF(B22=0,"",C22/B22) -> 2.625 | F22: =SUMIFS(Data_Eksportir!$N$2:$N$3401,Data_Eksportir!$C$2:$C$3401,A22,Data_Eksportir!$Q$2:$Q$3401,"Wajar")/10^6 -> 2.1215995 | G22: =B22+C22/10^4+ROW()/10^9 -> 8.0021 | I22: Trader | J22: =COUNTIF(Profil_Perusahaan!$C$2:$C$774,I22) -> 86 | K22: =COUNTIF(Data_Eksportir!$D$2:$D$3401,I22) -> 368 | L22: =J22/J$25 -> 0.11125485 | Q22: SOEKARNO-HATTA - MAKASSAR | R22: =COUNTIF(Data_Eksportir!$E$2:$E$3401,Q22) -> 37 | S22: =R22/COUNTA(Data_Eksportir!$B$2:$B$3401) -> 0.010882353
A23: Sulawesi Tenggara | B23: =COUNTIF(Profil_Perusahaan!$B$2:$B$774,A23) -> 7 | C23: =COUNTIF(Data_Eksportir!$C$2:$C$3401,A23) -> 18 | D23: =B23/$B$38 -> 0.0090556274 | E23: =IF(B23=0,"",C23/B23) -> 2.5714286 | F23: =SUMIFS(Data_Eksportir!$N$2:$N$3401,Data_Eksportir!$C$2:$C$3401,A23,Data_Eksportir!$Q$2:$Q$3401,"Wajar")/10^6 -> 6.9641356 | G23: =B23+C23/10^4+ROW()/10^9 -> 7.0018 | I23: Producer | J23: =COUNTIF(Profil_Perusahaan!$C$2:$C$774,I23) -> 31 | K23: =COUNTIF(Data_Eksportir!$D$2:$D$3401,I23) -> 107 | L23: =J23/J$25 -> 0.040103493 | Q23: PANJANG | R23: =COUNTIF(Data_Eksportir!$E$2:$E$3401,Q23) -> 27 | S23: =R23/COUNTA(Data_Eksportir!$B$2:$B$3401) -> 0.0079411765
A24: Jambi | B24: =COUNTIF(Profil_Perusahaan!$B$2:$B$774,A24) -> 7 | C24: =COUNTIF(Data_Eksportir!$C$2:$C$3401,A24) -> 22 | D24: =B24/$B$38 -> 0.0090556274 | E24: =IF(B24=0,"",C24/B24) -> 3.1428571 | F24: =SUMIFS(Data_Eksportir!$N$2:$N$3401,Data_Eksportir!$C$2:$C$3401,A24,Data_Eksportir!$Q$2:$Q$3401,"Wajar")/10^6 -> 0.76985927 | G24: =B24+C24/10^4+ROW()/10^9 -> 7.0022 | I24: Tidak diketahui | J24: =COUNTIF(Profil_Perusahaan!$C$2:$C$774,I24) -> 44 | K24: =COUNTIF(Data_Eksportir!$D$2:$D$3401,I24) -> 122 | L24: =J24/J$25 -> 0.056921087 | Q24: TANJUNG EMAS | R24: =COUNTIF(Data_Eksportir!$E$2:$E$3401,Q24) -> 25 | S24: =R24/COUNTA(Data_Eksportir!$B$2:$B$3401) -> 0.0073529412
A25: Sulawesi Utara | B25: =COUNTIF(Profil_Perusahaan!$B$2:$B$774,A25) -> 7 | C25: =COUNTIF(Data_Eksportir!$C$2:$C$3401,A25) -> 33 | D25: =B25/$B$38 -> 0.0090556274 | E25: =IF(B25=0,"",C25/B25) -> 4.7142857 | F25: =SUMIFS(Data_Eksportir!$N$2:$N$3401,Data_Eksportir!$C$2:$C$3401,A25,Data_Eksportir!$Q$2:$Q$3401,"Wajar")/10^6 -> 0.84658967 | G25: =B25+C25/10^4+ROW()/10^9 -> 7.0033 | I25: Total | J25: =SUM(J20:J24) -> 773 | K25: =SUM(K20:K24) -> 3400 | L25: =SUM(L20:L24) -> 1 | Q25: SURABAYA /JUANDA (U) | R25: =COUNTIF(Data_Eksportir!$E$2:$E$3401,Q25) -> 23 | S25: =R25/COUNTA(Data_Eksportir!$B$2:$B$3401) -> 0.0067647059
A26: Kepulauan Riau | B26: =COUNTIF(Profil_Perusahaan!$B$2:$B$774,A26) -> 5 | C26: =COUNTIF(Data_Eksportir!$C$2:$C$3401,A26) -> 43 | D26: =B26/$B$38 -> 0.0064683053 | E26: =IF(B26=0,"",C26/B26) -> 8.6 | F26: =SUMIFS(Data_Eksportir!$N$2:$N$3401,Data_Eksportir!$C$2:$C$3401,A26,Data_Eksportir!$Q$2:$Q$3401,"Wajar")/10^6 -> 3.5575546 | G26: =B26+C26/10^4+ROW()/10^9 -> 5.0043 | Q26: JAKARTA / PASAR IKAN | R26: =COUNTIF(Data_Eksportir!$E$2:$E$3401,Q26) -> 20 | S26: =R26/COUNTA(Data_Eksportir!$B$2:$B$3401) -> 0.0058823529
A27: Kalimantan Selatan | B27: =COUNTIF(Profil_Perusahaan!$B$2:$B$774,A27) -> 5 | C27: =COUNTIF(Data_Eksportir!$C$2:$C$3401,A27) -> 33 | D27: =B27/$B$38 -> 0.0064683053 | E27: =IF(B27=0,"",C27/B27) -> 6.6 | F27: =SUMIFS(Data_Eksportir!$N$2:$N$3401,Data_Eksportir!$C$2:$C$3401,A27,Data_Eksportir!$Q$2:$Q$3401,"Wajar")/10^6 -> 1.1760513 | G27: =B27+C27/10^4+ROW()/10^9 -> 5.0033 | Q27: Tidak diketahui (kosong) | R27: =COUNTIF(Data_Eksportir!$E$2:$E$3401,"Tidak diketahui") -> 2323 | S27: =R27/COUNTA(Data_Eksportir!$B$2:$B$3401) -> 0.68323529
A28: Sulawesi Tengah | B28: =COUNTIF(Profil_Perusahaan!$B$2:$B$774,A28) -> 4 | C28: =COUNTIF(Data_Eksportir!$C$2:$C$3401,A28) -> 21 | D28: =B28/$B$38 -> 0.0051746442 | E28: =IF(B28=0,"",C28/B28) -> 5.25 | F28: =SUMIFS(Data_Eksportir!$N$2:$N$3401,Data_Eksportir!$C$2:$C$3401,A28,Data_Eksportir!$Q$2:$Q$3401,"Wajar")/10^6 -> 0.24889332 | G28: =B28+C28/10^4+ROW()/10^9 -> 4.0021 | I28: Incoterms
A29: Bengkulu | B29: =COUNTIF(Profil_Perusahaan!$B$2:$B$774,A29) -> 3 | C29: =COUNTIF(Data_Eksportir!$C$2:$C$3401,A29) -> 10 | D29: =B29/$B$38 -> 0.0038809832 | E29: =IF(B29=0,"",C29/B29) -> 3.3333333 | F29: =SUMIFS(Data_Eksportir!$N$2:$N$3401,Data_Eksportir!$C$2:$C$3401,A29,Data_Eksportir!$Q$2:$Q$3401,"Wajar")/10^6 -> 0.011934231 | G29: =B29+C29/10^4+ROW()/10^9 -> 3.001 | I29: Incoterms | J29: Listing | K29: Pangsa
A30: Sulawesi Barat | B30: =COUNTIF(Profil_Perusahaan!$B$2:$B$774,A30) -> 3 | C30: =COUNTIF(Data_Eksportir!$C$2:$C$3401,A30) -> 9 | D30: =B30/$B$38 -> 0.0038809832 | E30: =IF(B30=0,"",C30/B30) -> 3 | F30: =SUMIFS(Data_Eksportir!$N$2:$N$3401,Data_Eksportir!$C$2:$C$3401,A30,Data_Eksportir!$Q$2:$Q$3401,"Wajar")/10^6 -> 1.5160702 | G30: =B30+C30/10^4+ROW()/10^9 -> 3.0009 | I30: FOB | J30: =COUNTIF(Data_Eksportir!$G$2:$G$3401,I30) -> 2373 | K30: =J30/J$33 -> 0.69794118 | Q30: 15 perusahaan dengan estimasi pendapatan wajar terbesar
A31: Nusa Tenggara Timur | B31: =COUNTIF(Profil_Perusahaan!$B$2:$B$774,A31) -> 3 | C31: =COUNTIF(Data_Eksportir!$C$2:$C$3401,A31) -> 7 | D31: =B31/$B$38 -> 0.0038809832 | E31: =IF(B31=0,"",C31/B31) -> 2.3333333 | F31: =SUMIFS(Data_Eksportir!$N$2:$N$3401,Data_Eksportir!$C$2:$C$3401,A31,Data_Eksportir!$Q$2:$Q$3401,"Wajar")/10^6 -> 0 | G31: =B31+C31/10^4+ROW()/10^9 -> 3.0007 | I31: CIF | J31: =COUNTIF(Data_Eksportir!$G$2:$G$3401,I31) -> 767 | K31: =J31/J$33 -> 0.22558824 | Q31: Perusahaan | R31: Provinsi | S31: Listing produk | T31: Est. pendapatan wajar (USD juta/bln) | U31: Baris (helper)
A32: Kep. Bangka Belitung | B32: =COUNTIF(Profil_Perusahaan!$B$2:$B$774,A32) -> 2 | C32: =COUNTIF(Data_Eksportir!$C$2:$C$3401,A32) -> 11 | D32: =B32/$B$38 -> 0.0025873221 | E32: =IF(B32=0,"",C32/B32) -> 5.5 | F32: =SUMIFS(Data_Eksportir!$N$2:$N$3401,Data_Eksportir!$C$2:$C$3401,A32,Data_Eksportir!$Q$2:$Q$3401,"Wajar")/10^6 -> 4.3240557 | G32: =B32+C32/10^4+ROW()/10^9 -> 2.0011 | I32: Tidak diketahui | J32: =COUNTIF(Data_Eksportir!$G$2:$G$3401,I32) -> 260 | K32: =J32/J$33 -> 0.076470588 | Q32: =INDEX(Profil_Perusahaan!$A$2:$A$774,$U32) -> ATHAYA AGRO PRATINDO, PT | R32: =INDEX(Profil_Perusahaan!$B$2:$B$774,$U32) -> Sumatera Selatan | S32: =INDEX(Profil_Perusahaan!$D$2:$D$774,$U32) -> 62 | T32: =INDEX(Profil_Perusahaan!$F$2:$F$774,$U32)/10^6 -> 111.10933 | U32: =MATCH(LARGE(Profil_Perusahaan!$H$2:$H$774,ROWS(Q$32:Q32)),Profil_Perusahaan!$H$2:$H$774,0) -> 102
A33: Kalimantan Tengah | B33: =COUNTIF(Profil_Perusahaan!$B$2:$B$774,A33) -> 1 | C33: =COUNTIF(Data_Eksportir!$C$2:$C$3401,A33) -> 1 | D33: =B33/$B$38 -> 0.0012936611 | E33: =IF(B33=0,"",C33/B33) -> 1 | F33: =SUMIFS(Data_Eksportir!$N$2:$N$3401,Data_Eksportir!$C$2:$C$3401,A33,Data_Eksportir!$Q$2:$Q$3401,"Wajar")/10^6 -> 0 | G33: =B33+C33/10^4+ROW()/10^9 -> 1.0001 | I33: Total | J33: =SUM(J30:J32) -> 3400 | K33: =SUM(K30:K32) -> 1 | Q33: =INDEX(Profil_Perusahaan!$A$2:$A$774,$U33) -> ANDINI RIZKI JAYA ABADI, PT | R33: =INDEX(Profil_Perusahaan!$B$2:$B$774,$U33) -> DKI Jakarta | S33: =INDEX(Profil_Perusahaan!$D$2:$D$774,$U33) -> 8 | T33: =INDEX(Profil_Perusahaan!$F$2:$F$774,$U33)/10^6 -> 98.291459 | U33: =MATCH(LARGE(Profil_Perusahaan!$H$2:$H$774,ROWS(Q$32:Q33)),Profil_Perusahaan!$H$2:$H$774,0) -> 73
A34: Kalimantan Utara | B34: =COUNTIF(Profil_Perusahaan!$B$2:$B$774,A34) -> 1 | C34: =COUNTIF(Data_Eksportir!$C$2:$C$3401,A34) -> 4 | D34: =B34/$B$38 -> 0.0012936611 | E34: =IF(B34=0,"",C34/B34) -> 4 | F34: =SUMIFS(Data_Eksportir!$N$2:$N$3401,Data_Eksportir!$C$2:$C$3401,A34,Data_Eksportir!$Q$2:$Q$3401,"Wajar")/10^6 -> 0.058535198 | G34: =B34+C34/10^4+ROW()/10^9 -> 1.0004 | Q34: =INDEX(Profil_Perusahaan!$A$2:$A$774,$U34) -> BAKRIE FOOD AND ENERGY, PT | R34: =INDEX(Profil_Perusahaan!$B$2:$B$774,$U34) -> Sumatera Utara | S34: =INDEX(Profil_Perusahaan!$D$2:$D$774,$U34) -> 5 | T34: =INDEX(Profil_Perusahaan!$F$2:$F$774,$U34)/10^6 -> 95.52787 | U34: =MATCH(LARGE(Profil_Perusahaan!$H$2:$H$774,ROWS(Q$32:Q34)),Profil_Perusahaan!$H$2:$H$774,0) -> 111
A35: Papua Barat | B35: =COUNTIF(Profil_Perusahaan!$B$2:$B$774,A35) -> 1 | C35: =COUNTIF(Data_Eksportir!$C$2:$C$3401,A35) -> 11 | D35: =B35/$B$38 -> 0.0012936611 | E35: =IF(B35=0,"",C35/B35) -> 11 | F35: =SUMIFS(Data_Eksportir!$N$2:$N$3401,Data_Eksportir!$C$2:$C$3401,A35,Data_Eksportir!$Q$2:$Q$3401,"Wajar")/10^6 -> 0.013957977 | G35: =B35+C35/10^4+ROW()/10^9 -> 1.0011 | Q35: =INDEX(Profil_Perusahaan!$A$2:$A$774,$U35) -> VISALA TUNGGA JAYA, PT | R35: =INDEX(Profil_Perusahaan!$B$2:$B$774,$U35) -> Jawa Barat | S35: =INDEX(Profil_Perusahaan!$D$2:$D$774,$U35) -> 4 | T35: =INDEX(Profil_Perusahaan!$F$2:$F$774,$U35)/10^6 -> 27.984859 | U35: =MATCH(LARGE(Profil_Perusahaan!$H$2:$H$774,ROWS(Q$32:Q35)),Profil_Perusahaan!$H$2:$H$774,0) -> 747
A36: Maluku Utara | B36: =COUNTIF(Profil_Perusahaan!$B$2:$B$774,A36) -> 1 | C36: =COUNTIF(Data_Eksportir!$C$2:$C$3401,A36) -> 1 | D36: =B36/$B$38 -> 0.0012936611 | E36: =IF(B36=0,"",C36/B36) -> 1 | F36: =SUMIFS(Data_Eksportir!$N$2:$N$3401,Data_Eksportir!$C$2:$C$3401,A36,Data_Eksportir!$Q$2:$Q$3401,"Wajar")/10^6 -> 0 | G36: =B36+C36/10^4+ROW()/10^9 -> 1.0001 | I36: Terms of payment | Q36: =INDEX(Profil_Perusahaan!$A$2:$A$774,$U36) -> WSR CAHAYA ABADI, PT | R36: =INDEX(Profil_Perusahaan!$B$2:$B$774,$U36) -> Jawa Tengah | S36: =INDEX(Profil_Perusahaan!$D$2:$D$774,$U36) -> 3 | T36: =INDEX(Profil_Perusahaan!$F$2:$F$774,$U36)/10^6 -> 20.315026 | U36: =MATCH(LARGE(Profil_Perusahaan!$H$2:$H$774,ROWS(Q$32:Q36)),Profil_Perusahaan!$H$2:$H$774,0) -> 761
A37: Papua | B37: =COUNTIF(Profil_Perusahaan!$B$2:$B$774,A37) -> 1 | C37: =COUNTIF(Data_Eksportir!$C$2:$C$3401,A37) -> 1 | D37: =B37/$B$38 -> 0.0012936611 | E37: =IF(B37=0,"",C37/B37) -> 1 | F37: =SUMIFS(Data_Eksportir!$N$2:$N$3401,Data_Eksportir!$C$2:$C$3401,A37,Data_Eksportir!$Q$2:$Q$3401,"Wajar")/10^6 -> 0.0020648441 | G37: =B37+C37/10^4+ROW()/10^9 -> 1.0001 | I37: Terms of payment | J37: Listing | K37: Pangsa | Q37: =INDEX(Profil_Perusahaan!$A$2:$A$774,$U37) -> COCO RIKI INTERNATIONAL, PT | R37: =INDEX(Profil_Perusahaan!$B$2:$B$774,$U37) -> Jawa Tengah | S37: =INDEX(Profil_Perusahaan!$D$2:$D$774,$U37) -> 12 | T37: =INDEX(Profil_Perusahaan!$F$2:$F$774,$U37)/10^6 -> 18.184168 | U37: =MATCH(LARGE(Profil_Perusahaan!$H$2:$H$774,ROWS(Q$32:Q37)),Profil_Perusahaan!$H$2:$H$774,0) -> 197
A38: Total | B38: =SUM(B6:B37) -> 773 | C38: =SUM(C6:C37) -> 3400 | D38: =SUM(D6:D37) -> 1 | E38: =C38/B38 -> 4.3984476 | F38: =SUM(F6:F37) -> 694.46059 | I38: T/T | J38: =COUNTIF(Data_Eksportir!$F$2:$F$3401,I38) -> 1807 | K38: =J38/J$42 -> 0.53147059 | Q38: =INDEX(Profil_Perusahaan!$A$2:$A$774,$U38) -> GOLDCORNA GLOBAL INDONESIA, CV | R38: =INDEX(Profil_Perusahaan!$B$2:$B$774,$U38) -> Sumatera Utara | S38: =INDEX(Profil_Perusahaan!$D$2:$D$774,$U38) -> 5 | T38: =INDEX(Profil_Perusahaan!$F$2:$F$774,$U38)/10^6 -> 13.026878 | U38: =MATCH(LARGE(Profil_Perusahaan!$H$2:$H$774,ROWS(Q$32:Q38)),Profil_Perusahaan!$H$2:$H$774,0) -> 299
I39: LC | J39: =COUNTIF(Data_Eksportir!$F$2:$F$3401,I39) -> 1300 | K39: =J39/J$42 -> 0.38235294 | Q39: =INDEX(Profil_Perusahaan!$A$2:$A$774,$U39) -> EXPINDO SINAR JAYA GROUP, PT | R39: =INDEX(Profil_Perusahaan!$B$2:$B$774,$U39) -> Kalimantan Timur | S39: =INDEX(Profil_Perusahaan!$D$2:$D$774,$U39) -> 12 | T39: =INDEX(Profil_Perusahaan!$F$2:$F$774,$U39)/10^6 -> 12.601449 | U39: =MATCH(LARGE(Profil_Perusahaan!$H$2:$H$774,ROWS(Q$32:Q39)),Profil_Perusahaan!$H$2:$H$774,0) -> 251
I40: PayPal | J40: =COUNTIF(Data_Eksportir!$F$2:$F$3401,I40) -> 33 | K40: =J40/J$42 -> 0.0097058824 | Q40: =INDEX(Profil_Perusahaan!$A$2:$A$774,$U40) -> SUKSES USAHA SEMESTA, PT | R40: =INDEX(Profil_Perusahaan!$B$2:$B$774,$U40) -> DKI Jakarta | S40: =INDEX(Profil_Perusahaan!$D$2:$D$774,$U40) -> 2 | T40: =INDEX(Profil_Perusahaan!$F$2:$F$774,$U40)/10^6 -> 11.235993 | U40: =MATCH(LARGE(Profil_Perusahaan!$H$2:$H$774,ROWS(Q$32:Q40)),Profil_Perusahaan!$H$2:$H$774,0) -> 672
A41: 15 perusahaan dengan listing produk terbanyak | I41: Tidak diketahui | J41: =COUNTIF(Data_Eksportir!$F$2:$F$3401,I41) -> 260 | K41: =J41/J$42 -> 0.076470588 | Q41: =INDEX(Profil_Perusahaan!$A$2:$A$774,$U41) -> DIDITOS, PT | R41: =INDEX(Profil_Perusahaan!$B$2:$B$774,$U41) -> DKI Jakarta | S41: =INDEX(Profil_Perusahaan!$D$2:$D$774,$U41) -> 5 | T41: =INDEX(Profil_Perusahaan!$F$2:$F$774,$U41)/10^6 -> 11.057192 | U41: =MATCH(LARGE(Profil_Perusahaan!$H$2:$H$774,ROWS(Q$32:Q41)),Profil_Perusahaan!$H$2:$H$774,0) -> 229
A42: Perusahaan | B42: Provinsi | C42: Jenis usaha | D42: Listing produk | E42: Est. pendapatan mentah (USD juta/bln) | F42: Est. pendapatan wajar (USD juta/bln) | G42: Baris (helper) | I42: Total | J42: =SUM(J38:J41) -> 3400 | K42: =SUM(K38:K41) -> 1 | Q42: =INDEX(Profil_Perusahaan!$A$2:$A$774,$U42) -> BIBIT NUSANTARA JAYA, PT | R42: =INDEX(Profil_Perusahaan!$B$2:$B$774,$U42) -> Banten | S42: =INDEX(Profil_Perusahaan!$D$2:$D$774,$U42) -> 3 | T42: =INDEX(Profil_Perusahaan!$F$2:$F$774,$U42)/10^6 -> 9.512261 | U42: =MATCH(LARGE(Profil_Perusahaan!$H$2:$H$774,ROWS(Q$32:Q42)),Profil_Perusahaan!$H$2:$H$774,0) -> 144
A43: =INDEX(Profil_Perusahaan!$A$2:$A$774,$G43) -> ATHAYA AGRO PRATINDO, PT | B43: =INDEX(Profil_Perusahaan!$B$2:$B$774,$G43) -> Sumatera Selatan | C43: =INDEX(Profil_Perusahaan!$C$2:$C$774,$G43) -> Exporter | D43: =INDEX(Profil_Perusahaan!$D$2:$D$774,$G43) -> 62 | E43: =INDEX(Profil_Perusahaan!$E$2:$E$774,$G43)/10^6 -> 320.61859 | F43: =INDEX(Profil_Perusahaan!$F$2:$F$774,$G43)/10^6 -> 111.10933 | G43: =MATCH(LARGE(Profil_Perusahaan!$G$2:$G$774,ROWS(A$43:A43)),Profil_Perusahaan!$G$2:$G$774,0) -> 102 | Q43: =INDEX(Profil_Perusahaan!$A$2:$A$774,$U43) -> GRAND KAKAO INDONESIA, PT | R43: =INDEX(Profil_Perusahaan!$B$2:$B$774,$U43) -> Sulawesi Selatan | S43: =INDEX(Profil_Perusahaan!$D$2:$D$774,$U43) -> 2 | T43: =INDEX(Profil_Perusahaan!$F$2:$F$774,$U43)/10^6 -> 9.1999783 | U43: =MATCH(LARGE(Profil_Perusahaan!$H$2:$H$774,ROWS(Q$32:Q43)),Profil_Perusahaan!$H$2:$H$774,0) -> 306
A44: =INDEX(Profil_Perusahaan!$A$2:$A$774,$G44) -> INFINITY GLOBAL EXPORT, PT | B44: =INDEX(Profil_Perusahaan!$B$2:$B$774,$G44) -> DI Yogyakarta | C44: =INDEX(Profil_Perusahaan!$C$2:$C$774,$G44) -> Exporter and Producer | D44: =INDEX(Profil_Perusahaan!$D$2:$D$774,$G44) -> 29 | E44: =INDEX(Profil_Perusahaan!$E$2:$E$774,$G44)/10^6 -> 0.121812 | F44: =INDEX(Profil_Perusahaan!$F$2:$F$774,$G44)/10^6 -> 0.121812 | G44: =MATCH(LARGE(Profil_Perusahaan!$G$2:$G$774,ROWS(A$43:A44)),Profil_Perusahaan!$G$2:$G$774,0) -> 358 | Q44: =INDEX(Profil_Perusahaan!$A$2:$A$774,$U44) -> GLOBAL PORTAL NUSANTARA, PT | R44: =INDEX(Profil_Perusahaan!$B$2:$B$774,$U44) -> Sulawesi Tenggara | S44: =INDEX(Profil_Perusahaan!$D$2:$D$774,$U44) -> 10 | T44: =INDEX(Profil_Perusahaan!$F$2:$F$774,$U44)/10^6 -> 6.9297998 | U44: =MATCH(LARGE(Profil_Perusahaan!$H$2:$H$774,ROWS(Q$32:Q44)),Profil_Perusahaan!$H$2:$H$774,0) -> 290
A45: =INDEX(Profil_Perusahaan!$A$2:$A$774,$G45) -> TREEYAS GROUP INDONESIA, PT | B45: =INDEX(Profil_Perusahaan!$B$2:$B$774,$G45) -> Jawa Timur | C45: =INDEX(Profil_Perusahaan!$C$2:$C$774,$G45) -> Exporter | D45: =INDEX(Profil_Perusahaan!$D$2:$D$774,$G45) -> 28 | E45: =INDEX(Profil_Perusahaan!$E$2:$E$774,$G45)/10^6 -> 2.4028618 | F45: =INDEX(Profil_Perusahaan!$F$2:$F$774,$G45)/10^6 -> 1.7495058 | G45: =MATCH(LARGE(Profil_Perusahaan!$G$2:$G$774,ROWS(A$43:A45)),Profil_Perusahaan!$G$2:$G$774,0) -> 720 | Q45: =INDEX(Profil_Perusahaan!$A$2:$A$774,$U45) -> Tropical Nature Export, CV | R45: =INDEX(Profil_Perusahaan!$B$2:$B$774,$U45) -> Sulawesi Selatan | S45: =INDEX(Profil_Perusahaan!$D$2:$D$774,$U45) -> 4 | T45: =INDEX(Profil_Perusahaan!$F$2:$F$774,$U45)/10^6 -> 6.8871438 | U45: =MATCH(LARGE(Profil_Perusahaan!$H$2:$H$774,ROWS(Q$32:Q45)),Profil_Perusahaan!$H$2:$H$774,0) -> 725
A46: =INDEX(Profil_Perusahaan!$A$2:$A$774,$G46) -> ZIVANA BERKAH EKSPORT, PT | B46: =INDEX(Profil_Perusahaan!$B$2:$B$774,$G46) -> Jawa Tengah | C46: =INDEX(Profil_Perusahaan!$C$2:$C$774,$G46) -> Trader | D46: =INDEX(Profil_Perusahaan!$D$2:$D$774,$G46) -> 26 | E46: =INDEX(Profil_Perusahaan!$E$2:$E$774,$G46)/10^6 -> 9.4325739 | F46: =INDEX(Profil_Perusahaan!$F$2:$F$774,$G46)/10^6 -> 1.9625169 | G46: =MATCH(LARGE(Profil_Perusahaan!$G$2:$G$774,ROWS(A$43:A46)),Profil_Perusahaan!$G$2:$G$774,0) -> 772 | Q46: =INDEX(Profil_Perusahaan!$A$2:$A$774,$U46) -> RANS SADAWIRA UTAMA GROUP, PT | R46: =INDEX(Profil_Perusahaan!$B$2:$B$774,$U46) -> Jawa Timur | S46: =INDEX(Profil_Perusahaan!$D$2:$D$774,$U46) -> 1 | T46: =INDEX(Profil_Perusahaan!$F$2:$F$774,$U46)/10^6 -> 6.7833417 | U46: =MATCH(LARGE(Profil_Perusahaan!$H$2:$H$774,ROWS(Q$32:Q46)),Profil_Perusahaan!$H$2:$H$774,0) -> 597
A47: =INDEX(Profil_Perusahaan!$A$2:$A$774,$G47) -> WONDERFUL INDONESIA CORP, PT | B47: =INDEX(Profil_Perusahaan!$B$2:$B$774,$G47) -> DKI Jakarta | C47: =INDEX(Profil_Perusahaan!$C$2:$C$774,$G47) -> Exporter | D47: =INDEX(Profil_Perusahaan!$D$2:$D$774,$G47) -> 23 | E47: =INDEX(Profil_Perusahaan!$E$2:$E$774,$G47)/10^6 -> 0.0011108007 | F47: =INDEX(Profil_Perusahaan!$F$2:$F$774,$G47)/10^6 -> 0.0011108007 | G47: =MATCH(LARGE(Profil_Perusahaan!$G$2:$G$774,ROWS(A$43:A47)),Profil_Perusahaan!$G$2:$G$774,0) -> 760
A48: =INDEX(Profil_Perusahaan!$A$2:$A$774,$G48) -> STAR LABORATORIES, UD | B48: =INDEX(Profil_Perusahaan!$B$2:$B$774,$G48) -> Jawa Timur | C48: =INDEX(Profil_Perusahaan!$C$2:$C$774,$G48) -> Exporter | D48: =INDEX(Profil_Perusahaan!$D$2:$D$774,$G48) -> 23 | E48: =INDEX(Profil_Perusahaan!$E$2:$E$774,$G48)/10^6 -> 1.8545301 | F48: =INDEX(Profil_Perusahaan!$F$2:$F$774,$G48)/10^6 -> 0.72526948 | G48: =MATCH(LARGE(Profil_Perusahaan!$G$2:$G$774,ROWS(A$43:A48)),Profil_Perusahaan!$G$2:$G$774,0) -> 668
A49: =INDEX(Profil_Perusahaan!$A$2:$A$774,$G49) -> BAHUREKSO DADI MULYA, PT | B49: =INDEX(Profil_Perusahaan!$B$2:$B$774,$G49) -> Jawa Tengah | C49: =INDEX(Profil_Perusahaan!$C$2:$C$774,$G49) -> Exporter and Producer | D49: =INDEX(Profil_Perusahaan!$D$2:$D$774,$G49) -> 22 | E49: =INDEX(Profil_Perusahaan!$E$2:$E$774,$G49)/10^6 -> 5.5238001 | F49: =INDEX(Profil_Perusahaan!$F$2:$F$774,$G49)/10^6 -> 3.5242286 | G49: =MATCH(LARGE(Profil_Perusahaan!$G$2:$G$774,ROWS(A$43:A49)),Profil_Perusahaan!$G$2:$G$774,0) -> 109
A50: =INDEX(Profil_Perusahaan!$A$2:$A$774,$G50) -> RAFIF ALMEERA INDONESIA, PT | B50: =INDEX(Profil_Perusahaan!$B$2:$B$774,$G50) -> Jawa Tengah | C50: =INDEX(Profil_Perusahaan!$C$2:$C$774,$G50) -> Exporter and Producer | D50: =INDEX(Profil_Perusahaan!$D$2:$D$774,$G50) -> 21 | E50: =INDEX(Profil_Perusahaan!$E$2:$E$774,$G50)/10^6 -> 0.057622692 | F50: =INDEX(Profil_Perusahaan!$F$2:$F$774,$G50)/10^6 -> 0 | G50: =MATCH(LARGE(Profil_Perusahaan!$G$2:$G$774,ROWS(A$43:A50)),Profil_Perusahaan!$G$2:$G$774,0) -> 590
A51: =INDEX(Profil_Perusahaan!$A$2:$A$774,$G51) -> Anak Muda Berkah, PT | B51: =INDEX(Profil_Perusahaan!$B$2:$B$774,$G51) -> Banten | C51: =INDEX(Profil_Perusahaan!$C$2:$C$774,$G51) -> Exporter | D51: =INDEX(Profil_Perusahaan!$D$2:$D$774,$G51) -> 21 | E51: =INDEX(Profil_Perusahaan!$E$2:$E$774,$G51)/10^6 -> 3.440424 | F51: =INDEX(Profil_Perusahaan!$F$2:$F$774,$G51)/10^6 -> 1.7298687 | G51: =MATCH(LARGE(Profil_Perusahaan!$G$2:$G$774,ROWS(A$43:A51)),Profil_Perusahaan!$G$2:$G$774,0) -> 66
A52: =INDEX(Profil_Perusahaan!$A$2:$A$774,$G52) -> BOYMAXWELL INDOJAYA GRUP, PT | B52: =INDEX(Profil_Perusahaan!$B$2:$B$774,$G52) -> DKI Jakarta | C52: =INDEX(Profil_Perusahaan!$C$2:$C$774,$G52) -> Exporter | D52: =INDEX(Profil_Perusahaan!$D$2:$D$774,$G52) -> 20 | E52: =INDEX(Profil_Perusahaan!$E$2:$E$774,$G52)/10^6 -> 2.0427443 | F52: =INDEX(Profil_Perusahaan!$F$2:$F$774,$G52)/10^6 -> 1.48427 | G52: =MATCH(LARGE(Profil_Perusahaan!$G$2:$G$774,ROWS(A$43:A52)),Profil_Perusahaan!$G$2:$G$774,0) -> 163
A53: =INDEX(Profil_Perusahaan!$A$2:$A$774,$G53) -> Exim Jaya Abadi (AsiaCommerce), PT | B53: =INDEX(Profil_Perusahaan!$B$2:$B$774,$G53) -> Jawa Timur | C53: =INDEX(Profil_Perusahaan!$C$2:$C$774,$G53) -> Exporter | D53: =INDEX(Profil_Perusahaan!$D$2:$D$774,$G53) -> 19 | E53: =INDEX(Profil_Perusahaan!$E$2:$E$774,$G53)/10^6 -> 0.41281647 | F53: =INDEX(Profil_Perusahaan!$F$2:$F$774,$G53)/10^6 -> 0.2812575 | G53: =MATCH(LARGE(Profil_Perusahaan!$G$2:$G$774,ROWS(A$43:A53)),Profil_Perusahaan!$G$2:$G$774,0) -> 250
A54: =INDEX(Profil_Perusahaan!$A$2:$A$774,$G54) -> Synectic in Nature Indonesia, PT | B54: =INDEX(Profil_Perusahaan!$B$2:$B$774,$G54) -> Jawa Barat | C54: =INDEX(Profil_Perusahaan!$C$2:$C$774,$G54) -> Exporter and Producer | D54: =INDEX(Profil_Perusahaan!$D$2:$D$774,$G54) -> 18 | E54: =INDEX(Profil_Perusahaan!$E$2:$E$774,$G54)/10^6 -> 23.880157 | F54: =INDEX(Profil_Perusahaan!$F$2:$F$774,$G54)/10^6 -> 4.4799791 | G54: =MATCH(LARGE(Profil_Perusahaan!$G$2:$G$774,ROWS(A$43:A54)),Profil_Perusahaan!$G$2:$G$774,0) -> 695
A55: =INDEX(Profil_Perusahaan!$A$2:$A$774,$G55) -> BINTANG ANARKI JAYAA ABADI, PT | B55: =INDEX(Profil_Perusahaan!$B$2:$B$774,$G55) -> Kepulauan Riau | C55: =INDEX(Profil_Perusahaan!$C$2:$C$774,$G55) -> Exporter and Producer | D55: =INDEX(Profil_Perusahaan!$D$2:$D$774,$G55) -> 18 | E55: =INDEX(Profil_Perusahaan!$E$2:$E$774,$G55)/10^6 -> 0.54906488 | F55: =INDEX(Profil_Perusahaan!$F$2:$F$774,$G55)/10^6 -> 0.16347621 | G55: =MATCH(LARGE(Profil_Perusahaan!$G$2:$G$774,ROWS(A$43:A55)),Profil_Perusahaan!$G$2:$G$774,0) -> 151
A56: =INDEX(Profil_Perusahaan!$A$2:$A$774,$G56) -> BINUANG SAKTI PERKASA, CV | B56: =INDEX(Profil_Perusahaan!$B$2:$B$774,$G56) -> Sulawesi Tengah | C56: =INDEX(Profil_Perusahaan!$C$2:$C$774,$G56) -> Exporter and Producer | D56: =INDEX(Profil_Perusahaan!$D$2:$D$774,$G56) -> 17 | E56: =INDEX(Profil_Perusahaan!$E$2:$E$774,$G56)/10^6 -> 0.59723917 | F56: =INDEX(Profil_Perusahaan!$F$2:$F$774,$G56)/10^6 -> 0.10180542 | G56: =MATCH(LARGE(Profil_Perusahaan!$G$2:$G$774,ROWS(A$43:A56)),Profil_Perusahaan!$G$2:$G$774,0) -> 157
A57: =INDEX(Profil_Perusahaan!$A$2:$A$774,$G57) -> SUMBER AIR HIDUP SENTOSA, PT | B57: =INDEX(Profil_Perusahaan!$B$2:$B$774,$G57) -> DKI Jakarta | C57: =INDEX(Profil_Perusahaan!$C$2:$C$774,$G57) -> Exporter | D57: =INDEX(Profil_Perusahaan!$D$2:$D$774,$G57) -> 16 | E57: =INDEX(Profil_Perusahaan!$E$2:$E$774,$G57)/10^6 -> 0.17886797 | F57: =INDEX(Profil_Perusahaan!$F$2:$F$774,$G57)/10^6 -> 0.041402285 | G57: =MATCH(LARGE(Profil_Perusahaan!$G$2:$G$774,ROWS(A$43:A57)),Profil_Perusahaan!$G$2:$G$774,0) -> 677

Sheet Celah_Pasokan
A1: Celah Pasokan: HS Bernilai Besar dengan Keterwakilan Rendah
A2: Alat skrining: kode HS dengan nilai ekspor tinggi yang belum/jarang diwakili listing eksportir di direktori
A4: ="Dari "&FIXED(COUNTIF(Data_HS!$D$2:$D$8217,">="&p_nilai_besar),0)&" kode HS bernilai ≥ US$ "&ROUND(p_nilai_besar/10^6,0)&" juta, "&FIXED(COUNTIF(Data_HS!$I$2:$I$8217,"Belum terwakili"),0)&" belum punya listing eksportir (nilai US$ "&ROUND(SUMIFS(Data_HS!$D$2:$D$8217,Data_HS!$I$2:$I$8217,"Belum terwakili")/10^9,1)&" miliar = "&ROUND(SUMIFS(Data_HS!$D$2:$D$8217,Data_HS!$I$2:$I$8217,"Belum terwakili")/SUM(Data_HS!$D$2:$D$8217)*100,1)&"% ekspor nasional Jan–Nov 2025)." -> Dari 1,308 kode HS bernilai ≥ US$ 10 juta, 1,187 belum punya listing eksportir (nilai US$ 201.1 miliar = 85.7% ekspor nasional Jan–Nov 2025).
A7: 30 kode HS prioritas (urut skor peluang = nilai FOB ÷ (1 + jumlah listing))
A8: Peringkat | B8: Kode HS | C8: Deskripsi | D8: Bab | E8: Nama bab | F8: Nilai FOB (USD juta) | G8: Harga (USD/kg) | H8: Listing eksportir | I8: Status pasokan | J8: Skor peluang (USD juta) | K8: Baris (helper)
A9: 1 | B9: =INDEX(Data_HS!$A$2:$A$8217,$K9) -> 72026000 | C9: =INDEX(Data_HS!$B$2:$B$8217,$K9) -> Ferro-nickel | D9: =INDEX(Data_HS!$F$2:$F$8217,$K9) -> 72 | E9: =INDEX(Bab_HS!$B$6:$B$104,MATCH(D9,Bab_HS!$A$6:$A$104,0)) -> Besi & baja | F9: =INDEX(Data_HS!$D$2:$D$8217,$K9)/10^6 -> 14941.058 | G9: =INDEX(Data_HS!$E$2:$E$8217,$K9) -> 1.4281334 | H9: =INDEX(Data_HS!$G$2:$G$8217,$K9) -> 0 | I9: =INDEX(Data_HS!$I$2:$I$8217,$K9) -> Belum terwakili | J9: =INDEX(Data_HS!$K$2:$K$8217,$K9)/10^6 -> 14941.058 | K9: =MATCH(LARGE(Data_HS!$L$2:$L$8217,A9),Data_HS!$L$2:$L$8217,0) -> 4553
A10: 2 | B10: =INDEX(Data_HS!$A$2:$A$8217,$K10) -> 15119037 | C10: =INDEX(Data_HS!$B$2:$B$8217,$K10) -> Liquid fractions of palm oil, refined oil, but not chemically modified, with iodine value 55 or more, but less than 60 | D10: =INDEX(Data_HS!$F$2:$F$8217,$K10) -> 15 | E10: =INDEX(Bab_HS!$B$6:$B$104,MATCH(D10,Bab_HS!$A$6:$A$104,0)) -> Lemak & minyak nabati/hewani | F10: =INDEX(Data_HS!$D$2:$D$8217,$K10)/10^6 -> 9998.5251 | G10: =INDEX(Data_HS!$E$2:$E$8217,$K10) -> 1.0186456 | H10: =INDEX(Data_HS!$G$2:$G$8217,$K10) -> 0 | I10: =INDEX(Data_HS!$I$2:$I$8217,$K10) -> Belum terwakili | J10: =INDEX(Data_HS!$K$2:$K$8217,$K10)/10^6 -> 9998.5251 | K10: =MATCH(LARGE(Data_HS!$L$2:$L$8217,A10),Data_HS!$L$2:$L$8217,0) -> 748
A11: 3 | B11: =INDEX(Data_HS!$A$2:$A$8217,$K11) -> 71131990 | C11: =INDEX(Data_HS!$B$2:$B$8217,$K11) -> Articles of other precious metal jewellery (other than its parts), other than of silver, whether or not plated or clad with precious metal | D11: =INDEX(Data_HS!$F$2:$F$8217,$K11) -> 71 | E11: =INDEX(Bab_HS!$B$6:$B$104,MATCH(D11,Bab_HS!$A$6:$A$104,0)) -> Mutiara, permata & logam mulia | F11: =INDEX(Data_HS!$D$2:$D$8217,$K11)/10^6 -> 6753.5157 | G11: =INDEX(Data_HS!$E$2:$E$8217,$K11) -> 93132.673 | H11: =INDEX(Data_HS!$G$2:$G$8217,$K11) -> 0 | I11: =INDEX(Data_HS!$I$2:$I$8217,$K11) -> Belum terwakili | J11: =INDEX(Data_HS!$K$2:$K$8217,$K11)/10^6 -> 6753.5157 | K11: =MATCH(LARGE(Data_HS!$L$2:$L$8217,A11),Data_HS!$L$2:$L$8217,0) -> 4527
A12: 4 | B12: =INDEX(Data_HS!$A$2:$A$8217,$K12) -> 15119020 | C12: =INDEX(Data_HS!$B$2:$B$8217,$K12) -> Refined palm oil | D12: =INDEX(Data_HS!$F$2:$F$8217,$K12) -> 15 | E12: =INDEX(Bab_HS!$B$6:$B$104,MATCH(D12,Bab_HS!$A$6:$A$104,0)) -> Lemak & minyak nabati/hewani | F12: =INDEX(Data_HS!$D$2:$D$8217,$K12)/10^6 -> 5248.687 | G12: =INDEX(Data_HS!$E$2:$E$8217,$K12) -> 1.0302279 | H12: =INDEX(Data_HS!$G$2:$G$8217,$K12) -> 0 | I12: =INDEX(Data_HS!$I$2:$I$8217,$K12) -> Belum terwakili | J12: =INDEX(Data_HS!$K$2:$K$8217,$K12)/10^6 -> 5248.687 | K12: =MATCH(LARGE(Data_HS!$L$2:$L$8217,A12),Data_HS!$L$2:$L$8217,0) -> 744
A13: 5 | B13: =INDEX(Data_HS!$A$2:$A$8217,$K13) -> 27021000 | C13: =INDEX(Data_HS!$B$2:$B$8217,$K13) -> Lignite, whether or not pulverised, but not agglomerated | D13: =INDEX(Data_HS!$F$2:$F$8217,$K13) -> 27 | E13: =INDEX(Bab_HS!$B$6:$B$104,MATCH(D13,Bab_HS!$A$6:$A$104,0)) -> Batubara, migas & bahan bakar | F13: =INDEX(Data_HS!$D$2:$D$8217,$K13)/10^6 -> 5051.5174 | G13: =INDEX(Data_HS!$E$2:$E$8217,$K13) | H13: =INDEX(Data_HS!$G$2:$G$8217,$K13) -> 0 | I13: =INDEX(Data_HS!$I$2:$I$8217,$K13) -> Belum terwakili | J13: =INDEX(Data_HS!$K$2:$K$8217,$K13)/10^6 -> 5051.5174 | K13: =MATCH(LARGE(Data_HS!$L$2:$L$8217,A13),Data_HS!$L$2:$L$8217,0) -> 1313
A14: 6 | B14: =INDEX(Data_HS!$A$2:$A$8217,$K14) -> 27111100 | C14: =INDEX(Data_HS!$B$2:$B$8217,$K14) -> Liquefied, natural gas | D14: =INDEX(Data_HS!$F$2:$F$8217,$K14) -> 27 | E14: =INDEX(Bab_HS!$B$6:$B$104,MATCH(D14,Bab_HS!$A$6:$A$104,0)) -> Batubara, migas & bahan bakar | F14: =INDEX(Data_HS!$D$2:$D$8217,$K14)/10^6 -> 4966.8666 | G14: =INDEX(Data_HS!$E$2:$E$8217,$K14) -> 0.51053798 | H14: =INDEX(Data_HS!$G$2:$G$8217,$K14) -> 0 | I14: =INDEX(Data_HS!$I$2:$I$8217,$K14) -> Belum terwakili | J14: =INDEX(Data_HS!$K$2:$K$8217,$K14)/10^6 -> 4966.8666 | K14: =MATCH(LARGE(Data_HS!$L$2:$L$8217,A14),Data_HS!$L$2:$L$8217,0) -> 1345
A15: 7 | B15: =INDEX(Data_HS!$A$2:$A$8217,$K15) -> 75012000 | C15: =INDEX(Data_HS!$B$2:$B$8217,$K15) -> Nickel oxide sinters and other intermediate products; of nickel metallurgy | D15: =INDEX(Data_HS!$F$2:$F$8217,$K15) -> 75 | E15: =INDEX(Bab_HS!$B$6:$B$104,MATCH(D15,Bab_HS!$A$6:$A$104,0)) -> Nikel | F15: =INDEX(Data_HS!$D$2:$D$8217,$K15)/10^6 -> 4843.0894 | G15: =INDEX(Data_HS!$E$2:$E$8217,$K15) -> 2.6637322 | H15: =INDEX(Data_HS!$G$2:$G$8217,$K15) -> 0 | I15: =INDEX(Data_HS!$I$2:$I$8217,$K15) -> Belum terwakili | J15: =INDEX(Data_HS!$K$2:$K$8217,$K15)/10^6 -> 4843.0894 | K15: =MATCH(LARGE(Data_HS!$L$2:$L$8217,A15),Data_HS!$L$2:$L$8217,0) -> 5097
A16: 8 | B16: =INDEX(Data_HS!$A$2:$A$8217,$K16) -> 26030000 | C16: =INDEX(Data_HS!$B$2:$B$8217,$K16) -> Copper ores and concentrates | D16: =INDEX(Data_HS!$F$2:$F$8217,$K16) -> 26 | E16: =INDEX(Bab_HS!$B$6:$B$104,MATCH(D16,Bab_HS!$A$6:$A$104,0)) -> Bijih, terak & abu logam | F16: =INDEX(Data_HS!$D$2:$D$8217,$K16)/10^6 -> 4545.5013 | G16: =INDEX(Data_HS!$E$2:$E$8217,$K16) -> 3.3306809 | H16: =INDEX(Data_HS!$G$2:$G$8217,$K16) -> 0 | I16: =INDEX(Data_HS!$I$2:$I$8217,$K16) -> Belum terwakili | J16: =INDEX(Data_HS!$K$2:$K$8217,$K16)/10^6 -> 4545.5013 | K16: =MATCH(LARGE(Data_HS!$L$2:$L$8217,A16),Data_HS!$L$2:$L$8217,0) -> 1294
A17: 9 | B17: =INDEX(Data_HS!$A$2:$A$8217,$K17) -> 87032259 | C17: =INDEX(Data_HS!$B$2:$B$8217,$K17) -> Motor cars (including station wagons and sports cars, but not including vans), other than of 4-wheel drive, with only spark-ignition internal combustion piston engine, of a cylinder capacity > 1,000 cc but ≤ 1,500 cc, other than CKD | D17: =INDEX(Data_HS!$F$2:$F$8217,$K17) -> 87 | E17: =INDEX(Bab_HS!$B$6:$B$104,MATCH(D17,Bab_HS!$A$6:$A$104,0)) -> Kendaraan bermotor | F17: =INDEX(Data_HS!$D$2:$D$8217,$K17)/10^6 -> 3584.1137 | G17: =INDEX(Data_HS!$E$2:$E$8217,$K17) -> 9.7744816 | H17: =INDEX(Data_HS!$G$2:$G$8217,$K17) -> 0 | I17: =INDEX(Data_HS!$I$2:$I$8217,$K17) -> Belum terwakili | J17: =INDEX(Data_HS!$K$2:$K$8217,$K17)/10^6 -> 3584.1137 | K17: =MATCH(LARGE(Data_HS!$L$2:$L$8217,A17),Data_HS!$L$2:$L$8217,0) -> 7233
A18: 10 | B18: =INDEX(Data_HS!$A$2:$A$8217,$K18) -> 27011290 | C18: =INDEX(Data_HS!$B$2:$B$8217,$K18) -> Bituminous coal, whether or not pulverised, but not agglomerated, other than coking coal | D18: =INDEX(Data_HS!$F$2:$F$8217,$K18) -> 27 | E18: =INDEX(Bab_HS!$B$6:$B$104,MATCH(D18,Bab_HS!$A$6:$A$104,0)) -> Batubara, migas & bahan bakar | F18: =INDEX(Data_HS!$D$2:$D$8217,$K18)/10^6 -> 3150.4652 | G18: =INDEX(Data_HS!$E$2:$E$8217,$K18) -> 0.08180771 | H18: =INDEX(Data_HS!$G$2:$G$8217,$K18) -> 0 | I18: =INDEX(Data_HS!$I$2:$I$8217,$K18) -> Belum terwakili | J18: =INDEX(Data_HS!$K$2:$K$8217,$K18)/10^6 -> 3150.4652 | K18: =MATCH(LARGE(Data_HS!$L$2:$L$8217,A18),Data_HS!$L$2:$L$8217,0) -> 1311
A19: 11 | B19: =INDEX(Data_HS!$A$2:$A$8217,$K19) -> 40012220 | C19: =INDEX(Data_HS!$B$2:$B$8217,$K19) -> Technically specified natural rubber (TSNR) 20 | D19: =INDEX(Data_HS!$F$2:$F$8217,$K19) -> 40 | E19: =INDEX(Bab_HS!$B$6:$B$104,MATCH(D19,Bab_HS!$A$6:$A$104,0)) -> Karet & barang karet | F19: =INDEX(Data_HS!$D$2:$D$8217,$K19)/10^6 -> 2485.8537 | G19: =INDEX(Data_HS!$E$2:$E$8217,$K19) -> 1.8898377 | H19: =INDEX(Data_HS!$G$2:$G$8217,$K19) -> 0 | I19: =INDEX(Data_HS!$I$2:$I$8217,$K19) -> Belum terwakili | J19: =INDEX(Data_HS!$K$2:$K$8217,$K19)/10^6 -> 2485.8537 | K19: =MATCH(LARGE(Data_HS!$L$2:$L$8217,A19),Data_HS!$L$2:$L$8217,0) -> 2568
A20: 12 | B20: =INDEX(Data_HS!$A$2:$A$8217,$K20) -> 75011000 | C20: =INDEX(Data_HS!$B$2:$B$8217,$K20) -> Nickel mattes | D20: =INDEX(Data_HS!$F$2:$F$8217,$K20) -> 75 | E20: =INDEX(Bab_HS!$B$6:$B$104,MATCH(D20,Bab_HS!$A$6:$A$104,0)) -> Nikel | F20: =INDEX(Data_HS!$D$2:$D$8217,$K20)/10^6 -> 2476.2362 | G20: =INDEX(Data_HS!$E$2:$E$8217,$K20) -> 9.5992548 | H20: =INDEX(Data_HS!$G$2:$G$8217,$K20) -> 0 | I20: =INDEX(Data_HS!$I$2:$I$8217,$K20) -> Belum terwakili | J20: =INDEX(Data_HS!$K$2:$K$8217,$K20)/10^6 -> 2476.2362 | K20: =MATCH(LARGE(Data_HS!$L$2:$L$8217,A20),Data_HS!$L$2:$L$8217,0) -> 5096
... A38: 30 | B38: =INDEX(Data_HS!$A$2:$A$8217,$K38) -> 76011000 | C38: =INDEX(Data_HS!$B$2:$B$8217,$K38) -> Unwrought aluminium, not alloyed | D38: =INDEX(Data_HS!$F$2:$F$8217,$K38) -> 76 | E38: =INDEX(Bab_HS!$B$6:$B$104,MATCH(D38,Bab_HS!$A$6:$A$104,0)) -> Aluminium | F38: =INDEX(Data_HS!$D$2:$D$8217,$K38)/10^6 -> 1208.8126 | G38: =INDEX(Data_HS!$E$2:$E$8217,$K38) -> 2.6921583 | H38: =INDEX(Data_HS!$G$2:$G$8217,$K38) -> 0 | I38: =INDEX(Data_HS!$I$2:$I$8217,$K38) -> Belum terwakili | J38: =INDEX(Data_HS!$K$2:$K$8217,$K38)/10^6 -> 1208.8126 | K38: =MATCH(LARGE(Data_HS!$L$2:$L$8217,A38),Data_HS!$L$2:$L$8217,0) -> 5112
A40: Catatan: ketiadaan listing tidak berarti tidak ada eksportir. Sebagian komoditas (batubara, nikel, LNG, kendaraan) didominasi pemain besar berizin khusus yang tidak memakai direktori. Gunakan daftar ini untuk skrining, lalu verifikasi di lapangan.

Sheet Metode_Catatan
A1: Metode, Parameter & Catatan Data
A2: Parameter di sel kuning dapat diubah; seluruh analisis akan menghitung ulang otomatis
B4: PARAMETER (ubah sel kuning)
B5: Parameter | C5: Nilai | D5: Keterangan
B6: Jumlah bulan data ekspor nasional | C6: 11 | D6: Data nasional mencakup Januari–November 2025 = 11 bulan. Dipakai untuk mengubah ekspor nasional per HS menjadi rata-rata per bulan.
B7: Ambang nilai 'HS bernilai besar' (USD) | C7: 10000000 | D7: Kode HS dengan nilai FOB ≥ ambang ini dianggap bernilai besar. Dipakai pada status pasokan dan skor peluang.
B8: Batas 'keterwakilan rendah' (jumlah listing) | C8: 3 | D8: HS bernilai besar dengan 1 s.d. nilai ini listing eksportir berstatus 'Keterwakilan rendah'; di atasnya 'Terwakili'.
B11: SUMBER DATA
B12: • HS_Code.csv — ekspor nasional per kode HS 8 digit, periode Januari–November 2025: berat bersih (kg), nilai FOB (USD), dan harga USD/kg. 8.216 kode HS.
B13: • IndonesiaExportir.csv — direktori eksportir: 3.400 baris listing produk dari 773 perusahaan, dengan kode HS, minimum order, kapasitas bulanan, harga FOB, estimasi volume, dan estimasi pendapatan bulanan.
B15: PEMBERSIHAN DATA (sudah diterapkan pada sheet Data_*)
B16: • Encoding file Windows-1252 dan desimal berkoma dibaca dengan benar. Nilai error bawaan sumber dikosongkan: 122 sel galat pembagian nol (USD/kg) di file HS, 552 sel galat nilai (estimasi pendapatan) dan 'TIDAK DIKETAHUI' pada kolom order/kapasitas/volume di file eksportir.
B17: • Kolom USD/kg di file HS dihitung ulang dengan rumus (FOB ÷ berat). 68 kode HS tidak punya data berat, sehingga harga per kg-nya kosong (nilai FOB tetap dihitung).
B18: • Nilai '-' pada Jenis Usaha, Pelabuhan, Terms of Payment, dan Incoterms diganti 'Tidak diketahui'. Nama provinsi diterjemahkan ke Bahasa Indonesia dan akhiran '- INDONESIA' dibuang.
B19: • 33 baris memiliki nama perusahaan dengan spasi ganda atau tanda '~'; dirapikan agar pencocokan rumus akurat. Kolom alamat, email, telepon, dan tautan produk tidak dibawa karena tidak diperlukan analisis.
B20: • Deskripsi HS: akhiran ' –' dibuang. Simbol ≥/≤ rusak di file sumber dan tampil sebagai '?'; hanya pola 'but ?' yang dipulihkan menjadi '≤'. Sisanya dibiarkan karena arahnya tidak dapat dipastikan.
B22: DEFINISI & METODE
B23: • Bab HS = 2 digit pertama kode HS. 'Bab 0' adalah listing eksportir dengan kode HS 00000000 (tidak terklasifikasi).
B24: • Segmen harga (USD/kg): Di bawah 1 · 1–5 · 5–20 · 20–100 · 100 ke atas. Batas segmen tetap (bukan parameter).
... B34: • Ekspor nasional adalah Jan–Nov 2025 (11 bulan), bukan setahun penuh.

Sheet Data_HS
A1: Kode HS | B1: Deskripsi HS | C1: Berat bersih (kg) | D1: Nilai FOB (USD) | E1: USD per kg | F1: Bab | G1: Listing eksportir | H1: Segmen harga (USD/kg) | I1: Status pasokan | J1: Urut nilai (helper) | K1: Skor peluang (USD) | L1: Urut peluang (helper)
A2: 01012900 | B2: Live horses, other than pure-bred breeding animals | C2: 2559 | D2: 12142 | E2: =IF(AND(ISNUMBER(C2),C2>0),D2/C2,"") -> 4.7448222 | F2: =VALUE(LEFT(A2,2)) -> 1 | G2: =COUNTIF(Data_Eksportir!$H$2:$H$3401,A2) -> 0 | H2: =IF(E2="","Tanpa data berat",IF(E2<1,"Di bawah 1",IF(E2<5,"1 – 5",IF(E2<20,"5 – 20",IF(E2<100,"20 – 100","100 ke atas"))))) -> 1 – 5 | I2: =IF(D2<p_nilai_besar,"Di bawah ambang nilai",IF(G2=0,"Belum terwakili",IF(G2<=p_listing_rendah,"Keterwakilan rendah","Terwakili"))) -> Di bawah ambang nilai | J2: =D2+ROW()/10^6 -> 12142 | K2: =IF(D2>=p_nilai_besar,D2/(1+G2),0) -> 0 | L2: =IF(K2>0,K2+ROW()/10^6,0) -> 0
A3: 01013090 | B3: Live asses, other than pure-bred breeding animals | C3: 32 | D3: 982 | E3: =IF(AND(ISNUMBER(C3),C3>0),D3/C3,"") -> 30.6875 | F3: =VALUE(LEFT(A3,2)) -> 1 | G3: =COUNTIF(Data_Eksportir!$H$2:$H$3401,A3) -> 0 | H3: =IF(E3="","Tanpa data berat",IF(E3<1,"Di bawah 1",IF(E3<5,"1 – 5",IF(E3<20,"5 – 20",IF(E3<100,"20 – 100","100 ke atas"))))) -> 20 – 100 | I3: =IF(D3<p_nilai_besar,"Di bawah ambang nilai",IF(G3=0,"Belum terwakili",IF(G3<=p_listing_rendah,"Keterwakilan rendah","Terwakili"))) -> Di bawah ambang nilai | J3: =D3+ROW()/10^6 -> 982 | K3: =IF(D3>=p_nilai_besar,D3/(1+G3),0) -> 0 | L3: =IF(K3>0,K3+ROW()/10^6,0) -> 0
A4: 01051110 | B4: Breeding fowls of the species gallus domesticus, weighing not more than 185 g | C4: 27669 | D4: 584975 | E4: =IF(AND(ISNUMBER(C4),C4>0),D4/C4,"") -> 21.141892 | F4: =VALUE(LEFT(A4,2)) -> 1 | G4: =COUNTIF(Data_Eksportir!$H$2:$H$3401,A4) -> 0 | H4: =IF(E4="","Tanpa data berat",IF(E4<1,"Di bawah 1",IF(E4<5,"1 – 5",IF(E4<20,"5 – 20",IF(E4<100,"20 – 100","100 ke atas"))))) -> 20 – 100 | I4: =IF(D4<p_nilai_besar,"Di bawah ambang nilai",IF(G4=0,"Belum terwakili",IF(G4<=p_listing_rendah,"Keterwakilan rendah","Terwakili"))) -> Di bawah ambang nilai | J4: =D4+ROW()/10^6 -> 584975 | K4: =IF(D4>=p_nilai_besar,D4/(1+G4),0) -> 0 | L4: =IF(K4>0,K4+ROW()/10^6,0) -> 0
A5: 01051190 | B5: Live fowls of the species gallus domesticus, other than breeding, weighing not more than 185 g | C5: 100 | D5: 2000 | E5: =IF(AND(ISNUMBER(C5),C5>0),D5/C5,"") -> 20 | F5: =VALUE(LEFT(A5,2)) -> 1 | G5: =COUNTIF(Data_Eksportir!$H$2:$H$3401,A5) -> 0 | H5: =IF(E5="","Tanpa data berat",IF(E5<1,"Di bawah 1",IF(E5<5,"1 – 5",IF(E5<20,"5 – 20",IF(E5<100,"20 – 100","100 ke atas"))))) -> 20 – 100 | I5: =IF(D5<p_nilai_besar,"Di bawah ambang nilai",IF(G5=0,"Belum terwakili",IF(G5<=p_listing_rendah,"Keterwakilan rendah","Terwakili"))) -> Di bawah ambang nilai | J5: =D5+ROW()/10^6 -> 2000 | K5: =IF(D5>=p_nilai_besar,D5/(1+G5),0) -> 0 | L5: =IF(K5>0,K5+ROW()/10^6,0) -> 0
A6: 01051290 | B6: Live turkeys, other than breeding, weighing not more than 185 g | C6: 5 | D6: 50 | E6: =IF(AND(ISNUMBER(C6),C6>0),D6/C6,"") -> 10 | F6: =VALUE(LEFT(A6,2)) -> 1 | G6: =COUNTIF(Data_Eksportir!$H$2:$H$3401,A6) -> 0 | H6: =IF(E6="","Tanpa data berat",IF(E6<1,"Di bawah 1",IF(E6<5,"1 – 5",IF(E6<20,"5 – 20",IF(E6<100,"20 – 100","100 ke atas"))))) -> 5 – 20 | I6: =IF(D6<p_nilai_besar,"Di bawah ambang nilai",IF(G6=0,"Belum terwakili",IF(G6<=p_listing_rendah,"Keterwakilan rendah","Terwakili"))) -> Di bawah ambang nilai | J6: =D6+ROW()/10^6 -> 50.000006 | K6: =IF(D6>=p_nilai_besar,D6/(1+G6),0) -> 0 | L6: =IF(K6>0,K6+ROW()/10^6,0) -> 0
A7: 01059441 | B7: Live fighting cocks of the species gallus domesticus, 185 g ? weighing ? 2 kg | C7: 1800 | D7: 2475 | E7: =IF(AND(ISNUMBER(C7),C7>0),D7/C7,"") -> 1.375 | F7: =VALUE(LEFT(A7,2)) -> 1 | G7: =COUNTIF(Data_Eksportir!$H$2:$H$3401,A7) -> 0 | H7: =IF(E7="","Tanpa data berat",IF(E7<1,"Di bawah 1",IF(E7<5,"1 – 5",IF(E7<20,"5 – 20",IF(E7<100,"20 – 100","100 ke atas"))))) -> 1 – 5 | I7: =IF(D7<p_nilai_besar,"Di bawah ambang nilai",IF(G7=0,"Belum terwakili",IF(G7<=p_listing_rendah,"Keterwakilan rendah","Terwakili"))) -> Di bawah ambang nilai | J7: =D7+ROW()/10^6 -> 2475 | K7: =IF(D7>=p_nilai_besar,D7/(1+G7),0) -> 0 | L7: =IF(K7>0,K7+ROW()/10^6,0) -> 0
A8: 01059449 | B8: Live fighting cocks of the species gallus domesticus, weighing more than 2 kg | C8: 120 | D8: 2700 | E8: =IF(AND(ISNUMBER(C8),C8>0),D8/C8,"") -> 22.5 | F8: =VALUE(LEFT(A8,2)) -> 1 | G8: =COUNTIF(Data_Eksportir!$H$2:$H$3401,A8) -> 0 | H8: =IF(E8="","Tanpa data berat",IF(E8<1,"Di bawah 1",IF(E8<5,"1 – 5",IF(E8<20,"5 – 20",IF(E8<100,"20 – 100","100 ke atas"))))) -> 20 – 100 | I8: =IF(D8<p_nilai_besar,"Di bawah ambang nilai",IF(G8=0,"Belum terwakili",IF(G8<=p_listing_rendah,"Keterwakilan rendah","Terwakili"))) -> Di bawah ambang nilai | J8: =D8+ROW()/10^6 -> 2700 | K8: =IF(D8>=p_nilai_besar,D8/(1+G8),0) -> 0 | L8: =IF(K8>0,K8+ROW()/10^6,0) -> 0
A9: 01059491 | B9: Live fowls of the species gallus domesticus, other than breeding fowls and fighting cocks, 185 g ? weighing ? 2 kg | C9: 54173 | D9: 108749 | E9: =IF(AND(ISNUMBER(C9),C9>0),D9/C9,"") -> 2.0074391 | F9: =VALUE(LEFT(A9,2)) -> 1 | G9: =COUNTIF(Data_Eksportir!$H$2:$H$3401,A9) -> 0 | H9: =IF(E9="","Tanpa data berat",IF(E9<1,"Di bawah 1",IF(E9<5,"1 – 5",IF(E9<20,"5 – 20",IF(E9<100,"20 – 100","100 ke atas"))))) -> 1 – 5 | I9: =IF(D9<p_nilai_besar,"Di bawah ambang nilai",IF(G9=0,"Belum terwakili",IF(G9<=p_listing_rendah,"Keterwakilan rendah","Terwakili"))) -> Di bawah ambang nilai | J9: =D9+ROW()/10^6 -> 108749 | K9: =IF(D9>=p_nilai_besar,D9/(1+G9),0) -> 0 | L9: =IF(K9>0,K9+ROW()/10^6,0) -> 0
A10: 01059940 | B10: Live geese, turkeys, and guinea fowls, other than breeding, weighing more than 185 g | C10: 12 | D10: 960 | E10: =IF(AND(ISNUMBER(C10),C10>0),D10/C10,"") -> 80 | F10: =VALUE(LEFT(A10,2)) -> 1 | G10: =COUNTIF(Data_Eksportir!$H$2:$H$3401,A10) -> 0 | H10: =IF(E10="","Tanpa data berat",IF(E10<1,"Di bawah 1",IF(E10<5,"1 – 5",IF(E10<20,"5 – 20",IF(E10<100,"20 – 100","100 ke atas"))))) -> 20 – 100 | I10: =IF(D10<p_nilai_besar,"Di bawah ambang nilai",IF(G10=0,"Belum terwakili",IF(G10<=p_listing_rendah,"Keterwakilan rendah","Terwakili"))) -> Di bawah ambang nilai | J10: =D10+ROW()/10^6 -> 960.00001 | K10: =IF(D10>=p_nilai_besar,D10/(1+G10),0) -> 0 | L10: =IF(K10>0,K10+ROW()/10^6,0) -> 0
A11: 01061100 | B11: Live primates | C11: 9938 | D11: 2095092 | E11: =IF(AND(ISNUMBER(C11),C11>0),D11/C11,"") -> 210.81626 | F11: =VALUE(LEFT(A11,2)) -> 1 | G11: =COUNTIF(Data_Eksportir!$H$2:$H$3401,A11) -> 0 | H11: =IF(E11="","Tanpa data berat",IF(E11<1,"Di bawah 1",IF(E11<5,"1 – 5",IF(E11<20,"5 – 20",IF(E11<100,"20 – 100","100 ke atas"))))) -> 100 ke atas | I11: =IF(D11<p_nilai_besar,"Di bawah ambang nilai",IF(G11=0,"Belum terwakili",IF(G11<=p_listing_rendah,"Keterwakilan rendah","Terwakili"))) -> Di bawah ambang nilai | J11: =D11+ROW()/10^6 -> 2095092 | K11: =IF(D11>=p_nilai_besar,D11/(1+G11),0) -> 0 | L11: =IF(K11>0,K11+ROW()/10^6,0) -> 0
A12: 01061400 | B12: Live rabbits and hares | C12: 7 | D12: 31 | E12: =IF(AND(ISNUMBER(C12),C12>0),D12/C12,"") -> 4.4285714 | F12: =VALUE(LEFT(A12,2)) -> 1 | G12: =COUNTIF(Data_Eksportir!$H$2:$H$3401,A12) -> 0 | H12: =IF(E12="","Tanpa data berat",IF(E12<1,"Di bawah 1",IF(E12<5,"1 – 5",IF(E12<20,"5 – 20",IF(E12<100,"20 – 100","100 ke atas"))))) -> 1 – 5 | I12: =IF(D12<p_nilai_besar,"Di bawah ambang nilai",IF(G12=0,"Belum terwakili",IF(G12<=p_listing_rendah,"Keterwakilan rendah","Terwakili"))) -> Di bawah ambang nilai | J12: =D12+ROW()/10^6 -> 31.000012 | K12: =IF(D12>=p_nilai_besar,D12/(1+G12),0) -> 0 | L12: =IF(K12>0,K12+ROW()/10^6,0) -> 0
A13: 01061900 | B13: Live mammals, other than in subheading 010611 to 010614 | C13: 5427 | D13: 99229 | E13: =IF(AND(ISNUMBER(C13),C13>0),D13/C13,"") -> 18.284319 | F13: =VALUE(LEFT(A13,2)) -> 1 | G13: =COUNTIF(Data_Eksportir!$H$2:$H$3401,A13) -> 0 | H13: =IF(E13="","Tanpa data berat",IF(E13<1,"Di bawah 1",IF(E13<5,"1 – 5",IF(E13<20,"5 – 20",IF(E13<100,"20 – 100","100 ke atas"))))) -> 5 – 20 | I13: =IF(D13<p_nilai_besar,"Di bawah ambang nilai",IF(G13=0,"Belum terwakili",IF(G13<=p_listing_rendah,"Keterwakilan rendah","Terwakili"))) -> Di bawah ambang nilai | J13: =D13+ROW()/10^6 -> 99229 | K13: =IF(D13>=p_nilai_besar,D13/(1+G13),0) -> 0 | L13: =IF(K13>0,K13+ROW()/10^6,0) -> 0
... A60: 03019949 | B60: Live freshwater fish, n.ec in heading 0301 and other than carp for breeding | C60: 209741 | D60: 1542191 | E60: =IF(AND(ISNUMBER(C60),C60>0),D60/C60,"") -> 7.3528352 | F60: =VALUE(LEFT(A60,2)) -> 3 | G60: =COUNTIF(Data_Eksportir!$H$2:$H$3401,A60) -> 0 | H60: =IF(E60="","Tanpa data berat",IF(E60<1,"Di bawah 1",IF(E60<5,"1 – 5",IF(E60<20,"5 – 20",IF(E60<100,"20 – 100","100 ke atas"))))) -> 5 – 20 | I60: =IF(D60<p_nilai_besar,"Di bawah ambang nilai",IF(G60=0,"Belum terwakili",IF(G60<=p_listing_rendah,"Keterwakilan rendah","Terwakili"))) -> Di bawah ambang nilai | J60: =D60+ROW()/10^6 -> 1542191 | K60: =IF(D60>=p_nilai_besar,D60/(1+G60),0) -> 0 | L60: =IF(K60>0,K60+ROW()/10^6,0) -> 0
A61: 03019950 | B61: Live marine fish, n.e.c in heading 0301 | D61: 100 | E61: =IF(AND(ISNUMBER(C61),C61>0),D61/C61,"") | F61: =VALUE(LEFT(A61,2)) -> 3 | G61: =COUNTIF(Data_Eksportir!$H$2:$H$3401,A61) -> 0 | H61: =IF(E61="","Tanpa data berat",IF(E61<1,"Di bawah 1",IF(E61<5,"1 – 5",IF(E61<20,"5 – 20",IF(E61<100,"20 – 100","100 ke atas"))))) -> Tanpa data berat | I61: =IF(D61<p_nilai_besar,"Di bawah ambang nilai",IF(G61=0,"Belum terwakili",IF(G61<=p_listing_rendah,"Keterwakilan rendah","Terwakili"))) -> Di bawah ambang nilai | J61: =D61+ROW()/10^6 -> 100.00006 | K61: =IF(D61>=p_nilai_besar,D61/(1+G61),0) -> 0 | L61: =IF(K61>0,K61+ROW()/10^6,0) -> 0
A62: 03019990 | B62: Live fish, other than freshwater and marine fish | C62: 136407 | D62: 548308 | E62: =IF(AND(ISNUMBER(C62),C62>0),D62/C62,"") -> 4.0196471 | F62: =VALUE(LEFT(A62,2)) -> 3 | G62: =COUNTIF(Data_Eksportir!$H$2:$H$3401,A62) -> 0 | H62: =IF(E62="","Tanpa data berat",IF(E62<1,"Di bawah 1",IF(E62<5,"1 – 5",IF(E62<20,"5 – 20",IF(E62<100,"20 – 100","100 ke atas"))))) -> 1 – 5 | I62: =IF(D62<p_nilai_besar,"Di bawah ambang nilai",IF(G62=0,"Belum terwakili",IF(G62<=p_listing_rendah,"Keterwakilan rendah","Terwakili"))) -> Di bawah ambang nilai | J62: =D62+ROW()/10^6 -> 548308 | K62: =IF(D62>=p_nilai_besar,D62/(1+G62),0) -> 0 | L62: =IF(K62>0,K62+ROW()/10^6,0) -> 0
A63: 03022100 | B63: Halibut (reinhardtius hippoglossoides, hippoglossus hippoglossus, hippoglossus stenolepis), fresh or chilled | C63: 768 | D63: 2903 | E63: =IF(AND(ISNUMBER(C63),C63>0),D63/C63,"") -> 3.7799479 | F63: =VALUE(LEFT(A63,2)) -> 3 | G63: =COUNTIF(Data_Eksportir!$H$2:$H$3401,A63) -> 0 | H63: =IF(E63="","Tanpa data berat",IF(E63<1,"Di bawah 1",IF(E63<5,"1 – 5",IF(E63<20,"5 – 20",IF(E63<100,"20 – 100","100 ke atas"))))) -> 1 – 5 | I63: =IF(D63<p_nilai_besar,"Di bawah ambang nilai",IF(G63=0,"Belum terwakili",IF(G63<=p_listing_rendah,"Keterwakilan rendah","Terwakili"))) -> Di bawah ambang nilai | J63: =D63+ROW()/10^6 -> 2903.0001 | K63: =IF(D63>=p_nilai_besar,D63/(1+G63),0) -> 0 | L63: =IF(K63>0,K63+ROW()/10^6,0) -> 0
A64: 03022200 | B64: Plaice (pleuronectes platessa), fresh or chilled | C64: 56 | D64: 426 | E64: =IF(AND(ISNUMBER(C64),C64>0),D64/C64,"") -> 7.6071429 | F64: =VALUE(LEFT(A64,2)) -> 3 | G64: =COUNTIF(Data_Eksportir!$H$2:$H$3401,A64) -> 0 | H64: =IF(E64="","Tanpa data berat",IF(E64<1,"Di bawah 1",IF(E64<5,"1 – 5",IF(E64<20,"5 – 20",IF(E64<100,"20 – 100","100 ke atas"))))) -> 5 – 20 | I64: =IF(D64<p_nilai_besar,"Di bawah ambang nilai",IF(G64=0,"Belum terwakili",IF(G64<=p_listing_rendah,"Keterwakilan rendah","Terwakili"))) -> Di bawah ambang nilai | J64: =D64+ROW()/10^6 -> 426.00006 | K64: =IF(D64>=p_nilai_besar,D64/(1+G64),0) -> 0 | L64: =IF(K64>0,K64+ROW()/10^6,0) -> 0
A65: 03022300 | B65: Sole (solea spp), fresh or chilled | C65: 58830 | D65: 56529 | E65: =IF(AND(ISNUMBER(C65),C65>0),D65/C65,"") -> 0.9608873 | F65: =VALUE(LEFT(A65,2)) -> 3 | G65: =COUNTIF(Data_Eksportir!$H$2:$H$3401,A65) -> 0 | H65: =IF(E65="","Tanpa data berat",IF(E65<1,"Di bawah 1",IF(E65<5,"1 – 5",IF(E65<20,"5 – 20",IF(E65<100,"20 – 100","100 ke atas"))))) -> Di bawah 1 | I65: =IF(D65<p_nilai_besar,"Di bawah ambang nilai",IF(G65=0,"Belum terwakili",IF(G65<=p_listing_rendah,"Keterwakilan rendah","Terwakili"))) -> Di bawah ambang nilai | J65: =D65+ROW()/10^6 -> 56529 | K65: =IF(D65>=p_nilai_besar,D65/(1+G65),0) -> 0 | L65: =IF(K65>0,K65+ROW()/10^6,0) -> 0
A66: 03022900 | B66: Flat fish (pleuronectidae, bothidae, cynoglossidae, soleidae, scophthalmidae and citharidae) other than halibut, plaice, sole, turbots, fresh or chilled | C66: 1926286 | D66: 2148170 | E66: =IF(AND(ISNUMBER(C66),C66>0),D66/C66,"") -> 1.1151875 | F66: =VALUE(LEFT(A66,2)) -> 3 | G66: =COUNTIF(Data_Eksportir!$H$2:$H$3401,A66) -> 0 | H66: =IF(E66="","Tanpa data berat",IF(E66<1,"Di bawah 1",IF(E66<5,"1 – 5",IF(E66<20,"5 – 20",IF(E66<100,"20 – 100","100 ke atas"))))) -> 1 – 5 | I66: =IF(D66<p_nilai_besar,"Di bawah ambang nilai",IF(G66=0,"Belum terwakili",IF(G66<=p_listing_rendah,"Keterwakilan rendah","Terwakili"))) -> Di bawah ambang nilai | J66: =D66+ROW()/10^6 -> 2148170 | K66: =IF(D66>=p_nilai_besar,D66/(1+G66),0) -> 0 | L66: =IF(K66>0,K66+ROW()/10^6,0) -> 0
A67: 03023100 | B67: Albacore or longfinned tunas (thunnus alalunga), fresh or chilled | C67: 100 | D67: 250 | E67: =IF(AND(ISNUMBER(C67),C67>0),D67/C67,"") -> 2.5 | F67: =VALUE(LEFT(A67,2)) -> 3 | G67: =COUNTIF(Data_Eksportir!$H$2:$H$3401,A67) -> 0 | H67: =IF(E67="","Tanpa data berat",IF(E67<1,"Di bawah 1",IF(E67<5,"1 – 5",IF(E67<20,"5 – 20",IF(E67<100,"20 – 100","100 ke atas"))))) -> 1 – 5 | I67: =IF(D67<p_nilai_besar,"Di bawah ambang nilai",IF(G67=0,"Belum terwakili",IF(G67<=p_listing_rendah,"Keterwakilan rendah","Terwakili"))) -> Di bawah ambang nilai | J67: =D67+ROW()/10^6 -> 250.00007 | K67: =IF(D67>=p_nilai_besar,D67/(1+G67),0) -> 0 | L67: =IF(K67>0,K67+ROW()/10^6,0) -> 0
A68: 03023200 | B68: Yellowfin tunas (thunnus albacares), fresh or chilled | C68: 1768797 | D68: 16120221 | E68: =IF(AND(ISNUMBER(C68),C68>0),D68/C68,"") -> 9.1136637 | F68: =VALUE(LEFT(A68,2)) -> 3 | G68: =COUNTIF(Data_Eksportir!$H$2:$H$3401,A68) -> 0 | H68: =IF(E68="","Tanpa data berat",IF(E68<1,"Di bawah 1",IF(E68<5,"1 – 5",IF(E68<20,"5 – 20",IF(E68<100,"20 – 100","100 ke atas"))))) -> 5 – 20 | I68: =IF(D68<p_nilai_besar,"Di bawah ambang nilai",IF(G68=0,"Belum terwakili",IF(G68<=p_listing_rendah,"Keterwakilan rendah","Terwakili"))) -> Belum terwakili | J68: =D68+ROW()/10^6 -> 16120221 | K68: =IF(D68>=p_nilai_besar,D68/(1+G68),0) -> 16120221 | L68: =IF(K68>0,K68+ROW()/10^6,0) -> 16120221
A69: 03023300 | B69: Skipjack tuna (stripe-bellied bonito) (katsuwonus pelamis), fresh or chilled | C69: 260 | D69: 476 | E69: =IF(AND(ISNUMBER(C69),C69>0),D69/C69,"") -> 1.8307692 | F69: =VALUE(LEFT(A69,2)) -> 3 | G69: =COUNTIF(Data_Eksportir!$H$2:$H$3401,A69) -> 2 | H69: =IF(E69="","Tanpa data berat",IF(E69<1,"Di bawah 1",IF(E69<5,"1 – 5",IF(E69<20,"5 – 20",IF(E69<100,"20 – 100","100 ke atas"))))) -> 1 – 5 | I69: =IF(D69<p_nilai_besar,"Di bawah ambang nilai",IF(G69=0,"Belum terwakili",IF(G69<=p_listing_rendah,"Keterwakilan rendah","Terwakili"))) -> Di bawah ambang nilai | J69: =D69+ROW()/10^6 -> 476.00007 | K69: =IF(D69>=p_nilai_besar,D69/(1+G69),0) -> 0 | L69: =IF(K69>0,K69+ROW()/10^6,0) -> 0
A70: 03023400 | B70: Bigeye tunas (thunnus obesus), fresh or chilled | C70: 247683 | D70: 1928507 | E70: =IF(AND(ISNUMBER(C70),C70>0),D70/C70,"") -> 7.7861904 | F70: =VALUE(LEFT(A70,2)) -> 3 | G70: =COUNTIF(Data_Eksportir!$H$2:$H$3401,A70) -> 0 | H70: =IF(E70="","Tanpa data berat",IF(E70<1,"Di bawah 1",IF(E70<5,"1 – 5",IF(E70<20,"5 – 20",IF(E70<100,"20 – 100","100 ke atas"))))) -> 5 – 20 | I70: =IF(D70<p_nilai_besar,"Di bawah ambang nilai",IF(G70=0,"Belum terwakili",IF(G70<=p_listing_rendah,"Keterwakilan rendah","Terwakili"))) -> Di bawah ambang nilai | J70: =D70+ROW()/10^6 -> 1928507 | K70: =IF(D70>=p_nilai_besar,D70/(1+G70),0) -> 0 | L70: =IF(K70>0,K70+ROW()/10^6,0) -> 0
A71: 03023600 | B71: Southern bluefin tunas (thunnus maccoyii), fresh or chilled | C71: 10550 | D71: 96232 | E71: =IF(AND(ISNUMBER(C71),C71>0),D71/C71,"") -> 9.1215166 | F71: =VALUE(LEFT(A71,2)) -> 3 | G71: =COUNTIF(Data_Eksportir!$H$2:$H$3401,A71) -> 0 | H71: =IF(E71="","Tanpa data berat",IF(E71<1,"Di bawah 1",IF(E71<5,"1 – 5",IF(E71<20,"5 – 20",IF(E71<100,"20 – 100","100 ke atas"))))) -> 5 – 20 | I71: =IF(D71<p_nilai_besar,"Di bawah ambang nilai",IF(G71=0,"Belum terwakili",IF(G71<=p_listing_rendah,"Keterwakilan rendah","Terwakili"))) -> Di bawah ambang nilai | J71: =D71+ROW()/10^6 -> 96232 | K71: =IF(D71>=p_nilai_besar,D71/(1+G71),0) -> 0 | L71: =IF(K71>0,K71+ROW()/10^6,0) -> 0
A72: 03023900 | B72: Tunas other than albacore tunas, yellowfin tunas, skipjack tuna, bigeye tunas, atlantic and pacific bluefin tunas, southern bluefin tunas, fresh or chilled | C72: 392798 | D72: 1345390 | E72: =IF(AND(ISNUMBER(C72),C72>0),D72/C72,"") -> 3.4251447 | F72: =VALUE(LEFT(A72,2)) -> 3 | G72: =COUNTIF(Data_Eksportir!$H$2:$H$3401,A72) -> 0 | H72: =IF(E72="","Tanpa data berat",IF(E72<1,"Di bawah 1",IF(E72<5,"1 – 5",IF(E72<20,"5 – 20",IF(E72<100,"20 – 100","100 ke atas"))))) -> 1 – 5 | I72: =IF(D72<p_nilai_besar,"Di bawah ambang nilai",IF(G72=0,"Belum terwakili",IF(G72<=p_listing_rendah,"Keterwakilan rendah","Terwakili"))) -> Di bawah ambang nilai | J72: =D72+ROW()/10^6 -> 1345390 | K72: =IF(D72>=p_nilai_besar,D72/(1+G72),0) -> 0 | L72: =IF(K72>0,K72+ROW()/10^6,0) -> 0
A73: 03024100 | B73: Herrings (clupea harengus, clupea pallasii), fresh or chilled | C73: 46000 | D73: 16790 | E73: =IF(AND(ISNUMBER(C73),C73>0),D73/C73,"") -> 0.365 | F73: =VALUE(LEFT(A73,2)) -> 3 | G73: =COUNTIF(Data_Eksportir!$H$2:$H$3401,A73) -> 0 | H73: =IF(E73="","Tanpa data berat",IF(E73<1,"Di bawah 1",IF(E73<5,"1 – 5",IF(E73<20,"5 – 20",IF(E73<100,"20 – 100","100 ke atas"))))) -> Di bawah 1 | I73: =IF(D73<p_nilai_besar,"Di bawah ambang nilai",IF(G73=0,"Belum terwakili",IF(G73<=p_listing_rendah,"Keterwakilan rendah","Terwakili"))) -> Di bawah ambang nilai | J73: =D73+ROW()/10^6 -> 16790 | K73: =IF(D73>=p_nilai_besar,D73/(1+G73),0) -> 0 | L73: =IF(K73>0,K73+ROW()/10^6,0) -> 0
... A115: 03034990 | B115: Tunas (of the genus thunnus), other than hs code 03024100 to 03024910, frozen | C115: 101744 | D115: 225039 | E115: =IF(AND(ISNUMBER(C115),C115>0),D115/C115,"") -> 2.2118159 | F115: =VALUE(LEFT(A115,2)) -> 3 | G115: =COUNTIF(Data_Eksportir!$H$2:$H$3401,A115) -> 0 | H115: =IF(E115="","Tanpa data berat",IF(E115<1,"Di bawah 1",IF(E115<5,"1 – 5",IF(E115<20,"5 – 20",IF(E115<100,"20 – 100","100 ke atas"))))) -> 1 – 5 | I115: =IF(D115<p_nilai_besar,"Di bawah ambang nilai",IF(G115=0,"Belum terwakili",IF(G115<=p_listing_rendah,"Keterwakilan rendah","Terwakili"))) -> Di bawah ambang nilai | J115: =D115+ROW()/10^6 -> 225039 | K115: =IF(D115>=p_nilai_besar,D115/(1+G115),0) -> 0 | L115: =IF(K115>0,K115+ROW()/10^6,0) -> 0
A116: 03035100 | B116: Herrings (clupea harengus, clupea pallasii), frozen | D116: 102 | E116: =IF(AND(ISNUMBER(C116),C116>0),D116/C116,"") | F116: =VALUE(LEFT(A116,2)) -> 3 | G116: =COUNTIF(Data_Eksportir!$H$2:$H$3401,A116) -> 0 | H116: =IF(E116="","Tanpa data berat",IF(E116<1,"Di bawah 1",IF(E116<5,"1 – 5",IF(E116<20,"5 – 20",IF(E116<100,"20 – 100","100 ke atas"))))) -> Tanpa data berat | I116: =IF(D116<p_nilai_besar,"Di bawah ambang nilai",IF(G116=0,"Belum terwakili",IF(G116<=p_listing_rendah,"Keterwakilan rendah","Terwakili"))) -> Di bawah ambang nilai | J116: =D116+ROW()/10^6 -> 102.00012 | K116: =IF(D116>=p_nilai_besar,D116/(1+G116),0) -> 0 | L116: =IF(K116>0,K116+ROW()/10^6,0) -> 0
A117: 03035300 | B117: Sardines (sardina pilchardus, sardinops spp), sardinella (sardinella spp), brisling or sprats (sprattus sprattus), frozen | C117: 2889113 | D117: 1339586 | E117: =IF(AND(ISNUMBER(C117),C117>0),D117/C117,"") -> 0.46366688 | F117: =VALUE(LEFT(A117,2)) -> 3 | G117: =COUNTIF(Data_Eksportir!$H$2:$H$3401,A117) -> 0 | H117: =IF(E117="","Tanpa data berat",IF(E117<1,"Di bawah 1",IF(E117<5,"1 – 5",IF(E117<20,"5 – 20",IF(E117<100,"20 – 100","100 ke atas"))))) -> Di bawah 1 | I117: =IF(D117<p_nilai_besar,"Di bawah ambang nilai",IF(G117=0,"Belum terwakili",IF(G117<=p_listing_rendah,"Keterwakilan rendah","Terwakili"))) -> Di bawah ambang nilai | J117: =D117+ROW()/10^6 -> 1339586 | K117: =IF(D117>=p_nilai_besar,D117/(1+G117),0) -> 0 | L117: =IF(K117>0,K117+ROW()/10^6,0) -> 0
A118: 03035410 | B118: Mackerel (scomber scombrus, scomber australasicus), frozen | C118: 777703 | D118: 2198470 | E118: =IF(AND(ISNUMBER(C118),C118>0),D118/C118,"") -> 2.8268761 | F118: =VALUE(LEFT(A118,2)) -> 3 | G118: =COUNTIF(Data_Eksportir!$H$2:$H$3401,A118) -> 0 | H118: =IF(E118="","Tanpa data berat",IF(E118<1,"Di bawah 1",IF(E118<5,"1 – 5",IF(E118<20,"5 – 20",IF(E118<100,"20 – 100","100 ke atas"))))) -> 1 – 5 | I118: =IF(D118<p_nilai_besar,"Di bawah ambang nilai",IF(G118=0,"Belum terwakili",IF(G118<=p_listing_rendah,"Keterwakilan rendah","Terwakili"))) -> Di bawah ambang nilai | J118: =D118+ROW()/10^6 -> 2198470 | K118: =IF(D118>=p_nilai_besar,D118/(1+G118),0) -> 0 | L118: =IF(K118>0,K118+ROW()/10^6,0) -> 0
A119: 03035500 | B119: Jack and horse mackerel (trachurus spp), frozen | C119: 1830219 | D119: 1364316 | E119: =IF(AND(ISNUMBER(C119),C119>0),D119/C119,"") -> 0.74543866 | F119: =VALUE(LEFT(A119,2)) -> 3 | G119: =COUNTIF(Data_Eksportir!$H$2:$H$3401,A119) -> 0 | H119: =IF(E119="","Tanpa data berat",IF(E119<1,"Di bawah 1",IF(E119<5,"1 – 5",IF(E119<20,"5 – 20",IF(E119<100,"20 – 100","100 ke atas"))))) -> Di bawah 1 | I119: =IF(D119<p_nilai_besar,"Di bawah ambang nilai",IF(G119=0,"Belum terwakili",IF(G119<=p_listing_rendah,"Keterwakilan rendah","Terwakili"))) -> Di bawah ambang nilai | J119: =D119+ROW()/10^6 -> 1364316 | K119: =IF(D119>=p_nilai_besar,D119/(1+G119),0) -> 0 | L119: =IF(K119>0,K119+ROW()/10^6,0) -> 0
A120: 03035600 | B120: Cobia (rachycentron canadum), frozen | C120: 296094 | D120: 552170 | E120: =IF(AND(ISNUMBER(C120),C120>0),D120/C120,"") -> 1.864847 | F120: =VALUE(LEFT(A120,2)) -> 3 | G120: =COUNTIF(Data_Eksportir!$H$2:$H$3401,A120) -> 0 | H120: =IF(E120="","Tanpa data berat",IF(E120<1,"Di bawah 1",IF(E120<5,"1 – 5",IF(E120<20,"5 – 20",IF(E120<100,"20 – 100","100 ke atas"))))) -> 1 – 5 | I120: =IF(D120<p_nilai_besar,"Di bawah ambang nilai",IF(G120=0,"Belum terwakili",IF(G120<=p_listing_rendah,"Keterwakilan rendah","Terwakili"))) -> Di bawah ambang nilai | J120: =D120+ROW()/10^6 -> 552170 | K120: =IF(D120>=p_nilai_besar,D120/(1+G120),0) -> 0 | L120: =IF(K120>0,K120+ROW()/10^6,0) -> 0
A121: 03035700 | B121: Swordfish (xiphias gladius), frozen | C121: 2377515 | D121: 8985556 | E121: =IF(AND(ISNUMBER(C121),C121>0),D121/C121,"") -> 3.7793898 | F121: =VALUE(LEFT(A121,2)) -> 3 | G121: =COUNTIF(Data_Eksportir!$H$2:$H$3401,A121) -> 0 | H121: =IF(E121="","Tanpa data berat",IF(E121<1,"Di bawah 1",IF(E121<5,"1 – 5",IF(E121<20,"5 – 20",IF(E121<100,"20 – 100","100 ke atas"))))) -> 1 – 5 | I121: =IF(D121<p_nilai_besar,"Di bawah ambang nilai",IF(G121=0,"Belum terwakili",IF(G121<=p_listing_rendah,"Keterwakilan rendah","Terwakili"))) -> Di bawah ambang nilai | J121: =D121+ROW()/10^6 -> 8985556 | K121: =IF(D121>=p_nilai_besar,D121/(1+G121),0) -> 0 | L121: =IF(K121>0,K121+ROW()/10^6,0) -> 0
A122: 03035910 | B122: Indian mackerels (rastrelliger kanagurta), island mackerels (rastrelliger faughni), frozen | C122: 1487605 | D122: 3073691 | E122: =IF(AND(ISNUMBER(C122),C122>0),D122/C122,"") -> 2.066201 | F122: =VALUE(LEFT(A122,2)) -> 3 | G122: =COUNTIF(Data_Eksportir!$H$2:$H$3401,A122) -> 0 | H122: =IF(E122="","Tanpa data berat",IF(E122<1,"Di bawah 1",IF(E122<5,"1 – 5",IF(E122<20,"5 – 20",IF(E122<100,"20 – 100","100 ke atas"))))) -> 1 – 5 | I122: =IF(D122<p_nilai_besar,"Di bawah ambang nilai",IF(G122=0,"Belum terwakili",IF(G122<=p_listing_rendah,"Keterwakilan rendah","Terwakili"))) -> Di bawah ambang nilai | J122: =D122+ROW()/10^6 -> 3073691 | K122: =IF(D122>=p_nilai_besar,D122/(1+G122),0) -> 0 | L122: =IF(K122>0,K122+ROW()/10^6,0) -> 0
A123: 03035920 | B123: Silver pomfrets (pampus spp), frozen | C123: 658020 | D123: 3488612 | E123: =IF(AND(ISNUMBER(C123),C123>0),D123/C123,"") -> 5.3016808 | F123: =VALUE(LEFT(A123,2)) -> 3 | G123: =COUNTIF(Data_Eksportir!$H$2:$H$3401,A123) -> 0 | H123: =IF(E123="","Tanpa data berat",IF(E123<1,"Di bawah 1",IF(E123<5,"1 – 5",IF(E123<20,"5 – 20",IF(E123<100,"20 – 100","100 ke atas"))))) -> 5 – 20 | I123: =IF(D123<p_nilai_besar,"Di bawah ambang nilai",IF(G123=0,"Belum terwakili",IF(G123<=p_listing_rendah,"Keterwakilan rendah","Terwakili"))) -> Di bawah ambang nilai | J123: =D123+ROW()/10^6 -> 3488612 | K123: =IF(D123>=p_nilai_besar,D123/(1+G123),0) -> 0 | L123: =IF(K123>0,K123+ROW()/10^6,0) -> 0
A124: 03035990 | B124: Anchovies, brisling or sprats, scomberomorus spp, caranx spp, pacific saury, decapterus spp, capelin, euthynnusaffinis, sarda spp, marlins, sailfishes, istiophoridae, frozen | C124: 18648122 | D124: 40904702 | E124: =IF(AND(ISNUMBER(C124),C124>0),D124/C124,"") -> 2.1935025 | F124: =VALUE(LEFT(A124,2)) -> 3 | G124: =COUNTIF(Data_Eksportir!$H$2:$H$3401,A124) -> 0 | H124: =IF(E124="","Tanpa data berat",IF(E124<1,"Di bawah 1",IF(E124<5,"1 – 5",IF(E124<20,"5 – 20",IF(E124<100,"20 – 100","100 ke atas"))))) -> 1 – 5 | I124: =IF(D124<p_nilai_besar,"Di bawah ambang nilai",IF(G124=0,"Belum terwakili",IF(G124<=p_listing_rendah,"Keterwakilan rendah","Terwakili"))) -> Belum terwakili | J124: =D124+ROW()/10^6 -> 40904702 | K124: =IF(D124>=p_nilai_besar,D124/(1+G124),0) -> 40904702 | L124: =IF(K124>0,K124+ROW()/10^6,0) -> 40904702
A125: 03036700 | B125: Alaska pollock (theragra chalcogramma), frozen | C125: 32400 | D125: 34020 | E125: =IF(AND(ISNUMBER(C125),C125>0),D125/C125,"") -> 1.05 | F125: =VALUE(LEFT(A125,2)) -> 3 | G125: =COUNTIF(Data_Eksportir!$H$2:$H$3401,A125) -> 0 | H125: =IF(E125="","Tanpa data berat",IF(E125<1,"Di bawah 1",IF(E125<5,"1 – 5",IF(E125<20,"5 – 20",IF(E125<100,"20 – 100","100 ke atas"))))) -> 1 – 5 | I125: =IF(D125<p_nilai_besar,"Di bawah ambang nilai",IF(G125=0,"Belum terwakili",IF(G125<=p_listing_rendah,"Keterwakilan rendah","Terwakili"))) -> Di bawah ambang nilai | J125: =D125+ROW()/10^6 -> 34020 | K125: =IF(D125>=p_nilai_besar,D125/(1+G125),0) -> 0 | L125: =IF(K125>0,K125+ROW()/10^6,0) -> 0
A126: 03036900 | B126: Fish of the families bregmacerotidae, euclichthyidae, gadidae, macrouridae, melanonidae, merlucciidae, moridae and muraenolepididae other than of hs code 030336-030368, frozen | C126: 26344 | D126: 85801 | E126: =IF(AND(ISNUMBER(C126),C126>0),D126/C126,"") -> 3.2569466 | F126: =VALUE(LEFT(A126,2)) -> 3 | G126: =COUNTIF(Data_Eksportir!$H$2:$H$3401,A126) -> 0 | H126: =IF(E126="","Tanpa data berat",IF(E126<1,"Di bawah 1",IF(E126<5,"1 – 5",IF(E126<20,"5 – 20",IF(E126<100,"20 – 100","100 ke atas"))))) -> 1 – 5 | I126: =IF(D126<p_nilai_besar,"Di bawah ambang nilai",IF(G126=0,"Belum terwakili",IF(G126<=p_listing_rendah,"Keterwakilan rendah","Terwakili"))) -> Di bawah ambang nilai | J126: =D126+ROW()/10^6 -> 85801 | K126: =IF(D126>=p_nilai_besar,D126/(1+G126),0) -> 0 | L126: =IF(K126>0,K126+ROW()/10^6,0) -> 0
A127: 03038100 | B127: Dogfish and other sharks, frozen | C127: 2201020 | D127: 3358550 | E127: =IF(AND(ISNUMBER(C127),C127>0),D127/C127,"") -> 1.5259062 | F127: =VALUE(LEFT(A127,2)) -> 3 | G127: =COUNTIF(Data_Eksportir!$H$2:$H$3401,A127) -> 0 | H127: =IF(E127="","Tanpa data berat",IF(E127<1,"Di bawah 1",IF(E127<5,"1 – 5",IF(E127<20,"5 – 20",IF(E127<100,"20 – 100","100 ke atas"))))) -> 1 – 5 | I127: =IF(D127<p_nilai_besar,"Di bawah ambang nilai",IF(G127=0,"Belum terwakili",IF(G127<=p_listing_rendah,"Keterwakilan rendah","Terwakili"))) -> Di bawah ambang nilai | J127: =D127+ROW()/10^6 -> 3358550 | K127: =IF(D127>=p_nilai_besar,D127/(1+G127),0) -> 0 | L127: =IF(K127>0,K127+ROW()/10^6,0) -> 0
A128: 03038200 | B128: Rays and skates (rajidae), frozen | C128: 1010230 | D128: 2514460 | E128: =IF(AND(ISNUMBER(C128),C128>0),D128/C128,"") -> 2.4889976 | F128: =VALUE(LEFT(A128,2)) -> 3 | G128: =COUNTIF(Data_Eksportir!$H$2:$H$3401,A128) -> 0 | H128: =IF(E128="","Tanpa data berat",IF(E128<1,"Di bawah 1",IF(E128<5,"1 – 5",IF(E128<20,"5 – 20",IF(E128<100,"20 – 100","100 ke atas"))))) -> 1 – 5 | I128: =IF(D128<p_nilai_besar,"Di bawah ambang nilai",IF(G128=0,"Belum terwakili",IF(G128<=p_listing_rendah,"Keterwakilan rendah","Terwakili"))) -> Di bawah ambang nilai | J128: =D128+ROW()/10^6 -> 2514460 | K128: =IF(D128>=p_nilai_besar,D128/(1+G128),0) -> 0 | L128: =IF(K128>0,K128+ROW()/10^6,0) -> 0
... A580: 09096110 | B580: Seeds of anise, neither crushed nor ground | C580: 1811 | D580: 15083 | E580: =IF(AND(ISNUMBER(C580),C580>0),D580/C580,"") -> 8.3285478 | F580: =VALUE(LEFT(A580,2)) -> 9 | G580: =COUNTIF(Data_Eksportir!$H$2:$H$3401,A580) -> 0 | H580: =IF(E580="","Tanpa data berat",IF(E580<1,"Di bawah 1",IF(E580<5,"1 – 5",IF(E580<20,"5 – 20",IF(E580<100,"20 – 100","100 ke atas"))))) -> 5 – 20 | I580: =IF(D580<p_nilai_besar,"Di bawah ambang nilai",IF(G580=0,"Belum terwakili",IF(G580<=p_listing_rendah,"Keterwakilan rendah","Terwakili"))) -> Di bawah ambang nilai | J580: =D580+ROW()/10^6 -> 15083.001 | K580: =IF(D580>=p_nilai_besar,D580/(1+G580),0) -> 0 | L580: =IF(K580>0,K580+ROW()/10^6,0) -> 0
A581: 09096130 | B581: Seeds of caraway, neither crushed nor ground | D581: 120 | E581: =IF(AND(ISNUMBER(C581),C581>0),D581/C581,"") | F581: =VALUE(LEFT(A581,2)) -> 9 | G581: =COUNTIF(Data_Eksportir!$H$2:$H$3401,A581) -> 1 | H581: =IF(E581="","Tanpa data berat",IF(E581<1,"Di bawah 1",IF(E581<5,"1 – 5",IF(E581<20,"5 – 20",IF(E581<100,"20 – 100","100 ke atas"))))) -> Tanpa data berat | I581: =IF(D581<p_nilai_besar,"Di bawah ambang nilai",IF(G581=0,"Belum terwakili",IF(G581<=p_listing_rendah,"Keterwakilan rendah","Terwakili"))) -> Di bawah ambang nilai | J581: =D581+ROW()/10^6 -> 120.00058 | K581: =IF(D581>=p_nilai_besar,D581/(1+G581),0) -> 0 | L581: =IF(K581>0,K581+ROW()/10^6,0) -> 0
A582: 09096190 | B582: Juniper berries, neither crushed nor ground | C582: 1037 | D582: 2838 | E582: =IF(AND(ISNUMBER(C582),C582>0),D582/C582,"") -> 2.7367406 | F582: =VALUE(LEFT(A582,2)) -> 9 | G582: =COUNTIF(Data_Eksportir!$H$2:$H$3401,A582) -> 0 | H582: =IF(E582="","Tanpa data berat",IF(E582<1,"Di bawah 1",IF(E582<5,"1 – 5",IF(E582<20,"5 – 20",IF(E582<100,"20 – 100","100 ke atas"))))) -> 1 – 5 | I582: =IF(D582<p_nilai_besar,"Di bawah ambang nilai",IF(G582=0,"Belum terwakili",IF(G582<=p_listing_rendah,"Keterwakilan rendah","Terwakili"))) -> Di bawah ambang nilai | J582: =D582+ROW()/10^6 -> 2838.0006 | K582: =IF(D582>=p_nilai_besar,D582/(1+G582),0) -> 0 | L582: =IF(K582>0,K582+ROW()/10^6,0) -> 0
A583: 09096210 | B583: Seeds of anise, crushed or ground | C583: 250 | D583: 2877 | E583: =IF(AND(ISNUMBER(C583),C583>0),D583/C583,"") -> 11.508 | F583: =VALUE(LEFT(A583,2)) -> 9 | G583: =COUNTIF(Data_Eksportir!$H$2:$H$3401,A583) -> 0 | H583: =IF(E583="","Tanpa data berat",IF(E583<1,"Di bawah 1",IF(E583<5,"1 – 5",IF(E583<20,"5 – 20",IF(E583<100,"20 – 100","100 ke atas"))))) -> 5 – 20 | I583: =IF(D583<p_nilai_besar,"Di bawah ambang nilai",IF(G583=0,"Belum terwakili",IF(G583<=p_listing_rendah,"Keterwakilan rendah","Terwakili"))) -> Di bawah ambang nilai | J583: =D583+ROW()/10^6 -> 2877.0006 | K583: =IF(D583>=p_nilai_besar,D583/(1+G583),0) -> 0 | L583: =IF(K583>0,K583+ROW()/10^6,0) -> 0
A584: 09096230 | B584: Seeds of caraway, crushed or ground | C584: 108 | D584: 245 | E584: =IF(AND(ISNUMBER(C584),C584>0),D584/C584,"") -> 2.2685185 | F584: =VALUE(LEFT(A584,2)) -> 9 | G584: =COUNTIF(Data_Eksportir!$H$2:$H$3401,A584) -> 0 | H584: =IF(E584="","Tanpa data berat",IF(E584<1,"Di bawah 1",IF(E584<5,"1 – 5",IF(E584<20,"5 – 20",IF(E584<100,"20 – 100","100 ke atas"))))) -> 1 – 5 | I584: =IF(D584<p_nilai_besar,"Di bawah ambang nilai",IF(G584=0,"Belum terwakili",IF(G584<=p_listing_rendah,"Keterwakilan rendah","Terwakili"))) -> Di bawah ambang nilai | J584: =D584+ROW()/10^6 -> 245.00058 | K584: =IF(D584>=p_nilai_besar,D584/(1+G584),0) -> 0 | L584: =IF(K584>0,K584+ROW()/10^6,0) -> 0
A585: 09101100 | B585: Ginger, neither crushed nor ground | C585: 2455209 | D585: 1883070 | E585: =IF(AND(ISNUMBER(C585),C585>0),D585/C585,"") -> 0.76696933 | F585: =VALUE(LEFT(A585,2)) -> 9 | G585: =COUNTIF(Data_Eksportir!$H$2:$H$3401,A585) -> 61 | H585: =IF(E585="","Tanpa data berat",IF(E585<1,"Di bawah 1",IF(E585<5,"1 – 5",IF(E585<20,"5 – 20",IF(E585<100,"20 – 100","100 ke atas"))))) -> Di bawah 1 | I585: =IF(D585<p_nilai_besar,"Di bawah ambang nilai",IF(G585=0,"Belum terwakili",IF(G585<=p_listing_rendah,"Keterwakilan rendah","Terwakili"))) -> Di bawah ambang nilai | J585: =D585+ROW()/10^6 -> 1883070 | K585: =IF(D585>=p_nilai_besar,D585/(1+G585),0) -> 0 | L585: =IF(K585>0,K585+ROW()/10^6,0) -> 0
A586: 09101200 | B586: Ginger, crushed or ground | C586: 311971 | D586: 1747262 | E586: =IF(AND(ISNUMBER(C586),C586>0),D586/C586,"") -> 5.6007193 | F586: =VALUE(LEFT(A586,2)) -> 9 | G586: =COUNTIF(Data_Eksportir!$H$2:$H$3401,A586) -> 0 | H586: =IF(E586="","Tanpa data berat",IF(E586<1,"Di bawah 1",IF(E586<5,"1 – 5",IF(E586<20,"5 – 20",IF(E586<100,"20 – 100","100 ke atas"))))) -> 5 – 20 | I586: =IF(D586<p_nilai_besar,"Di bawah ambang nilai",IF(G586=0,"Belum terwakili",IF(G586<=p_listing_rendah,"Keterwakilan rendah","Terwakili"))) -> Di bawah ambang nilai | J586: =D586+ROW()/10^6 -> 1747262 | K586: =IF(D586>=p_nilai_besar,D586/(1+G586),0) -> 0 | L586: =IF(K586>0,K586+ROW()/10^6,0) -> 0
A587: 09102000 | B587: Saffron | C587: 3116 | D587: 23116 | E587: =IF(AND(ISNUMBER(C587),C587>0),D587/C587,"") -> 7.4184852 | F587: =VALUE(LEFT(A587,2)) -> 9 | G587: =COUNTIF(Data_Eksportir!$H$2:$H$3401,A587) -> 0 | H587: =IF(E587="","Tanpa data berat",IF(E587<1,"Di bawah 1",IF(E587<5,"1 – 5",IF(E587<20,"5 – 20",IF(E587<100,"20 – 100","100 ke atas"))))) -> 5 – 20 | I587: =IF(D587<p_nilai_besar,"Di bawah ambang nilai",IF(G587=0,"Belum terwakili",IF(G587<=p_listing_rendah,"Keterwakilan rendah","Terwakili"))) -> Di bawah ambang nilai | J587: =D587+ROW()/10^6 -> 23116.001 | K587: =IF(D587>=p_nilai_besar,D587/(1+G587),0) -> 0 | L587: =IF(K587>0,K587+ROW()/10^6,0) -> 0
A588: 09103000 | B588: Turmeric (curcuma) | C588: 5328563 | D588: 7174947 | E588: =IF(AND(ISNUMBER(C588),C588>0),D588/C588,"") -> 1.3465069 | F588: =VALUE(LEFT(A588,2)) -> 9 | G588: =COUNTIF(Data_Eksportir!$H$2:$H$3401,A588) -> 40 | H588: =IF(E588="","Tanpa data berat",IF(E588<1,"Di bawah 1",IF(E588<5,"1 – 5",IF(E588<20,"5 – 20",IF(E588<100,"20 – 100","100 ke atas"))))) -> 1 – 5 | I588: =IF(D588<p_nilai_besar,"Di bawah ambang nilai",IF(G588=0,"Belum terwakili",IF(G588<=p_listing_rendah,"Keterwakilan rendah","Terwakili"))) -> Di bawah ambang nilai | J588: =D588+ROW()/10^6 -> 7174947 | K588: =IF(D588>=p_nilai_besar,D588/(1+G588),0) -> 0 | L588: =IF(K588>0,K588+ROW()/10^6,0) -> 0
A589: 09109110 | B589: Curry, mixtures referred to in note 1(b) to this chapter | C589: 1416 | D589: 12889 | E589: =IF(AND(ISNUMBER(C589),C589>0),D589/C589,"") -> 9.1024011 | F589: =VALUE(LEFT(A589,2)) -> 9 | G589: =COUNTIF(Data_Eksportir!$H$2:$H$3401,A589) -> 0 | H589: =IF(E589="","Tanpa data berat",IF(E589<1,"Di bawah 1",IF(E589<5,"1 – 5",IF(E589<20,"5 – 20",IF(E589<100,"20 – 100","100 ke atas"))))) -> 5 – 20 | I589: =IF(D589<p_nilai_besar,"Di bawah ambang nilai",IF(G589=0,"Belum terwakili",IF(G589<=p_listing_rendah,"Keterwakilan rendah","Terwakili"))) -> Di bawah ambang nilai | J589: =D589+ROW()/10^6 -> 12889.001 | K589: =IF(D589>=p_nilai_besar,D589/(1+G589),0) -> 0 | L589: =IF(K589>0,K589+ROW()/10^6,0) -> 0
A590: 09109190 | B590: Spices other than curry, mixtures referred to in note 1(b) to this chapter | C590: 627181 | D590: 861342 | E590: =IF(AND(ISNUMBER(C590),C590>0),D590/C590,"") -> 1.3733547 | F590: =VALUE(LEFT(A590,2)) -> 9 | G590: =COUNTIF(Data_Eksportir!$H$2:$H$3401,A590) -> 5 | H590: =IF(E590="","Tanpa data berat",IF(E590<1,"Di bawah 1",IF(E590<5,"1 – 5",IF(E590<20,"5 – 20",IF(E590<100,"20 – 100","100 ke atas"))))) -> 1 – 5 | I590: =IF(D590<p_nilai_besar,"Di bawah ambang nilai",IF(G590=0,"Belum terwakili",IF(G590<=p_listing_rendah,"Keterwakilan rendah","Terwakili"))) -> Di bawah ambang nilai | J590: =D590+ROW()/10^6 -> 861342 | K590: =IF(D590>=p_nilai_besar,D590/(1+G590),0) -> 0 | L590: =IF(K590>0,K590+ROW()/10^6,0) -> 0
A591: 09109910 | B591: Thyme, bay leaves | C591: 29749 | D591: 186284 | E591: =IF(AND(ISNUMBER(C591),C591>0),D591/C591,"") -> 6.2618575 | F591: =VALUE(LEFT(A591,2)) -> 9 | G591: =COUNTIF(Data_Eksportir!$H$2:$H$3401,A591) -> 5 | H591: =IF(E591="","Tanpa data berat",IF(E591<1,"Di bawah 1",IF(E591<5,"1 – 5",IF(E591<20,"5 – 20",IF(E591<100,"20 – 100","100 ke atas"))))) -> 5 – 20 | I591: =IF(D591<p_nilai_besar,"Di bawah ambang nilai",IF(G591=0,"Belum terwakili",IF(G591<=p_listing_rendah,"Keterwakilan rendah","Terwakili"))) -> Di bawah ambang nilai | J591: =D591+ROW()/10^6 -> 186284 | K591: =IF(D591>=p_nilai_besar,D591/(1+G591),0) -> 0 | L591: =IF(K591>0,K591+ROW()/10^6,0) -> 0
A592: 09109990 | B592: Spices,other than HS 09101100-09109910, mixtures referred to in note 1(b) to this chapter | C592: 2771723 | D592: 3695668 | E592: =IF(AND(ISNUMBER(C592),C592>0),D592/C592,"") -> 1.3333468 | F592: =VALUE(LEFT(A592,2)) -> 9 | G592: =COUNTIF(Data_Eksportir!$H$2:$H$3401,A592) -> 0 | H592: =IF(E592="","Tanpa data berat",IF(E592<1,"Di bawah 1",IF(E592<5,"1 – 5",IF(E592<20,"5 – 20",IF(E592<100,"20 – 100","100 ke atas"))))) -> 1 – 5 | I592: =IF(D592<p_nilai_besar,"Di bawah ambang nilai",IF(G592=0,"Belum terwakili",IF(G592<=p_listing_rendah,"Keterwakilan rendah","Terwakili"))) -> Di bawah ambang nilai | J592: =D592+ROW()/10^6 -> 3695668 | K592: =IF(D592>=p_nilai_besar,D592/(1+G592),0) -> 0 | L592: =IF(K592>0,K592+ROW()/10^6,0) -> 0
A593: 10011100 | B593: Durum wheat, seed | C593: 50 | D593: 10000 | E593: =IF(AND(ISNUMBER(C593),C593>0),D593/C593,"") -> 200 | F593: =VALUE(LEFT(A593,2)) -> 10 | G593: =COUNTIF(Data_Eksportir!$H$2:$H$3401,A593) -> 0 | H593: =IF(E593="","Tanpa data berat",IF(E593<1,"Di bawah 1",IF(E593<5,"1 – 5",IF(E593<20,"5 – 20",IF(E593<100,"20 – 100","100 ke atas"))))) -> 100 ke atas | I593: =IF(D593<p_nilai_besar,"Di bawah ambang nilai",IF(G593=0,"Belum terwakili",IF(G593<=p_listing_rendah,"Keterwakilan rendah","Terwakili"))) -> Di bawah ambang nilai | J593: =D593+ROW()/10^6 -> 10000.001 | K593: =IF(D593>=p_nilai_besar,D593/(1+G593),0) -> 0 | L593: =IF(K593>0,K593+ROW()/10^6,0) -> 0
... A711: 13023100 | B711: Agar-agar | C711: 1435224 | D711: 17369843 | E711: =IF(AND(ISNUMBER(C711),C711>0),D711/C711,"") -> 12.102531 | F711: =VALUE(LEFT(A711,2)) -> 13 | G711: =COUNTIF(Data_Eksportir!$H$2:$H$3401,A711) -> 1 | H711: =IF(E711="","Tanpa data berat",IF(E711<1,"Di bawah 1",IF(E711<5,"1 – 5",IF(E711<20,"5 – 20",IF(E711<100,"20 – 100","100 ke atas"))))) -> 5 – 20 | I711: =IF(D711<p_nilai_besar,"Di bawah ambang nilai",IF(G711=0,"Belum terwakili",IF(G711<=p_listing_rendah,"Keterwakilan rendah","Terwakili"))) -> Keterwakilan rendah | J711: =D711+ROW()/10^6 -> 17369843 | K711: =IF(D711>=p_nilai_besar,D711/(1+G711),0) -> 8684921.5 | L711: =IF(K711>0,K711+ROW()/10^6,0) -> 8684921.5
A712: 13023200 | B712: Mucilages and thickeners, whether or not modified, derived from locust beans, locust bean seeds or guar seeds | D712: 124 | E712: =IF(AND(ISNUMBER(C712),C712>0),D712/C712,"") | F712: =VALUE(LEFT(A712,2)) -> 13 | G712: =COUNTIF(Data_Eksportir!$H$2:$H$3401,A712) -> 1 | H712: =IF(E712="","Tanpa data berat",IF(E712<1,"Di bawah 1",IF(E712<5,"1 – 5",IF(E712<20,"5 – 20",IF(E712<100,"20 – 100","100 ke atas"))))) -> Tanpa data berat | I712: =IF(D712<p_nilai_besar,"Di bawah ambang nilai",IF(G712=0,"Belum terwakili",IF(G712<=p_listing_rendah,"Keterwakilan rendah","Terwakili"))) -> Di bawah ambang nilai | J712: =D712+ROW()/10^6 -> 124.00071 | K712: =IF(D712>=p_nilai_besar,D712/(1+G712),0) -> 0 | L712: =IF(K712>0,K712+ROW()/10^6,0) -> 0
A713: 13023911 | B713: Carrageenan, powder, semi-refined | C713: 15565282 | D713: 95921214 | E713: =IF(AND(ISNUMBER(C713),C713>0),D713/C713,"") -> 6.1625105 | F713: =VALUE(LEFT(A713,2)) -> 13 | G713: =COUNTIF(Data_Eksportir!$H$2:$H$3401,A713) -> 0 | H713: =IF(E713="","Tanpa data berat",IF(E713<1,"Di bawah 1",IF(E713<5,"1 – 5",IF(E713<20,"5 – 20",IF(E713<100,"20 – 100","100 ke atas"))))) -> 5 – 20 | I713: =IF(D713<p_nilai_besar,"Di bawah ambang nilai",IF(G713=0,"Belum terwakili",IF(G713<=p_listing_rendah,"Keterwakilan rendah","Terwakili"))) -> Belum terwakili | J713: =D713+ROW()/10^6 -> 95921214 | K713: =IF(D713>=p_nilai_besar,D713/(1+G713),0) -> 95921214 | L713: =IF(K713>0,K713+ROW()/10^6,0) -> 95921214
A714: 13023912 | B714: Carrageenan, powder, refined | C714: 275913 | D714: 4550559 | E714: =IF(AND(ISNUMBER(C714),C714>0),D714/C714,"") -> 16.492731 | F714: =VALUE(LEFT(A714,2)) -> 13 | G714: =COUNTIF(Data_Eksportir!$H$2:$H$3401,A714) -> 0 | H714: =IF(E714="","Tanpa data berat",IF(E714<1,"Di bawah 1",IF(E714<5,"1 – 5",IF(E714<20,"5 – 20",IF(E714<100,"20 – 100","100 ke atas"))))) -> 5 – 20 | I714: =IF(D714<p_nilai_besar,"Di bawah ambang nilai",IF(G714=0,"Belum terwakili",IF(G714<=p_listing_rendah,"Keterwakilan rendah","Terwakili"))) -> Di bawah ambang nilai | J714: =D714+ROW()/10^6 -> 4550559 | K714: =IF(D714>=p_nilai_besar,D714/(1+G714),0) -> 0 | L714: =IF(K714>0,K714+ROW()/10^6,0) -> 0
A715: 13023913 | B715: Carrageenan, alkali treated carrageenan chips (atcc) | C715: 319280 | D715: 1982925 | E715: =IF(AND(ISNUMBER(C715),C715>0),D715/C715,"") -> 6.2106145 | F715: =VALUE(LEFT(A715,2)) -> 13 | G715: =COUNTIF(Data_Eksportir!$H$2:$H$3401,A715) -> 0 | H715: =IF(E715="","Tanpa data berat",IF(E715<1,"Di bawah 1",IF(E715<5,"1 – 5",IF(E715<20,"5 – 20",IF(E715<100,"20 – 100","100 ke atas"))))) -> 5 – 20 | I715: =IF(D715<p_nilai_besar,"Di bawah ambang nilai",IF(G715=0,"Belum terwakili",IF(G715<=p_listing_rendah,"Keterwakilan rendah","Terwakili"))) -> Di bawah ambang nilai | J715: =D715+ROW()/10^6 -> 1982925 | K715: =IF(D715>=p_nilai_besar,D715/(1+G715),0) -> 0 | L715: =IF(K715>0,K715+ROW()/10^6,0) -> 0
A716: 13023919 | B716: Carrageenan, other than powder and alkali treated carrageenan chips (atcc) | C716: 116656 | D716: 694987 | E716: =IF(AND(ISNUMBER(C716),C716>0),D716/C716,"") -> 5.9575761 | F716: =VALUE(LEFT(A716,2)) -> 13 | G716: =COUNTIF(Data_Eksportir!$H$2:$H$3401,A716) -> 0 | H716: =IF(E716="","Tanpa data berat",IF(E716<1,"Di bawah 1",IF(E716<5,"1 – 5",IF(E716<20,"5 – 20",IF(E716<100,"20 – 100","100 ke atas"))))) -> 5 – 20 | I716: =IF(D716<p_nilai_besar,"Di bawah ambang nilai",IF(G716=0,"Belum terwakili",IF(G716<=p_listing_rendah,"Keterwakilan rendah","Terwakili"))) -> Di bawah ambang nilai | J716: =D716+ROW()/10^6 -> 694987 | K716: =IF(D716>=p_nilai_besar,D716/(1+G716),0) -> 0 | L716: =IF(K716>0,K716+ROW()/10^6,0) -> 0
A717: 13023990 | B717: Mucilages and thickeners, whether or not modified, derived from vegetable products, other than HS code 13023100 to 13023919 | C717: 104053 | D717: 1797893 | E717: =IF(AND(ISNUMBER(C717),C717>0),D717/C717,"") -> 17.278627 | F717: =VALUE(LEFT(A717,2)) -> 13 | G717: =COUNTIF(Data_Eksportir!$H$2:$H$3401,A717) -> 0 | H717: =IF(E717="","Tanpa data berat",IF(E717<1,"Di bawah 1",IF(E717<5,"1 – 5",IF(E717<20,"5 – 20",IF(E717<100,"20 – 100","100 ke atas"))))) -> 5 – 20 | I717: =IF(D717<p_nilai_besar,"Di bawah ambang nilai",IF(G717=0,"Belum terwakili",IF(G717<=p_listing_rendah,"Keterwakilan rendah","Terwakili"))) -> Di bawah ambang nilai | J717: =D717+ROW()/10^6 -> 1797893 | K717: =IF(D717>=p_nilai_besar,D717/(1+G717),0) -> 0 | L717: =IF(K717>0,K717+ROW()/10^6,0) -> 0
A718: 14011000 | B718: Bamboos, a kind used primarily for plaiting | C718: 1096996 | D718: 651953 | E718: =IF(AND(ISNUMBER(C718),C718>0),D718/C718,"") -> 0.59430755 | F718: =VALUE(LEFT(A718,2)) -> 14 | G718: =COUNTIF(Data_Eksportir!$H$2:$H$3401,A718) -> 0 | H718: =IF(E718="","Tanpa data berat",IF(E718<1,"Di bawah 1",IF(E718<5,"1 – 5",IF(E718<20,"5 – 20",IF(E718<100,"20 – 100","100 ke atas"))))) -> Di bawah 1 | I718: =IF(D718<p_nilai_besar,"Di bawah ambang nilai",IF(G718=0,"Belum terwakili",IF(G718<=p_listing_rendah,"Keterwakilan rendah","Terwakili"))) -> Di bawah ambang nilai | J718: =D718+ROW()/10^6 -> 651953 | K718: =IF(D718>=p_nilai_besar,D718/(1+G718),0) -> 0 | L718: =IF(K718>0,K718+ROW()/10^6,0) -> 0
A719: 14019000 | B719: Vegetable materials of a kind used primarily for plaiting (for example, reeds, rushes, osier, raffia, cleaned, bleached or dyed cereal straw, and lime bark), other than bamboos and rattans | C719: 432470 | D719: 453791 | E719: =IF(AND(ISNUMBER(C719),C719>0),D719/C719,"") -> 1.0493005 | F719: =VALUE(LEFT(A719,2)) -> 14 | G719: =COUNTIF(Data_Eksportir!$H$2:$H$3401,A719) -> 1 | H719: =IF(E719="","Tanpa data berat",IF(E719<1,"Di bawah 1",IF(E719<5,"1 – 5",IF(E719<20,"5 – 20",IF(E719<100,"20 – 100","100 ke atas"))))) -> 1 – 5 | I719: =IF(D719<p_nilai_besar,"Di bawah ambang nilai",IF(G719=0,"Belum terwakili",IF(G719<=p_listing_rendah,"Keterwakilan rendah","Terwakili"))) -> Di bawah ambang nilai | J719: =D719+ROW()/10^6 -> 453791 | K719: =IF(D719>=p_nilai_besar,D719/(1+G719),0) -> 0 | L719: =IF(K719>0,K719+ROW()/10^6,0) -> 0
A720: 14042000 | B720: Cotton linters | C720: 3047 | D720: 12093 | E720: =IF(AND(ISNUMBER(C720),C720>0),D720/C720,"") -> 3.9688218 | F720: =VALUE(LEFT(A720,2)) -> 14 | G720: =COUNTIF(Data_Eksportir!$H$2:$H$3401,A720) -> 0 | H720: =IF(E720="","Tanpa data berat",IF(E720<1,"Di bawah 1",IF(E720<5,"1 – 5",IF(E720<20,"5 – 20",IF(E720<100,"20 – 100","100 ke atas"))))) -> 1 – 5 | I720: =IF(D720<p_nilai_besar,"Di bawah ambang nilai",IF(G720=0,"Belum terwakili",IF(G720<=p_listing_rendah,"Keterwakilan rendah","Terwakili"))) -> Di bawah ambang nilai | J720: =D720+ROW()/10^6 -> 12093.001 | K720: =IF(D720>=p_nilai_besar,D720/(1+G720),0) -> 0 | L720: =IF(K720>0,K720+ROW()/10^6,0) -> 0
A721: 14049020 | B721: Vegetable products not elsewhere specified or included, of a kind used primarily in tanning or dyeing | C721: 6165549 | D721: 1900708 | E721: =IF(AND(ISNUMBER(C721),C721>0),D721/C721,"") -> 0.30827879 | F721: =VALUE(LEFT(A721,2)) -> 14 | G721: =COUNTIF(Data_Eksportir!$H$2:$H$3401,A721) -> 0 | H721: =IF(E721="","Tanpa data berat",IF(E721<1,"Di bawah 1",IF(E721<5,"1 – 5",IF(E721<20,"5 – 20",IF(E721<100,"20 – 100","100 ke atas"))))) -> Di bawah 1 | I721: =IF(D721<p_nilai_besar,"Di bawah ambang nilai",IF(G721=0,"Belum terwakili",IF(G721<=p_listing_rendah,"Keterwakilan rendah","Terwakili"))) -> Di bawah ambang nilai | J721: =D721+ROW()/10^6 -> 1900708 | K721: =IF(D721>=p_nilai_besar,D721/(1+G721),0) -> 0 | L721: =IF(K721>0,K721+ROW()/10^6,0) -> 0
A722: 14049030 | B722: Kapok | C722: 8380924 | D722: 5445419 | E722: =IF(AND(ISNUMBER(C722),C722>0),D722/C722,"") -> 0.64973969 | F722: =VALUE(LEFT(A722,2)) -> 14 | G722: =COUNTIF(Data_Eksportir!$H$2:$H$3401,A722) -> 1 | H722: =IF(E722="","Tanpa data berat",IF(E722<1,"Di bawah 1",IF(E722<5,"1 – 5",IF(E722<20,"5 – 20",IF(E722<100,"20 – 100","100 ke atas"))))) -> Di bawah 1 | I722: =IF(D722<p_nilai_besar,"Di bawah ambang nilai",IF(G722=0,"Belum terwakili",IF(G722<=p_listing_rendah,"Keterwakilan rendah","Terwakili"))) -> Di bawah ambang nilai | J722: =D722+ROW()/10^6 -> 5445419 | K722: =IF(D722>=p_nilai_besar,D722/(1+G722),0) -> 0 | L722: =IF(K722>0,K722+ROW()/10^6,0) -> 0
A723: 14049091 | B723: Palm kernel shells | C723: 5441216928 | D723: 561491959 | E723: =IF(AND(ISNUMBER(C723),C723>0),D723/C723,"") -> 0.10319235 | F723: =VALUE(LEFT(A723,2)) -> 14 | G723: =COUNTIF(Data_Eksportir!$H$2:$H$3401,A723) -> 52 | H723: =IF(E723="","Tanpa data berat",IF(E723<1,"Di bawah 1",IF(E723<5,"1 – 5",IF(E723<20,"5 – 20",IF(E723<100,"20 – 100","100 ke atas"))))) -> Di bawah 1 | I723: =IF(D723<p_nilai_besar,"Di bawah ambang nilai",IF(G723=0,"Belum terwakili",IF(G723<=p_listing_rendah,"Keterwakilan rendah","Terwakili"))) -> Terwakili | J723: =D723+ROW()/10^6 -> 5.6149196e+08 | K723: =IF(D723>=p_nilai_besar,D723/(1+G723),0) -> 10594188 | L723: =IF(K723>0,K723+ROW()/10^6,0) -> 10594188
A724: 14049092 | B724: Empty fruit bunch of oil palm | C724: 515 | D724: 134 | E724: =IF(AND(ISNUMBER(C724),C724>0),D724/C724,"") -> 0.26019417 | F724: =VALUE(LEFT(A724,2)) -> 14 | G724: =COUNTIF(Data_Eksportir!$H$2:$H$3401,A724) -> 0 | H724: =IF(E724="","Tanpa data berat",IF(E724<1,"Di bawah 1",IF(E724<5,"1 – 5",IF(E724<20,"5 – 20",IF(E724<100,"20 – 100","100 ke atas"))))) -> Di bawah 1 | I724: =IF(D724<p_nilai_besar,"Di bawah ambang nilai",IF(G724=0,"Belum terwakili",IF(G724<=p_listing_rendah,"Keterwakilan rendah","Terwakili"))) -> Di bawah ambang nilai | J724: =D724+ROW()/10^6 -> 134.00072 | K724: =IF(D724>=p_nilai_besar,D724/(1+G724),0) -> 0 | L724: =IF(K724>0,K724+ROW()/10^6,0) -> 0
... A768: 15149990 | B768: Rape, colza or mustard oil, other than low erucic acid, other than HS code 15149100 to 15149910 | C768: 20 | D768: 48 | E768: =IF(AND(ISNUMBER(C768),C768>0),D768/C768,"") -> 2.4 | F768: =VALUE(LEFT(A768,2)) -> 15 | G768: =COUNTIF(Data_Eksportir!$H$2:$H$3401,A768) -> 0 | H768: =IF(E768="","Tanpa data berat",IF(E768<1,"Di bawah 1",IF(E768<5,"1 – 5",IF(E768<20,"5 – 20",IF(E768<100,"20 – 100","100 ke atas"))))) -> 1 – 5 | I768: =IF(D768<p_nilai_besar,"Di bawah ambang nilai",IF(G768=0,"Belum terwakili",IF(G768<=p_listing_rendah,"Keterwakilan rendah","Terwakili"))) -> Di bawah ambang nilai | J768: =D768+ROW()/10^6 -> 48.000768 | K768: =IF(D768>=p_nilai_besar,D768/(1+G768),0) -> 0 | L768: =IF(K768>0,K768+ROW()/10^6,0) -> 0
A769: 15151900 | B769: Linseed oil and its fractions, other than crude oil | D769: 126 | E769: =IF(AND(ISNUMBER(C769),C769>0),D769/C769,"") | F769: =VALUE(LEFT(A769,2)) -> 15 | G769: =COUNTIF(Data_Eksportir!$H$2:$H$3401,A769) -> 0 | H769: =IF(E769="","Tanpa data berat",IF(E769<1,"Di bawah 1",IF(E769<5,"1 – 5",IF(E769<20,"5 – 20",IF(E769<100,"20 – 100","100 ke atas"))))) -> Tanpa data berat | I769: =IF(D769<p_nilai_besar,"Di bawah ambang nilai",IF(G769=0,"Belum terwakili",IF(G769<=p_listing_rendah,"Keterwakilan rendah","Terwakili"))) -> Di bawah ambang nilai | J769: =D769+ROW()/10^6 -> 126.00077 | K769: =IF(D769>=p_nilai_besar,D769/(1+G769),0) -> 0 | L769: =IF(K769>0,K769+ROW()/10^6,0) -> 0
A770: 15152100 | B770: Maize (corn) oil, crude oil | C770: 368 | D770: 2548 | E770: =IF(AND(ISNUMBER(C770),C770>0),D770/C770,"") -> 6.923913 | F770: =VALUE(LEFT(A770,2)) -> 15 | G770: =COUNTIF(Data_Eksportir!$H$2:$H$3401,A770) -> 0 | H770: =IF(E770="","Tanpa data berat",IF(E770<1,"Di bawah 1",IF(E770<5,"1 – 5",IF(E770<20,"5 – 20",IF(E770<100,"20 – 100","100 ke atas"))))) -> 5 – 20 | I770: =IF(D770<p_nilai_besar,"Di bawah ambang nilai",IF(G770=0,"Belum terwakili",IF(G770<=p_listing_rendah,"Keterwakilan rendah","Terwakili"))) -> Di bawah ambang nilai | J770: =D770+ROW()/10^6 -> 2548.0008 | K770: =IF(D770>=p_nilai_besar,D770/(1+G770),0) -> 0 | L770: =IF(K770>0,K770+ROW()/10^6,0) -> 0
A771: 15152919 | B771: Maize (corn) oil, fractions of unrefined oil, other than solid fractions | C771: 32 | D771: 169 | E771: =IF(AND(ISNUMBER(C771),C771>0),D771/C771,"") -> 5.28125 | F771: =VALUE(LEFT(A771,2)) -> 15 | G771: =COUNTIF(Data_Eksportir!$H$2:$H$3401,A771) -> 0 | H771: =IF(E771="","Tanpa data berat",IF(E771<1,"Di bawah 1",IF(E771<5,"1 – 5",IF(E771<20,"5 – 20",IF(E771<100,"20 – 100","100 ke atas"))))) -> 5 – 20 | I771: =IF(D771<p_nilai_besar,"Di bawah ambang nilai",IF(G771=0,"Belum terwakili",IF(G771<=p_listing_rendah,"Keterwakilan rendah","Terwakili"))) -> Di bawah ambang nilai | J771: =D771+ROW()/10^6 -> 169.00077 | K771: =IF(D771>=p_nilai_besar,D771/(1+G771),0) -> 0 | L771: =IF(K771>0,K771+ROW()/10^6,0) -> 0
A772: 15152999 | B772: Maize (corn) oil, fractions of refined oil, other than solid fractions | C772: 22 | D772: 77 | E772: =IF(AND(ISNUMBER(C772),C772>0),D772/C772,"") -> 3.5 | F772: =VALUE(LEFT(A772,2)) -> 15 | G772: =COUNTIF(Data_Eksportir!$H$2:$H$3401,A772) -> 1 | H772: =IF(E772="","Tanpa data berat",IF(E772<1,"Di bawah 1",IF(E772<5,"1 – 5",IF(E772<20,"5 – 20",IF(E772<100,"20 – 100","100 ke atas"))))) -> 1 – 5 | I772: =IF(D772<p_nilai_besar,"Di bawah ambang nilai",IF(G772=0,"Belum terwakili",IF(G772<=p_listing_rendah,"Keterwakilan rendah","Terwakili"))) -> Di bawah ambang nilai | J772: =D772+ROW()/10^6 -> 77.000772 | K772: =IF(D772>=p_nilai_besar,D772/(1+G772),0) -> 0 | L772: =IF(K772>0,K772+ROW()/10^6,0) -> 0
A773: 15153090 | B773: Castor oil, other than crude oil | C773: 8225 | D773: 27704 | E773: =IF(AND(ISNUMBER(C773),C773>0),D773/C773,"") -> 3.3682675 | F773: =VALUE(LEFT(A773,2)) -> 15 | G773: =COUNTIF(Data_Eksportir!$H$2:$H$3401,A773) -> 0 | H773: =IF(E773="","Tanpa data berat",IF(E773<1,"Di bawah 1",IF(E773<5,"1 – 5",IF(E773<20,"5 – 20",IF(E773<100,"20 – 100","100 ke atas"))))) -> 1 – 5 | I773: =IF(D773<p_nilai_besar,"Di bawah ambang nilai",IF(G773=0,"Belum terwakili",IF(G773<=p_listing_rendah,"Keterwakilan rendah","Terwakili"))) -> Di bawah ambang nilai | J773: =D773+ROW()/10^6 -> 27704.001 | K773: =IF(D773>=p_nilai_besar,D773/(1+G773),0) -> 0 | L773: =IF(K773>0,K773+ROW()/10^6,0) -> 0
A774: 15155010 | B774: Sesame oil, crude oil | C774: 726 | D774: 8612 | E774: =IF(AND(ISNUMBER(C774),C774>0),D774/C774,"") -> 11.862259 | F774: =VALUE(LEFT(A774,2)) -> 15 | G774: =COUNTIF(Data_Eksportir!$H$2:$H$3401,A774) -> 1 | H774: =IF(E774="","Tanpa data berat",IF(E774<1,"Di bawah 1",IF(E774<5,"1 – 5",IF(E774<20,"5 – 20",IF(E774<100,"20 – 100","100 ke atas"))))) -> 5 – 20 | I774: =IF(D774<p_nilai_besar,"Di bawah ambang nilai",IF(G774=0,"Belum terwakili",IF(G774<=p_listing_rendah,"Keterwakilan rendah","Terwakili"))) -> Di bawah ambang nilai | J774: =D774+ROW()/10^6 -> 8612.0008 | K774: =IF(D774>=p_nilai_besar,D774/(1+G774),0) -> 0 | L774: =IF(K774>0,K774+ROW()/10^6,0) -> 0
A775: 15155090 | B775: Sesame oil and its fractions, other than crude oil and unrefined oil | C775: 1735 | D775: 9400 | E775: =IF(AND(ISNUMBER(C775),C775>0),D775/C775,"") -> 5.4178674 | F775: =VALUE(LEFT(A775,2)) -> 15 | G775: =COUNTIF(Data_Eksportir!$H$2:$H$3401,A775) -> 0 | H775: =IF(E775="","Tanpa data berat",IF(E775<1,"Di bawah 1",IF(E775<5,"1 – 5",IF(E775<20,"5 – 20",IF(E775<100,"20 – 100","100 ke atas"))))) -> 5 – 20 | I775: =IF(D775<p_nilai_besar,"Di bawah ambang nilai",IF(G775=0,"Belum terwakili",IF(G775<=p_listing_rendah,"Keterwakilan rendah","Terwakili"))) -> Di bawah ambang nilai | J775: =D775+ROW()/10^6 -> 9400.0008 | K775: =IF(D775>=p_nilai_besar,D775/(1+G775),0) -> 0 | L775: =IF(K775>0,K775+ROW()/10^6,0) -> 0
A776: 15159019 | B776: Illipe nut oil, other than crude oil and unrefined oil | C776: 54100 | D776: 150789 | E776: =IF(AND(ISNUMBER(C776),C776>0),D776/C776,"") -> 2.7872274 | F776: =VALUE(LEFT(A776,2)) -> 15 | G776: =COUNTIF(Data_Eksportir!$H$2:$H$3401,A776) -> 0 | H776: =IF(E776="","Tanpa data berat",IF(E776<1,"Di bawah 1",IF(E776<5,"1 – 5",IF(E776<20,"5 – 20",IF(E776<100,"20 – 100","100 ke atas"))))) -> 1 – 5 | I776: =IF(D776<p_nilai_besar,"Di bawah ambang nilai",IF(G776=0,"Belum terwakili",IF(G776<=p_listing_rendah,"Keterwakilan rendah","Terwakili"))) -> Di bawah ambang nilai | J776: =D776+ROW()/10^6 -> 150789 | K776: =IF(D776>=p_nilai_besar,D776/(1+G776),0) -> 0 | L776: =IF(K776>0,K776+ROW()/10^6,0) -> 0
A777: 15159021 | B777: Tung oil, crude oil | C777: 800 | D777: 19200 | E777: =IF(AND(ISNUMBER(C777),C777>0),D777/C777,"") -> 24 | F777: =VALUE(LEFT(A777,2)) -> 15 | G777: =COUNTIF(Data_Eksportir!$H$2:$H$3401,A777) -> 0 | H777: =IF(E777="","Tanpa data berat",IF(E777<1,"Di bawah 1",IF(E777<5,"1 – 5",IF(E777<20,"5 – 20",IF(E777<100,"20 – 100","100 ke atas"))))) -> 20 – 100 | I777: =IF(D777<p_nilai_besar,"Di bawah ambang nilai",IF(G777=0,"Belum terwakili",IF(G777<=p_listing_rendah,"Keterwakilan rendah","Terwakili"))) -> Di bawah ambang nilai | J777: =D777+ROW()/10^6 -> 19200.001 | K777: =IF(D777>=p_nilai_besar,D777/(1+G777),0) -> 0 | L777: =IF(K777>0,K777+ROW()/10^6,0) -> 0
A778: 15159029 | B778: Tung oil, other than crude oil and unrefined oil | C778: 5260 | D778: 14 | E778: =IF(AND(ISNUMBER(C778),C778>0),D778/C778,"") -> 0.002661597 | F778: =VALUE(LEFT(A778,2)) -> 15 | G778: =COUNTIF(Data_Eksportir!$H$2:$H$3401,A778) -> 0 | H778: =IF(E778="","Tanpa data berat",IF(E778<1,"Di bawah 1",IF(E778<5,"1 – 5",IF(E778<20,"5 – 20",IF(E778<100,"20 – 100","100 ke atas"))))) -> Di bawah 1 | I778: =IF(D778<p_nilai_besar,"Di bawah ambang nilai",IF(G778=0,"Belum terwakili",IF(G778<=p_listing_rendah,"Keterwakilan rendah","Terwakili"))) -> Di bawah ambang nilai | J778: =D778+ROW()/10^6 -> 14.000778 | K778: =IF(D778>=p_nilai_besar,D778/(1+G778),0) -> 0 | L778: =IF(K778>0,K778+ROW()/10^6,0) -> 0
A779: 15159039 | B779: Jojoba oil, other than crude oil and unrefined oil | C779: 25 | D779: 38 | E779: =IF(AND(ISNUMBER(C779),C779>0),D779/C779,"") -> 1.52 | F779: =VALUE(LEFT(A779,2)) -> 15 | G779: =COUNTIF(Data_Eksportir!$H$2:$H$3401,A779) -> 0 | H779: =IF(E779="","Tanpa data berat",IF(E779<1,"Di bawah 1",IF(E779<5,"1 – 5",IF(E779<20,"5 – 20",IF(E779<100,"20 – 100","100 ke atas"))))) -> 1 – 5 | I779: =IF(D779<p_nilai_besar,"Di bawah ambang nilai",IF(G779=0,"Belum terwakili",IF(G779<=p_listing_rendah,"Keterwakilan rendah","Terwakili"))) -> Di bawah ambang nilai | J779: =D779+ROW()/10^6 -> 38.000779 | K779: =IF(D779>=p_nilai_besar,D779/(1+G779),0) -> 0 | L779: =IF(K779>0,K779+ROW()/10^6,0) -> 0
A780: 15159099 | B780: Other fixed vegetable oils, but not chemically modified, other than HS code 15151100 to 15159039, other than crude oil and unrefined oil | C780: 3227413 | D780: 64852094 | E780: =IF(AND(ISNUMBER(C780),C780>0),D780/C780,"") -> 20.094142 | F780: =VALUE(LEFT(A780,2)) -> 15 | G780: =COUNTIF(Data_Eksportir!$H$2:$H$3401,A780) -> 0 | H780: =IF(E780="","Tanpa data berat",IF(E780<1,"Di bawah 1",IF(E780<5,"1 – 5",IF(E780<20,"5 – 20",IF(E780<100,"20 – 100","100 ke atas"))))) -> 20 – 100 | I780: =IF(D780<p_nilai_besar,"Di bawah ambang nilai",IF(G780=0,"Belum terwakili",IF(G780<=p_listing_rendah,"Keterwakilan rendah","Terwakili"))) -> Belum terwakili | J780: =D780+ROW()/10^6 -> 64852094 | K780: =IF(D780>=p_nilai_besar,D780/(1+G780),0) -> 64852094 | L780: =IF(K780>0,K780+ROW()/10^6,0) -> 64852094
A781: 15161020 | B781: Animal fats and oils and their fractions, not further prepared, re-esterified | C781: 134410 | D781: 260314 | E781: =IF(AND(ISNUMBER(C781),C781>0),D781/C781,"") -> 1.936716 | F781: =VALUE(LEFT(A781,2)) -> 15 | G781: =COUNTIF(Data_Eksportir!$H$2:$H$3401,A781) -> 0 | H781: =IF(E781="","Tanpa data berat",IF(E781<1,"Di bawah 1",IF(E781<5,"1 – 5",IF(E781<20,"5 – 20",IF(E781<100,"20 – 100","100 ke atas"))))) -> 1 – 5 | I781: =IF(D781<p_nilai_besar,"Di bawah ambang nilai",IF(G781=0,"Belum terwakili",IF(G781<=p_listing_rendah,"Keterwakilan rendah","Terwakili"))) -> Di bawah ambang nilai | J781: =D781+ROW()/10^6 -> 260314 | K781: =IF(D781>=p_nilai_besar,D781/(1+G781),0) -> 0 | L781: =IF(K781>0,K781+ROW()/10^6,0) -> 0
... A819: 15179050 | B819: Solid mixtures or preparations of vegetable fats or oils or of their fractions other than imitation ghee, shortening, imitation lard | C819: 1560000 | D819: 2432286 | E819: =IF(AND(ISNUMBER(C819),C819>0),D819/C819,"") -> 1.5591577 | F819: =VALUE(LEFT(A819,2)) -> 15 | G819: =COUNTIF(Data_Eksportir!$H$2:$H$3401,A819) -> 0 | H819: =IF(E819="","Tanpa data berat",IF(E819<1,"Di bawah 1",IF(E819<5,"1 – 5",IF(E819<20,"5 – 20",IF(E819<100,"20 – 100","100 ke atas"))))) -> 1 – 5 | I819: =IF(D819<p_nilai_besar,"Di bawah ambang nilai",IF(G819=0,"Belum terwakili",IF(G819<=p_listing_rendah,"Keterwakilan rendah","Terwakili"))) -> Di bawah ambang nilai | J819: =D819+ROW()/10^6 -> 2432286 | K819: =IF(D819>=p_nilai_besar,D819/(1+G819),0) -> 0 | L819: =IF(K819>0,K819+ROW()/10^6,0) -> 0
